Workbook

Sheet README
A1: Random versus spatial cross-validation in machine-learning environmental maps: database of the systematic review and meta-analysis
A2: Vilca-Solorzano, R.A. & Torres-Cruz, F. Universidad Nacional del Altiplano, Puno, Peru. Data: https://doi.org/10.17605/OSF.IO/S8Y5H · Protocol: https://doi.org/10.17605/OSF.IO/6P8YM
A4: Sheet | B4: Type | C4: Content
A5: S1_Validation_practice | B5: Summary | C5: Summary tables (formulas): validation schemes, folds, splits, block-size choice, sampling design, data source.
A6: S2_Countries | B6: Summary | C6: Summary table (formulas): studies per country and continent, ranked.
A7: S3_When_to_use | B7: Summary | C7: Summary table (linked formulas): size of the gap per situation and which validation to use.
A8: 1_Screening | B8: Raw | C8: All 3,227 records screened on title and abstract, with decision and reason (raw).
A9: 2_Full_text | B9: Raw | C9: 390 full texts assessed (+2 not retrieved): include (266) or exclude with reason E1-E6 (raw).
A10: 3_Extraction_raw | B10: Raw | C10: Every extracted row (model x metric x data set) of the included studies, values as reported (raw).
A11: 4_Studies | B11: Raw | C11: One row per included study (266): country, data source, sampling design and validation schemes (raw, second pass).
A12: 5_Effect_sizes | B12: Processed | C12: Effect sizes used in the meta-analysis (processed): yi = random minus spatial (lnRR for RMSE), vi = sampling variance.
A13: 6_Pooled | B13: Processed | C13: Pooled three-level random-effects estimates per metric, with sensitivity analyses (processed).
A14: 7_Moderators | B14: Processed | C14: Subgroup estimates by sampling design, model, domain and spatial-CV type (processed).
A15: 8_Study_moderators | B15: Processed | C15: Subgroup estimates by study-level variables: data source, random-CV scheme, block-size justification, n, continent (processed).
... A20: 12_Risk_of_bias | B20: Processed | C20: Risk-of-bias and reporting items per study (PROBAST-based).
A22: Codes. yi > 0 means random cross-validation gave the more favourable value. lnRR = ln(RMSE spatial / RMSE random); % higher = 100*(exp(lnRR)-1).
A23: sampling_h: clustered, regular_grid, probability_random, unknown (not reported). Rows in 3_Extraction_raw with primary = yes were analysed.
A24: Raw sheets are as extracted; processed sheets are outputs of analysis/01, 04 and 07 (R, metafor). Summary sheets use COUNTIF/INDEX formulas and update when the data change.
A25: Abstracts and full texts are not included (copyright).

Sheet S1_Validation_practice
A1: Which validation designs are used, and on what data (counts recalculate from sheet 4_Studies)
A3: Random cross-validation used as baseline
A4: Level | B4: Studies | C4: % of 266
A5: k-fold | B5: =COUNTIF('4_Studies'!$U$2:$U$267,"kfold") -> 115 | C5: =B5/COUNTA('4_Studies'!$A$2:$A$267) -> 0.43233083
A6: Repeated k-fold | B6: =COUNTIF('4_Studies'!$U$2:$U$267,"repeated_kfold") -> 27 | C6: =B6/COUNTA('4_Studies'!$A$2:$A$267) -> 0.10150376
A7: Nested k-fold | B7: =COUNTIF('4_Studies'!$U$2:$U$267,"nested_kfold") -> 7 | C7: =B7/COUNTA('4_Studies'!$A$2:$A$267) -> 0.026315789
A8: Hold-out split | B8: =COUNTIF('4_Studies'!$U$2:$U$267,"holdout_split") -> 103 | C8: =B8/COUNTA('4_Studies'!$A$2:$A$267) -> 0.38721805
A9: Leave-one-out | B9: =COUNTIF('4_Studies'!$U$2:$U$267,"LOO") -> 6 | C9: =B9/COUNTA('4_Studies'!$A$2:$A$267) -> 0.022556391
A10: Out-of-bag | B10: =COUNTIF('4_Studies'!$U$2:$U$267,"OOB") -> 6 | C10: =B10/COUNTA('4_Studies'!$A$2:$A$267) -> 0.022556391
A11: Other | B11: =COUNTIF('4_Studies'!$U$2:$U$267,"other") -> 2 | C11: =B11/COUNTA('4_Studies'!$A$2:$A$267) -> 0.007518797
A13: Number of folds (k-fold studies)
A14: Level | B14: Studies | C14: % of 266
A15: 5-fold | B15: =COUNTIF('4_Studies'!$V$2:$V$267,"5") -> 64 | C15: =B15/COUNTA('4_Studies'!$A$2:$A$267) -> 0.2406015
A16: 10-fold | B16: =COUNTIF('4_Studies'!$V$2:$V$267,"10") -> 71 | C16: =B16/COUNTA('4_Studies'!$A$2:$A$267) -> 0.26691729
A17: 4-fold | B17: =COUNTIF('4_Studies'!$V$2:$V$267,"4") -> 4 | C17: =B17/COUNTA('4_Studies'!$A$2:$A$267) -> 0.015037594
A18: 15-fold | B18: =COUNTIF('4_Studies'!$V$2:$V$267,"15") -> 3 | C18: =B18/COUNTA('4_Studies'!$A$2:$A$267) -> 0.011278195
A20: Hold-out split (training %)
A21: Level | B21: Studies | C21: % of 266
A22: 80/20 | B22: =COUNTIF('4_Studies'!$X$2:$X$267,"80") -> 42 | C22: =B22/COUNTA('4_Studies'!$A$2:$A$267) -> 0.15789474
A23: 70/30 | B23: =COUNTIF('4_Studies'!$X$2:$X$267,"70") -> 41 | C23: =B23/COUNTA('4_Studies'!$A$2:$A$267) -> 0.15413534
A24: 75/25 | B24: =COUNTIF('4_Studies'!$X$2:$X$267,"75") -> 13 | C24: =B24/COUNTA('4_Studies'!$A$2:$A$267) -> 0.04887218
A25: 60/40 | B25: =COUNTIF('4_Studies'!$X$2:$X$267,"60") -> 11 | C25: =B25/COUNTA('4_Studies'!$A$2:$A$267) -> 0.041353383
A26: 90/10 | B26: =COUNTIF('4_Studies'!$X$2:$X$267,"90") -> 4 | C26: =B26/COUNTA('4_Studies'!$A$2:$A$267) -> 0.015037594
A28: Stratified random folds
A29: Level | B29: Studies | C29: % of 266
A30: yes | B30: =COUNTIF('4_Studies'!$Z$2:$Z$267,"yes") -> 56 | C30: =B30/COUNTA('4_Studies'!$A$2:$A$267) -> 0.21052632
A31: no | B31: =COUNTIF('4_Studies'!$Z$2:$Z$267,"no") -> 158 | C31: =B31/COUNTA('4_Studies'!$A$2:$A$267) -> 0.59398496
A33: Spatial cross-validation used
A34: Level | B34: Studies | C34: % of 266
A35: Leave-location-out | B35: =COUNTIF('4_Studies'!$AA$2:$AA$267,"leave_location_out") -> 111 | C35: =B35/COUNTA('4_Studies'!$A$2:$A$267) -> 0.41729323
A36: Spatial blocks | B36: =COUNTIF('4_Studies'!$AA$2:$AA$267,"blocks") -> 79 | C36: =B36/COUNTA('4_Studies'!$A$2:$A$267) -> 0.29699248
A37: k-means clusters | B37: =COUNTIF('4_Studies'!$AA$2:$AA$267,"kmeans_clusters") -> 39 | C37: =B37/COUNTA('4_Studies'!$A$2:$A$267) -> 0.14661654
A38: Buffered leave-one-out | B38: =COUNTIF('4_Studies'!$AA$2:$AA$267,"buffered_LOO") -> 10 | C38: =B38/COUNTA('4_Studies'!$A$2:$A$267) -> 0.037593985
A39: NNDM / kNNDM | B39: =COUNTIF('4_Studies'!$AA$2:$AA$267,"NNDM_kNNDM") -> 3 | C39: =B39/COUNTA('4_Studies'!$A$2:$A$267) -> 0.011278195
A40: Other | B40: =COUNTIF('4_Studies'!$AA$2:$AA$267,"other") -> 24 | C40: =B40/COUNTA('4_Studies'!$A$2:$A$267) -> 0.090225564
A42: How the block or buffer size was chosen
A43: Level | B43: Studies | C43: % of 266
A44: From the autocorrelation range | B44: =COUNTIF('4_Studies'!$AE$2:$AE$267,"autocorrelation_range") -> 26 | C44: =B44/COUNTA('4_Studies'!$A$2:$A$267) -> 0.097744361
A45: Expert choice | B45: =COUNTIF('4_Studies'!$AE$2:$AE$267,"expert_choice") -> 63 | C45: =B45/COUNTA('4_Studies'!$A$2:$A$267) -> 0.23684211
A46: Not justified | B46: =COUNTIF('4_Studies'!$AE$2:$AE$267,"not_justified") -> 154 | C46: =B46/COUNTA('4_Studies'!$A$2:$A$267) -> 0.57894737
A48: Sampling design of the data
A49: Level | B49: Studies | C49: % of 266
A50: Clustered | B50: =COUNTIF('4_Studies'!$AJ$2:$AJ$267,"clustered") -> 148 | C50: =B50/COUNTA('4_Studies'!$A$2:$A$267) -> 0.55639098
A51: Regular grid | B51: =COUNTIF('4_Studies'!$AJ$2:$AJ$267,"regular_grid") -> 31 | C51: =B51/COUNTA('4_Studies'!$A$2:$A$267) -> 0.11654135
A52: Probability sample | B52: =COUNTIF('4_Studies'!$AJ$2:$AJ$267,"probability_random") -> 19 | C52: =B52/COUNTA('4_Studies'!$A$2:$A$267) -> 0.071428571
A53: Not reported | B53: =COUNTIF('4_Studies'!$AJ$2:$AJ$267,"unknown") -> 68 | C53: =B53/COUNTA('4_Studies'!$A$2:$A$267) -> 0.2556391
A55: Source of the response data
A56: Level | B56: Studies | C56: % of 266
A57: Field samples | B57: =COUNTIF('4_Studies'!$K$2:$K$267,"in_situ_samples") -> 68 | C57: =B57/COUNTA('4_Studies'!$A$2:$A$267) -> 0.2556391
A58: Labels from imagery | B58: =COUNTIF('4_Studies'!$K$2:$K$267,"remote_sensing_labels") -> 49 | C58: =B58/COUNTA('4_Studies'!$A$2:$A$267) -> 0.18421053
A59: Monitoring stations | B59: =COUNTIF('4_Studies'!$K$2:$K$267,"monitoring_stations") -> 41 | C59: =B59/COUNTA('4_Studies'!$A$2:$A$267) -> 0.15413534
A60: Surveys / inventories | B60: =COUNTIF('4_Studies'!$K$2:$K$267,"survey_inventory") -> 33 | C60: =B60/COUNTA('4_Studies'!$A$2:$A$267) -> 0.12406015
A61: Gridded products | B61: =COUNTIF('4_Studies'!$K$2:$K$267,"gridded_product") -> 24 | C61: =B61/COUNTA('4_Studies'!$A$2:$A$267) -> 0.090225564
A62: Compiled databases | B62: =COUNTIF('4_Studies'!$K$2:$K$267,"compiled_database") -> 19 | C62: =B62/COUNTA('4_Studies'!$A$2:$A$267) -> 0.071428571
A63: Species occurrences | B63: =COUNTIF('4_Studies'!$K$2:$K$267,"occurrence_records") -> 12 | C63: =B63/COUNTA('4_Studies'!$A$2:$A$267) -> 0.045112782
A64: Mixed | B64: =COUNTIF('4_Studies'!$K$2:$K$267,"mixed") -> 14 | C64: =B64/COUNTA('4_Studies'!$A$2:$A$267) -> 0.052631579
A65: Simulated | B65: =COUNTIF('4_Studies'!$K$2:$K$267,"simulated") -> 6 | C65: =B65/COUNTA('4_Studies'!$A$2:$A$267) -> 0.022556391
A67: Data geometry
A68: Level | B68: Studies | C68: % of 266
A69: points | B69: =COUNTIF('4_Studies'!$L$2:$L$267,"points") -> 168 | C69: =B69/COUNTA('4_Studies'!$A$2:$A$267) -> 0.63157895
A70: raster_pixels | B70: =COUNTIF('4_Studies'!$L$2:$L$267,"raster_pixels") -> 55 | C70: =B70/COUNTA('4_Studies'!$A$2:$A$267) -> 0.20676692
A71: polygons | B71: =COUNTIF('4_Studies'!$L$2:$L$267,"polygons") -> 38 | C71: =B71/COUNTA('4_Studies'!$A$2:$A$267) -> 0.14285714
A72: mixed | B72: =COUNTIF('4_Studies'!$L$2:$L$267,"mixed") -> 5 | C72: =B72/COUNTA('4_Studies'!$A$2:$A$267) -> 0.018796992
A74: Task
A75: Level | B75: Studies | C75: % of 266
A76: regression | B76: =COUNTIF('4_Studies'!$R$2:$R$267,"regression") -> 161 | C76: =B76/COUNTA('4_Studies'!$A$2:$A$267) -> 0.60526316
A77: classification | B77: =COUNTIF('4_Studies'!$R$2:$R$267,"classification") -> 100 | C77: =B77/COUNTA('4_Studies'!$A$2:$A$267) -> 0.37593985
A78: both | B78: =COUNTIF('4_Studies'!$R$2:$R$267,"both") -> 5 | C78: =B78/COUNTA('4_Studies'!$A$2:$A$267) -> 0.018796992
A80: Independent test reported
A81: Level | B81: Studies | C81: % of 266
A82: none | B82: =COUNTIF('4_Studies'!$AG$2:$AG$267,"none") -> 181 | C82: =B82/COUNTA('4_Studies'!$A$2:$A$267) -> 0.68045113
A83: separate_holdout | B83: =COUNTIF('4_Studies'!$AG$2:$AG$267,"separate_holdout") -> 31 | C83: =B83/COUNTA('4_Studies'!$A$2:$A$267) -> 0.11654135
A84: later_period | B84: =COUNTIF('4_Studies'!$AG$2:$AG$267,"later_period") -> 22 | C84: =B84/COUNTA('4_Studies'!$A$2:$A$267) -> 0.082706767
A85: other_region | B85: =COUNTIF('4_Studies'!$AG$2:$AG$267,"other_region") -> 17 | C85: =B85/COUNTA('4_Studies'!$A$2:$A$267) -> 0.063909774
A86: probability_sample | B86: =COUNTIF('4_Studies'!$AG$2:$AG$267,"probability_sample") -> 5 | C86: =B86/COUNTA('4_Studies'!$A$2:$A$267) -> 0.018796992
A87: other | B87: =COUNTIF('4_Studies'!$AG$2:$AG$267,"other") -> 10 | C87: =B87/COUNTA('4_Studies'!$A$2:$A$267) -> 0.037593985

Sheet S2_Countries
A1: Where the studies were carried out (counts recalculate from sheet 4_Studies; multi-country studies count once per country)
A3: Rank | B3: ISO3 | C3: Country | D3: Continent | E3: Studies | F3: % of 266
A4: =RANK(E4,$E$4:$E$89) -> 1 | B4: CHN | C4: China | D4: Asia | E4: =COUNTIF('4_Studies'!$F$2:$F$267,"*CHN*") -> 54 | F4: =E4/COUNTA('4_Studies'!$A$2:$A$267) -> 0.20300752
A5: =RANK(E5,$E$4:$E$89) -> 2 | B5: USA | C5: United States | D5: North America | E5: =COUNTIF('4_Studies'!$F$2:$F$267,"*USA*") -> 42 | F5: =E5/COUNTA('4_Studies'!$A$2:$A$267) -> 0.15789474
A6: =RANK(E6,$E$4:$E$89) -> 3 | B6: CAN | C6: Canada | D6: North America | E6: =COUNTIF('4_Studies'!$F$2:$F$267,"*CAN*") -> 12 | F6: =E6/COUNTA('4_Studies'!$A$2:$A$267) -> 0.045112782
A7: =RANK(E7,$E$4:$E$89) -> 3 | B7: DEU | C7: Germany | D7: Europe | E7: =COUNTIF('4_Studies'!$F$2:$F$267,"*DEU*") -> 12 | F7: =E7/COUNTA('4_Studies'!$A$2:$A$267) -> 0.045112782
A8: =RANK(E8,$E$4:$E$89) -> 5 | B8: AUS | C8: Australia | D8: Oceania | E8: =COUNTIF('4_Studies'!$F$2:$F$267,"*AUS*") -> 11 | F8: =E8/COUNTA('4_Studies'!$A$2:$A$267) -> 0.041353383
A9: =RANK(E9,$E$4:$E$89) -> 5 | B9: BRA | C9: Brazil | D9: South America | E9: =COUNTIF('4_Studies'!$F$2:$F$267,"*BRA*") -> 11 | F9: =E9/COUNTA('4_Studies'!$A$2:$A$267) -> 0.041353383
A10: =RANK(E10,$E$4:$E$89) -> 7 | B10: ESP | C10: Spain | D10: Europe | E10: =COUNTIF('4_Studies'!$F$2:$F$267,"*ESP*") -> 10 | F10: =E10/COUNTA('4_Studies'!$A$2:$A$267) -> 0.037593985
A11: =RANK(E11,$E$4:$E$89) -> 8 | B11: FRA | C11: France | D11: Europe | E11: =COUNTIF('4_Studies'!$F$2:$F$267,"*FRA*") -> 8 | F11: =E11/COUNTA('4_Studies'!$A$2:$A$267) -> 0.030075188
A12: =RANK(E12,$E$4:$E$89) -> 9 | B12: IND | C12: India | D12: Asia | E12: =COUNTIF('4_Studies'!$F$2:$F$267,"*IND*") -> 5 | F12: =E12/COUNTA('4_Studies'!$A$2:$A$267) -> 0.018796992
A13: =RANK(E13,$E$4:$E$89) -> 9 | B13: PER | C13: Peru | D13: South America | E13: =COUNTIF('4_Studies'!$F$2:$F$267,"*PER*") -> 5 | F13: =E13/COUNTA('4_Studies'!$A$2:$A$267) -> 0.018796992
A14: =RANK(E14,$E$4:$E$89) -> 11 | B14: AUT | C14: Austria | D14: Europe | E14: =COUNTIF('4_Studies'!$F$2:$F$267,"*AUT*") -> 4 | F14: =E14/COUNTA('4_Studies'!$A$2:$A$267) -> 0.015037594
A15: =RANK(E15,$E$4:$E$89) -> 11 | B15: IDN | C15: Indonesia | D15: Asia | E15: =COUNTIF('4_Studies'!$F$2:$F$267,"*IDN*") -> 4 | F15: =E15/COUNTA('4_Studies'!$A$2:$A$267) -> 0.015037594
A16: =RANK(E16,$E$4:$E$89) -> 11 | B16: JPN | C16: Japan | D16: Asia | E16: =COUNTIF('4_Studies'!$F$2:$F$267,"*JPN*") -> 4 | F16: =E16/COUNTA('4_Studies'!$A$2:$A$267) -> 0.015037594
A17: =RANK(E17,$E$4:$E$89) -> 11 | B17: TWN | C17: Taiwan | D17: Asia | E17: =COUNTIF('4_Studies'!$F$2:$F$267,"*TWN*") -> 4 | F17: =E17/COUNTA('4_Studies'!$A$2:$A$267) -> 0.015037594
A18: =RANK(E18,$E$4:$E$89) -> 11 | B18: VNM | C18: Vietnam | D18: Asia | E18: =COUNTIF('4_Studies'!$F$2:$F$267,"*VNM*") -> 4 | F18: =E18/COUNTA('4_Studies'!$A$2:$A$267) -> 0.015037594
A19: =RANK(E19,$E$4:$E$89) -> 16 | B19: BFA | C19: Burkina Faso | D19: Africa | E19: =COUNTIF('4_Studies'!$F$2:$F$267,"*BFA*") -> 3 | F19: =E19/COUNTA('4_Studies'!$A$2:$A$267) -> 0.011278195
A20: =RANK(E20,$E$4:$E$89) -> 16 | B20: ETH | C20: Ethiopia | D20: Africa | E20: =COUNTIF('4_Studies'!$F$2:$F$267,"*ETH*") -> 3 | F20: =E20/COUNTA('4_Studies'!$A$2:$A$267) -> 0.011278195
A21: =RANK(E21,$E$4:$E$89) -> 16 | B21: GBR | C21: United Kingdom | D21: Europe | E21: =COUNTIF('4_Studies'!$F$2:$F$267,"*GBR*") -> 3 | F21: =E21/COUNTA('4_Studies'!$A$2:$A$267) -> 0.011278195
A22: =RANK(E22,$E$4:$E$89) -> 16 | B22: ITA | C22: Italy | D22: Europe | E22: =COUNTIF('4_Studies'!$F$2:$F$267,"*ITA*") -> 3 | F22: =E22/COUNTA('4_Studies'!$A$2:$A$267) -> 0.011278195
A23: =RANK(E23,$E$4:$E$89) -> 16 | B23: KOR | C23: South Korea | D23: Asia | E23: =COUNTIF('4_Studies'!$F$2:$F$267,"*KOR*") -> 3 | F23: =E23/COUNTA('4_Studies'!$A$2:$A$267) -> 0.011278195
A24: =RANK(E24,$E$4:$E$89) -> 16 | B24: MAR | C24: Morocco | D24: Africa | E24: =COUNTIF('4_Studies'!$F$2:$F$267,"*MAR*") -> 3 | F24: =E24/COUNTA('4_Studies'!$A$2:$A$267) -> 0.011278195
A25: =RANK(E25,$E$4:$E$89) -> 16 | B25: NLD | C25: Netherlands | D25: Europe | E25: =COUNTIF('4_Studies'!$F$2:$F$267,"*NLD*") -> 3 | F25: =E25/COUNTA('4_Studies'!$A$2:$A$267) -> 0.011278195
A26: =RANK(E26,$E$4:$E$89) -> 16 | B26: PRT | C26: Portugal | D26: Europe | E26: =COUNTIF('4_Studies'!$F$2:$F$267,"*PRT*") -> 3 | F26: =E26/COUNTA('4_Studies'!$A$2:$A$267) -> 0.011278195
A27: =RANK(E27,$E$4:$E$89) -> 16 | B27: SWE | C27: Sweden | D27: Europe | E27: =COUNTIF('4_Studies'!$F$2:$F$267,"*SWE*") -> 3 | F27: =E27/COUNTA('4_Studies'!$A$2:$A$267) -> 0.011278195
A28: =RANK(E28,$E$4:$E$89) -> 16 | B28: THA | C28: Thailand | D28: Asia | E28: =COUNTIF('4_Studies'!$F$2:$F$267,"*THA*") -> 3 | F28: =E28/COUNTA('4_Studies'!$A$2:$A$267) -> 0.011278195
A29: =RANK(E29,$E$4:$E$89) -> 26 | B29: ARG | C29: Argentina | D29: South America | E29: =COUNTIF('4_Studies'!$F$2:$F$267,"*ARG*") -> 2 | F29: =E29/COUNTA('4_Studies'!$A$2:$A$267) -> 0.007518797
A30: =RANK(E30,$E$4:$E$89) -> 26 | B30: ATA | C30: Antarctica | D30: Antarctica | E30: =COUNTIF('4_Studies'!$F$2:$F$267,"*ATA*") -> 2 | F30: =E30/COUNTA('4_Studies'!$A$2:$A$267) -> 0.007518797
A31: =RANK(E31,$E$4:$E$89) -> 26 | B31: BGR | C31: Bulgaria | D31: Europe | E31: =COUNTIF('4_Studies'!$F$2:$F$267,"*BGR*") -> 2 | F31: =E31/COUNTA('4_Studies'!$A$2:$A$267) -> 0.007518797
A32: =RANK(E32,$E$4:$E$89) -> 26 | B32: BOL | C32: Bolivia | D32: South America | E32: =COUNTIF('4_Studies'!$F$2:$F$267,"*BOL*") -> 2 | F32: =E32/COUNTA('4_Studies'!$A$2:$A$267) -> 0.007518797
A33: =RANK(E33,$E$4:$E$89) -> 26 | B33: CHE | C33: Switzerland | D33: Europe | E33: =COUNTIF('4_Studies'!$F$2:$F$267,"*CHE*") -> 2 | F33: =E33/COUNTA('4_Studies'!$A$2:$A$267) -> 0.007518797
A34: =RANK(E34,$E$4:$E$89) -> 26 | B34: CHL | C34: Chile | D34: South America | E34: =COUNTIF('4_Studies'!$F$2:$F$267,"*CHL*") -> 2 | F34: =E34/COUNTA('4_Studies'!$A$2:$A$267) -> 0.007518797
A35: =RANK(E35,$E$4:$E$89) -> 26 | B35: CMR | C35: Cameroon | D35: Africa | E35: =COUNTIF('4_Studies'!$F$2:$F$267,"*CMR*") -> 2 | F35: =E35/COUNTA('4_Studies'!$A$2:$A$267) -> 0.007518797
A36: =RANK(E36,$E$4:$E$89) -> 26 | B36: CZE | C36: Czechia | D36: Europe | E36: =COUNTIF('4_Studies'!$F$2:$F$267,"*CZE*") -> 2 | F36: =E36/COUNTA('4_Studies'!$A$2:$A$267) -> 0.007518797
A37: =RANK(E37,$E$4:$E$89) -> 26 | B37: DNK | C37: Denmark | D37: Europe | E37: =COUNTIF('4_Studies'!$F$2:$F$267,"*DNK*") -> 2 | F37: =E37/COUNTA('4_Studies'!$A$2:$A$267) -> 0.007518797
A38: =RANK(E38,$E$4:$E$89) -> 26 | B38: ECU | C38: Ecuador | D38: South America | E38: =COUNTIF('4_Studies'!$F$2:$F$267,"*ECU*") -> 2 | F38: =E38/COUNTA('4_Studies'!$A$2:$A$267) -> 0.007518797
A39: =RANK(E39,$E$4:$E$89) -> 26 | B39: EGY | C39: Egypt | D39: Africa | E39: =COUNTIF('4_Studies'!$F$2:$F$267,"*EGY*") -> 2 | F39: =E39/COUNTA('4_Studies'!$A$2:$A$267) -> 0.007518797
A40: =RANK(E40,$E$4:$E$89) -> 26 | B40: GHA | C40: Ghana | D40: Africa | E40: =COUNTIF('4_Studies'!$F$2:$F$267,"*GHA*") -> 2 | F40: =E40/COUNTA('4_Studies'!$A$2:$A$267) -> 0.007518797
A41: =RANK(E41,$E$4:$E$89) -> 26 | B41: HRV | C41: Croatia | D41: Europe | E41: =COUNTIF('4_Studies'!$F$2:$F$267,"*HRV*") -> 2 | F41: =E41/COUNTA('4_Studies'!$A$2:$A$267) -> 0.007518797
A42: =RANK(E42,$E$4:$E$89) -> 26 | B42: HUN | C42: Hungary | D42: Europe | E42: =COUNTIF('4_Studies'!$F$2:$F$267,"*HUN*") -> 2 | F42: =E42/COUNTA('4_Studies'!$A$2:$A$267) -> 0.007518797
A43: =RANK(E43,$E$4:$E$89) -> 26 | B43: IRN | C43: Iran | D43: Asia | E43: =COUNTIF('4_Studies'!$F$2:$F$267,"*IRN*") -> 2 | F43: =E43/COUNTA('4_Studies'!$A$2:$A$267) -> 0.007518797
A44: =RANK(E44,$E$4:$E$89) -> 26 | B44: LTU | C44: Lithuania | D44: Europe | E44: =COUNTIF('4_Studies'!$F$2:$F$267,"*LTU*") -> 2 | F44: =E44/COUNTA('4_Studies'!$A$2:$A$267) -> 0.007518797
A45: =RANK(E45,$E$4:$E$89) -> 26 | B45: MEX | C45: Mexico | D45: North America | E45: =COUNTIF('4_Studies'!$F$2:$F$267,"*MEX*") -> 2 | F45: =E45/COUNTA('4_Studies'!$A$2:$A$267) -> 0.007518797
A46: =RANK(E46,$E$4:$E$89) -> 26 | B46: MNG | C46: Mongolia | D46: Asia | E46: =COUNTIF('4_Studies'!$F$2:$F$267,"*MNG*") -> 2 | F46: =E46/COUNTA('4_Studies'!$A$2:$A$267) -> 0.007518797
A47: =RANK(E47,$E$4:$E$89) -> 26 | B47: MYS | C47: Malaysia | D47: Asia | E47: =COUNTIF('4_Studies'!$F$2:$F$267,"*MYS*") -> 2 | F47: =E47/COUNTA('4_Studies'!$A$2:$A$267) -> 0.007518797
A48: =RANK(E48,$E$4:$E$89) -> 26 | B48: NAM | C48: Namibia | D48: Africa | E48: =COUNTIF('4_Studies'!$F$2:$F$267,"*NAM*") -> 2 | F48: =E48/COUNTA('4_Studies'!$A$2:$A$267) -> 0.007518797
A49: =RANK(E49,$E$4:$E$89) -> 26 | B49: NOR | C49: Norway | D49: Europe | E49: =COUNTIF('4_Studies'!$F$2:$F$267,"*NOR*") -> 2 | F49: =E49/COUNTA('4_Studies'!$A$2:$A$267) -> 0.007518797
A50: =RANK(E50,$E$4:$E$89) -> 26 | B50: NZL | C50: New Zealand | D50: Oceania | E50: =COUNTIF('4_Studies'!$F$2:$F$267,"*NZL*") -> 2 | F50: =E50/COUNTA('4_Studies'!$A$2:$A$267) -> 0.007518797
A51: =RANK(E51,$E$4:$E$89) -> 26 | B51: PAK | C51: Pakistan | D51: Asia | E51: =COUNTIF('4_Studies'!$F$2:$F$267,"*PAK*") -> 2 | F51: =E51/COUNTA('4_Studies'!$A$2:$A$267) -> 0.007518797
A52: =RANK(E52,$E$4:$E$89) -> 26 | B52: SAU | C52: Saudi Arabia | D52: Asia | E52: =COUNTIF('4_Studies'!$F$2:$F$267,"*SAU*") -> 2 | F52: =E52/COUNTA('4_Studies'!$A$2:$A$267) -> 0.007518797
A53: =RANK(E53,$E$4:$E$89) -> 26 | B53: SVN | C53: Slovenia | D53: Europe | E53: =COUNTIF('4_Studies'!$F$2:$F$267,"*SVN*") -> 2 | F53: =E53/COUNTA('4_Studies'!$A$2:$A$267) -> 0.007518797
A54: =RANK(E54,$E$4:$E$89) -> 51 | B54: AFG | C54: Afghanistan | D54: Asia | E54: =COUNTIF('4_Studies'!$F$2:$F$267,"*AFG*") -> 1 | F54: =E54/COUNTA('4_Studies'!$A$2:$A$267) -> 0.0037593985
A55: =RANK(E55,$E$4:$E$89) -> 51 | B55: BEL | C55: Belgium | D55: Europe | E55: =COUNTIF('4_Studies'!$F$2:$F$267,"*BEL*") -> 1 | F55: =E55/COUNTA('4_Studies'!$A$2:$A$267) -> 0.0037593985
A56: =RANK(E56,$E$4:$E$89) -> 51 | B56: BRN | C56: Brunei | D56: Asia | E56: =COUNTIF('4_Studies'!$F$2:$F$267,"*BRN*") -> 1 | F56: =E56/COUNTA('4_Studies'!$A$2:$A$267) -> 0.0037593985
A57: =RANK(E57,$E$4:$E$89) -> 51 | B57: CAF | C57: Central African Rep. | D57: Africa | E57: =COUNTIF('4_Studies'!$F$2:$F$267,"*CAF*") -> 1 | F57: =E57/COUNTA('4_Studies'!$A$2:$A$267) -> 0.0037593985
A58: =RANK(E58,$E$4:$E$89) -> 51 | B58: CIV | C58: Côte d'Ivoire | D58: Africa | E58: =COUNTIF('4_Studies'!$F$2:$F$267,"*CIV*") -> 1 | F58: =E58/COUNTA('4_Studies'!$A$2:$A$267) -> 0.0037593985
A59: =RANK(E59,$E$4:$E$89) -> 51 | B59: COD | C59: Dem. Rep. Congo | D59: Africa | E59: =COUNTIF('4_Studies'!$F$2:$F$267,"*COD*") -> 1 | F59: =E59/COUNTA('4_Studies'!$A$2:$A$267) -> 0.0037593985
A60: =RANK(E60,$E$4:$E$89) -> 51 | B60: COG | C60: Congo | D60: Africa | E60: =COUNTIF('4_Studies'!$F$2:$F$267,"*COG*") -> 1 | F60: =E60/COUNTA('4_Studies'!$A$2:$A$267) -> 0.0037593985
A61: =RANK(E61,$E$4:$E$89) -> 51 | B61: COL | C61: Colombia | D61: South America | E61: =COUNTIF('4_Studies'!$F$2:$F$267,"*COL*") -> 1 | F61: =E61/COUNTA('4_Studies'!$A$2:$A$267) -> 0.0037593985
A62: =RANK(E62,$E$4:$E$89) -> 51 | B62: CYP | C62: Cyprus | D62: Asia | E62: =COUNTIF('4_Studies'!$F$2:$F$267,"*CYP*") -> 1 | F62: =E62/COUNTA('4_Studies'!$A$2:$A$267) -> 0.0037593985
A63: =RANK(E63,$E$4:$E$89) -> 51 | B63: DZA | C63: Algeria | D63: Africa | E63: =COUNTIF('4_Studies'!$F$2:$F$267,"*DZA*") -> 1 | F63: =E63/COUNTA('4_Studies'!$A$2:$A$267) -> 0.0037593985
A64: =RANK(E64,$E$4:$E$89) -> 51 | B64: EST | C64: Estonia | D64: Europe | E64: =COUNTIF('4_Studies'!$F$2:$F$267,"*EST*") -> 1 | F64: =E64/COUNTA('4_Studies'!$A$2:$A$267) -> 0.0037593985
A65: =RANK(E65,$E$4:$E$89) -> 51 | B65: FIN | C65: Finland | D65: Europe | E65: =COUNTIF('4_Studies'!$F$2:$F$267,"*FIN*") -> 1 | F65: =E65/COUNTA('4_Studies'!$A$2:$A$267) -> 0.0037593985
A66: =RANK(E66,$E$4:$E$89) -> 51 | B66: GAB | C66: Gabon | D66: Africa | E66: =COUNTIF('4_Studies'!$F$2:$F$267,"*GAB*") -> 1 | F66: =E66/COUNTA('4_Studies'!$A$2:$A$267) -> 0.0037593985
A67: =RANK(E67,$E$4:$E$89) -> 51 | B67: GRC | C67: Greece | D67: Europe | E67: =COUNTIF('4_Studies'!$F$2:$F$267,"*GRC*") -> 1 | F67: =E67/COUNTA('4_Studies'!$A$2:$A$267) -> 0.0037593985
A68: =RANK(E68,$E$4:$E$89) -> 51 | B68: GRL | C68: Greenland | D68: North America | E68: =COUNTIF('4_Studies'!$F$2:$F$267,"*GRL*") -> 1 | F68: =E68/COUNTA('4_Studies'!$A$2:$A$267) -> 0.0037593985
A69: =RANK(E69,$E$4:$E$89) -> 51 | B69: HKG | C69: Hong Kong | E69: =COUNTIF('4_Studies'!$F$2:$F$267,"*HKG*") -> 1 | F69: =E69/COUNTA('4_Studies'!$A$2:$A$267) -> 0.0037593985
A70: =RANK(E70,$E$4:$E$89) -> 51 | B70: IRL | C70: Ireland | D70: Europe | E70: =COUNTIF('4_Studies'!$F$2:$F$267,"*IRL*") -> 1 | F70: =E70/COUNTA('4_Studies'!$A$2:$A$267) -> 0.0037593985
A71: =RANK(E71,$E$4:$E$89) -> 51 | B71: ISR | C71: Israel | D71: Asia | E71: =COUNTIF('4_Studies'!$F$2:$F$267,"*ISR*") -> 1 | F71: =E71/COUNTA('4_Studies'!$A$2:$A$267) -> 0.0037593985
A72: =RANK(E72,$E$4:$E$89) -> 51 | B72: KAZ | C72: Kazakhstan | D72: Asia | E72: =COUNTIF('4_Studies'!$F$2:$F$267,"*KAZ*") -> 1 | F72: =E72/COUNTA('4_Studies'!$A$2:$A$267) -> 0.0037593985
A73: =RANK(E73,$E$4:$E$89) -> 51 | B73: KEN | C73: Kenya | D73: Africa | E73: =COUNTIF('4_Studies'!$F$2:$F$267,"*KEN*") -> 1 | F73: =E73/COUNTA('4_Studies'!$A$2:$A$267) -> 0.0037593985
A74: =RANK(E74,$E$4:$E$89) -> 51 | B74: KHM | C74: Cambodia | D74: Asia | E74: =COUNTIF('4_Studies'!$F$2:$F$267,"*KHM*") -> 1 | F74: =E74/COUNTA('4_Studies'!$A$2:$A$267) -> 0.0037593985
A75: =RANK(E75,$E$4:$E$89) -> 51 | B75: LAO | C75: Laos | D75: Asia | E75: =COUNTIF('4_Studies'!$F$2:$F$267,"*LAO*") -> 1 | F75: =E75/COUNTA('4_Studies'!$A$2:$A$267) -> 0.0037593985
A76: =RANK(E76,$E$4:$E$89) -> 51 | B76: LUX | C76: Luxembourg | D76: Europe | E76: =COUNTIF('4_Studies'!$F$2:$F$267,"*LUX*") -> 1 | F76: =E76/COUNTA('4_Studies'!$A$2:$A$267) -> 0.0037593985
A77: =RANK(E77,$E$4:$E$89) -> 51 | B77: LVA | C77: Latvia | D77: Europe | E77: =COUNTIF('4_Studies'!$F$2:$F$267,"*LVA*") -> 1 | F77: =E77/COUNTA('4_Studies'!$A$2:$A$267) -> 0.0037593985
A78: =RANK(E78,$E$4:$E$89) -> 51 | B78: MLT | C78: Malta | E78: =COUNTIF('4_Studies'!$F$2:$F$267,"*MLT*") -> 1 | F78: =E78/COUNTA('4_Studies'!$A$2:$A$267) -> 0.0037593985
A79: =RANK(E79,$E$4:$E$89) -> 51 | B79: MMR | C79: Myanmar | D79: Asia | E79: =COUNTIF('4_Studies'!$F$2:$F$267,"*MMR*") -> 1 | F79: =E79/COUNTA('4_Studies'!$A$2:$A$267) -> 0.0037593985
A80: =RANK(E80,$E$4:$E$89) -> 51 | B80: NGA | C80: Nigeria | D80: Africa | E80: =COUNTIF('4_Studies'!$F$2:$F$267,"*NGA*") -> 1 | F80: =E80/COUNTA('4_Studies'!$A$2:$A$267) -> 0.0037593985
A81: =RANK(E81,$E$4:$E$89) -> 51 | B81: PHL | C81: Philippines | D81: Asia | E81: =COUNTIF('4_Studies'!$F$2:$F$267,"*PHL*") -> 1 | F81: =E81/COUNTA('4_Studies'!$A$2:$A$267) -> 0.0037593985
A82: =RANK(E82,$E$4:$E$89) -> 51 | B82: POL | C82: Poland | D82: Europe | E82: =COUNTIF('4_Studies'!$F$2:$F$267,"*POL*") -> 1 | F82: =E82/COUNTA('4_Studies'!$A$2:$A$267) -> 0.0037593985
A83: =RANK(E83,$E$4:$E$89) -> 51 | B83: PRI | C83: Puerto Rico | D83: North America | E83: =COUNTIF('4_Studies'!$F$2:$F$267,"*PRI*") -> 1 | F83: =E83/COUNTA('4_Studies'!$A$2:$A$267) -> 0.0037593985
A84: =RANK(E84,$E$4:$E$89) -> 51 | B84: ROU | C84: Romania | D84: Europe | E84: =COUNTIF('4_Studies'!$F$2:$F$267,"*ROU*") -> 1 | F84: =E84/COUNTA('4_Studies'!$A$2:$A$267) -> 0.0037593985
A85: =RANK(E85,$E$4:$E$89) -> 51 | B85: RUS | C85: Russia | D85: Europe | E85: =COUNTIF('4_Studies'!$F$2:$F$267,"*RUS*") -> 1 | F85: =E85/COUNTA('4_Studies'!$A$2:$A$267) -> 0.0037593985
A86: =RANK(E86,$E$4:$E$89) -> 51 | B86: SOM | C86: Somalia | D86: Africa | E86: =COUNTIF('4_Studies'!$F$2:$F$267,"*SOM*") -> 1 | F86: =E86/COUNTA('4_Studies'!$A$2:$A$267) -> 0.0037593985
A87: =RANK(E87,$E$4:$E$89) -> 51 | B87: SVK | C87: Slovakia | D87: Europe | E87: =COUNTIF('4_Studies'!$F$2:$F$267,"*SVK*") -> 1 | F87: =E87/COUNTA('4_Studies'!$A$2:$A$267) -> 0.0037593985
A88: =RANK(E88,$E$4:$E$89) -> 51 | B88: TUR | C88: Turkey | D88: Asia | E88: =COUNTIF('4_Studies'!$F$2:$F$267,"*TUR*") -> 1 | F88: =E88/COUNTA('4_Studies'!$A$2:$A$267) -> 0.0037593985
A89: =RANK(E89,$E$4:$E$89) -> 51 | B89: ZAF | C89: South Africa | D89: Africa | E89: =COUNTIF('4_Studies'!$F$2:$F$267,"*ZAF*") -> 1 | F89: =E89/COUNTA('4_Studies'!$A$2:$A$267) -> 0.0037593985
C90: Global or several continents | E90: =COUNTIF('4_Studies'!$F$2:$F$267,"*GLOBAL*")+COUNTIF('4_Studies'!$F$2:$F$267,"*MULTI*") -> 22
C91: Countries with at least one study | E91: =COUNTIF(E4:E89,">0") -> 86
A93: Continents
C94: Continent | E94: Studies | F94: % of 266
C95: Asia | E95: =COUNTIF('4_Studies'!$H$2:$H$267,"Asia") -> 88 | F95: =E95/COUNTA('4_Studies'!$A$2:$A$267) -> 0.33082707
C96: Europe | E96: =COUNTIF('4_Studies'!$H$2:$H$267,"Europe") -> 52 | F96: =E96/COUNTA('4_Studies'!$A$2:$A$267) -> 0.19548872
C97: North America | E97: =COUNTIF('4_Studies'!$H$2:$H$267,"North America") -> 52 | F97: =E97/COUNTA('4_Studies'!$A$2:$A$267) -> 0.19548872
C98: South America | E98: =COUNTIF('4_Studies'!$H$2:$H$267,"South America") -> 19 | F98: =E98/COUNTA('4_Studies'!$A$2:$A$267) -> 0.071428571
C99: Africa | E99: =COUNTIF('4_Studies'!$H$2:$H$267,"Africa") -> 17 | F99: =E99/COUNTA('4_Studies'!$A$2:$A$267) -> 0.063909774
C100: Oceania | E100: =COUNTIF('4_Studies'!$H$2:$H$267,"Oceania") -> 10 | F100: =E100/COUNTA('4_Studies'!$A$2:$A$267) -> 0.037593985
C101: Global | E101: =COUNTIF('4_Studies'!$H$2:$H$267,"Global") -> 13 | F101: =E101/COUNTA('4_Studies'!$A$2:$A$267) -> 0.04887218
C102: Multiple | E102: =COUNTIF('4_Studies'!$H$2:$H$267,"Multiple") -> 11 | F102: =E102/COUNTA('4_Studies'!$A$2:$A$267) -> 0.041353383
...

Sheet S3_When_to_use
A1: How large is the gap, and which validation to use (values linked to sheets 6, 7, 8 and 9)
A3: Situation | B3: R2 random minus spatial | C3: RMSE higher under spatial (%) | D3: Studies (R2) | E3: What to do
A4: All studies (pooled) | B4: ='6_Pooled'!D2 -> 0.20871274 | C4: =100*(EXP('6_Pooled'!D3)-1) -> 30.290372 | D4: ='6_Pooled'!C2 -> 132 | E4: Expect random CV to look better; report both designs.
A5: Clustered sample (roads, stations, plots) | B5: =INDEX('7_Moderators'!$E:$E,MATCH("dR2|sampling_h|clustered",'7_Moderators'!$A:$A,0)) -> 0.2359642 | C5: =100*(EXP(INDEX('7_Moderators'!$E:$E,MATCH("lnRR_RMSE|sampling_h|clustered",'7_Moderators'!$A:$A,0)))-1) -> 39.527077 | D5: =INDEX('7_Moderators'!$I:$I,MATCH("dR2|sampling_h|clustered",'7_Moderators'!$A:$A,0)) -> 77 | E5: Use spatial CV (blocks at least as wide as the autocorrelation range, or kNNDM); random CV is an upper bound.
A6: Regular grid | B6: =INDEX('7_Moderators'!$E:$E,MATCH("dR2|sampling_h|regular_grid",'7_Moderators'!$A:$A,0)) -> 0.22020918 | C6: =100*(EXP(INDEX('7_Moderators'!$E:$E,MATCH("lnRR_RMSE|sampling_h|regular_grid",'7_Moderators'!$A:$A,0)))-1) -> 16.851216 | D6: =INDEX('7_Moderators'!$I:$I,MATCH("dR2|sampling_h|regular_grid",'7_Moderators'!$A:$A,0)) -> 22 | E6: Report both; a moderate gap is expected.
A7: Sampling design not reported | B7: =INDEX('7_Moderators'!$E:$E,MATCH("dR2|sampling_h|unknown",'7_Moderators'!$A:$A,0)) -> 0.15578201 | C7: =100*(EXP(INDEX('7_Moderators'!$E:$E,MATCH("lnRR_RMSE|sampling_h|unknown",'7_Moderators'!$A:$A,0)))-1) -> 18.085275 | D7: =INDEX('7_Moderators'!$I:$I,MATCH("dR2|sampling_h|unknown",'7_Moderators'!$A:$A,0)) -> 30 | E7: Treat as clustered; describe how the data were collected.
A8: Probability sample of the mapped area | B8: =INDEX('7_Moderators'!$E:$E,MATCH("dR2|sampling_h|probability_random",'7_Moderators'!$A:$A,0)) -> 0.11619072 | C8: =100*(EXP(INDEX('7_Moderators'!$E:$E,MATCH("lnRR_RMSE|sampling_h|probability_random",'7_Moderators'!$A:$A,0)))-1) -> 11.83939 | D8: =INDEX('7_Moderators'!$I:$I,MATCH("dR2|sampling_h|probability_random",'7_Moderators'!$A:$A,0)) -> 9 | E8: Random CV is adequate for the accuracy of the whole map.
A9: Block size from the autocorrelation range | B9: =INDEX('8_Study_moderators'!$E:$E,MATCH("dR2|Block size justified by|autocorrelation_range",'8_Study_moderators'!$A:$A,0)) -> 0.40207396 | D9: =INDEX('8_Study_moderators'!$H:$H,MATCH("dR2|Block size justified by|autocorrelation_range",'8_Study_moderators'!$A:$A,0)) -> 9 | E9: Size blocks from the semivariogram range; the gap measured is then about 2.7 times larger.
A10: Block size not justified | B10: =INDEX('8_Study_moderators'!$E:$E,MATCH("dR2|Block size justified by|not_justified",'8_Study_moderators'!$A:$A,0)) -> 0.15149789 | D10: =INDEX('8_Study_moderators'!$H:$H,MATCH("dR2|Block size justified by|not_justified",'8_Study_moderators'!$A:$A,0)) -> 74 | E10: Gap is underestimated; justify the block size.
A11: Random baseline: leave-one-out / out-of-bag | B11: =INDEX('8_Study_moderators'!$E:$E,MATCH("dR2|Random-CV scheme|LOO/OOB",'8_Study_moderators'!$A:$A,0)) -> 0.38458686 | D11: =INDEX('8_Study_moderators'!$H:$H,MATCH("dR2|Random-CV scheme|LOO/OOB",'8_Study_moderators'!$A:$A,0)) -> 7 | E11: Most optimistic baseline; avoid as the reference.
A12: Random baseline: k-fold | B12: =INDEX('8_Study_moderators'!$E:$E,MATCH("dR2|Random-CV scheme|k-fold",'8_Study_moderators'!$A:$A,0)) -> 0.18351087 | D12: =INDEX('8_Study_moderators'!$H:$H,MATCH("dR2|Random-CV scheme|k-fold",'8_Study_moderators'!$A:$A,0)) -> 77 | E12: 5 or 10 folds give the same gap.
A13: Random baseline: hold-out split | B13: =INDEX('8_Study_moderators'!$E:$E,MATCH("dR2|Random-CV scheme|Hold-out split",'8_Study_moderators'!$A:$A,0)) -> 0.22719243 | D13: =INDEX('8_Study_moderators'!$H:$H,MATCH("dR2|Random-CV scheme|Hold-out split",'8_Study_moderators'!$A:$A,0)) -> 47 | E13: 70/30 and 80/20 give the same gap.
A15: Agreement with independent test data
A16: Quantity | B16: Mean | C16: 95% CI low | D16: 95% CI high | E16: p
A17: Optimism of random CV (R2, AUC, accuracy) | B17: ='11_Independent_summary'!C2 -> 0.15481129 | C17: ='11_Independent_summary'!D2 -> 0.073765741 | D17: ='11_Independent_summary'!E2 -> 0.23585684 | E17: ='11_Independent_summary'!F2 -> 0.00328981
A18: Optimism of spatial CV (R2, AUC, accuracy) | B18: ='11_Independent_summary'!C3 -> 0.025712903 | C18: ='11_Independent_summary'!D3 -> -0.03710933 | D18: ='11_Independent_summary'!E3 -> 0.088535137 | E18: ='11_Independent_summary'!F3 -> 0.35710749
A19: Share of comparisons where spatial CV was closer | B19: ='11_Independent_summary'!C5 -> 0.72580645
A21: Positive optimism: cross-validation estimate better than the independent test. Values recalculate if sheets 6-11 are updated.

Sheet 1_Screening
A1: record_id | B1: priority | C1: source_query | D1: Year | E1: Title | F1: Source title | G1: DOI | H1: EID | I1: ta_decision | J1: ta_reason
A2: R0001 | B2: A_both | C2: v1/v2 | D2: 2020 | E2: Spatial validation reveals poor predictive performance of large-scale ecological mapping models | F2: Nature Communications | G2: 10.1038/s41467-020-18321-y | H2: 2-s2.0-85090794111 | I2: include
A3: R0002 | B3: A_both | C3: v1/v2 | D3: 2019 | E3: Hyperparameter tuning and performance assessment of statistical and machine-learning algorithms using spatial data | F3: Ecological Modelling | G3: 10.1016/j.ecolmodel.2019.06.002 | H3: 2-s2.0-85067413523 | I3: include
A4: R0003 | B4: A_both | C4: v1/v2 | D4: 2018 | E4: Improving performance of spatio-temporal machine learning models using forward feature selection and target-oriented validation | F4: Environmental Modelling and Software | G4: 10.1016/j.envsoft.2017.12.001 | H4: 2-s2.0-85038035153 | I4: include
A5: R0004 | B5: A_both | C5: v1/v2 | D5: 2020 | E5: Testing whether ensemble modelling is advantageous for maximising predictive performance of species distribution models | F5: Ecography | G5: 10.1111/ecog.04890 | H5: 2-s2.0-85078760878 | I5: include
A6: R0005 | B6: A_both | C6: v1/v2 | D6: 2019 | E6: Importance of spatial predictor variable selection in machine learning applications – Moving from data reproduction to spatial prediction | F6: Ecological Modelling | G6: 10.1016/j.ecolmodel.2019.108815 | H6: 2-s2.0-85072071754 | I6: include
A7: R0006 | B7: A_both | C7: v1/v2 | D7: 2021 | E7: Assessing the reliability of species distribution projections in climate change research | F7: Diversity and Distributions | G7: 10.1111/ddi.13252 | H7: 2-s2.0-85101122718 | I7: include
A8: R0007 | B8: A_both | C8: v1/v2 | D8: 2021 | E8: Spatial cross-validation is not the right way to evaluate map accuracy | F8: Ecological Modelling | G8: 10.1016/j.ecolmodel.2021.109692 | H8: 2-s2.0-85112366164 | I8: include
A9: R0008 | B9: A_both | C9: v1/v2 | D9: 2020 | E9: Comparison of Machine Learning and Land Use Regression for fine scale spatiotemporal estimation of ambient air pollution: Modeling ozone concentrations across the contiguous United States | F9: Environment International | G9: 10.1016/j.envint.2020.105827 | H9: 2-s2.0-85086853689 | I9: maybe
A10: R0009 | B10: A_both | C10: v1/v2 | D10: 2022 | E10: Spatially autocorrelated training and validation samples inflate performance assessment of convolutional neural networks | F10: ISPRS Open Journal of Photogrammetry and Remote Sensing | G10: 10.1016/j.ophoto.2022.100018 | H10: 2-s2.0-85135896909 | I10: include
A11: R0010 | B11: A_both | C11: v1/v2 | D11: 2022 | E11: Fair train-test split in machine learning: Mitigating spatial autocorrelation for improved prediction accuracy | F11: Journal of Petroleum Science and Engineering | G11: 10.1016/j.petrol.2021.109885 | H11: 2-s2.0-85119406427 | I11: exclude | J11: E4
A12: R0011 | B12: A_both | C12: v1/v2 | D12: 2022 | E12: Nearest neighbour distance matching Leave-One-Out Cross-Validation for map validation | F12: Methods in Ecology and Evolution | G12: 10.1111/2041-210X.13851 | H12: 2-s2.0-85127570689 | I12: include
A13: R0012 | B13: A_both | C13: v1/v2 | D13: 2022 | E13: Dealing with clustered samples for assessing map accuracy by cross-validation | F13: Ecological Informatics | G13: 10.1016/j.ecoinf.2022.101665 | H13: 2-s2.0-85129503131 | I13: include
A14: R0013 | B14: A_both | C14: v1/v2 | D14: 2021 | E14: Global Prediction of Soil Saturated Hydraulic Conductivity Using Random Forest in a Covariate-Based GeoTransfer Function (CoGTF) Framework | F14: Journal of Advances in Modeling Earth Systems | G14: 10.1029/2020MS002242 | H14: 2-s2.0-85104950878 | I14: include
A15: R0014 | B15: A_both | C15: v1/v2 | D15: 2024 | E15: Corn Grain Yield Prediction Using UAV-Based High Spatiotemporal Resolution Imagery, Machine Learning, and Spatial Cross-Validation | F15: Remote Sensing | G15: 10.3390/rs16040683 | H15: 2-s2.0-85185711225 | I15: include
A16: R0015 | B16: A_both | C16: v1/v2 | D16: 2024 | E16: Random forest and spatial cross-validation performance in predicting species abundance distributions | F16: Environmental Systems Research | G16: 10.1186/s40068-024-00352-9 | H16: 2-s2.0-85197278197 | I16: include
A17: R0016 | B17: A_both | C17: v1/v2 | D17: 2025 | E17: Random Cross-Validation Produces Biased Assessment of Machine Learning Performance in Regional Landslide Susceptibility Prediction | F17: Remote Sensing | G17: 10.3390/rs17020213 | H17: 2-s2.0-85215798869 | I17: include
A18: R0017 | B18: A_both | C18: v1/v2 | D18: 2019 | E18: A spatially explicit comparison of quantitative and categorical modelling approaches for mapping seabed sediments using random forest | F18: Geosciences (Switzerland) | G18: 10.3390/geosciences9060254 | H18: 2-s2.0-85067996135 | I18: include
A19: R0018 | B19: A_both | C19: v1/v2 | D19: 2025 | E19: Choosing blocks for spatial cross-validation: lessons from a marine remote sensing case study | F19: Frontiers in Remote Sensing | G19: 10.3389/frsen.2025.1531097 | H19: 2-s2.0-105001675641 | I19: maybe
A20: R0019 | B20: A_both | C20: v1/v2 | D20: 2023 | E20: Examining the Spatially Varying Relationships between Landslide Susceptibility and Conditioning Factors Using a Geographical Random Forest Approach: A Case Study in Liangshan, China | F20: Remote Sensing | G20: 10.3390/rs15061513 | H20: 2-s2.0-85151976377 | I20: maybe
A21: R0020 | B21: A_both | C21: v1/v2 | D21: 2022 | E21: Predicting methane emission in Canadian Holstein dairy cattle using milk mid-infrared reflectance spectroscopy and other commonly available predictors via artificial neural networks | F21: Journal of Dairy Science | G21: 10.3168/jds.2021-21176 | H21: 2-s2.0-85137018329 | I21: exclude | J21: E4
A22: R0021 | B22: A_both | C22: v1/v2 | D22: 2018 | E22: Fire regimes at the arid fringe: A 16-year remote sensing perspective (2000–2016) on the controls of fire activity in Namibia from spatial predictive models | F22: Ecological Indicators | G22: 10.1016/j.ecolind.2018.04.022 | H22: 2-s2.0-85045706551 | I22: include
A23: R0022 | B23: A_both | C23: v1/v2 | D23: 2019 | E23: Broad-scale species distribution models applied to data-poor areas | F23: Progress in Oceanography | G23: 10.1016/j.pocean.2019.04.007 | H23: 2-s2.0-85065068292 | I23: include
A24: R0023 | B24: A_both | C24: v1/v2 | D24: 2023 | E24: Evaluation of computer vision for detecting agonistic behavior of pigs in a single-space feeding stall through blocked cross-validation strategies | F24: Computers and Electronics in Agriculture | G24: 10.1016/j.compag.2022.107520 | H24: 2-s2.0-85144014809 | I24: exclude | J24: E4
A25: R0024 | B25: A_both | C25: v1/v2 | D25: 2024 | E25: Improving spatial transferability of deep learning models for small-field crop yield prediction | F25: ISPRS Open Journal of Photogrammetry and Remote Sensing | G25: 10.1016/j.ophoto.2024.100064 | H25: 2-s2.0-85191008945 | I25: include
A26: R0025 | B26: A_both | C26: v1/v2 | D26: 2022 | E26: Assessing spatial transferability of a random forest metamodel for predicting drainage fraction | F26: Journal of Hydrology | G26: 10.1016/j.jhydrol.2022.128177 | H26: 2-s2.0-85134575492 | I26: include
A27: R0026 | B27: A_both | C27: v1/v2 | D27: 2021 | E27: Estimation and mapping of surface soil properties in the Caucasus Mountains, Azerbaijan using high-resolution remote sensing data | F27: Geoderma Regional | G27: 10.1016/j.geodrs.2021.e00411 | H27: 2-s2.0-85108591332 | I27: exclude | J27: E2
A28: R0027 | B28: A_both | C28: v1/v2 | D28: 2022 | E28: Spatiotemporal distribution of labeled data can bias the validation and selection of supervised learning algorithms: A marine remote sensing example | F28: ISPRS Journal of Photogrammetry and Remote Sensing | G28: 10.1016/j.isprsjprs.2022.02.023 | H28: 2-s2.0-85125871380 | I28: include
A29: R0028 | B29: A_both | C29: v1/v2 | D29: 2022 | E29: Identifying low-PM2.5 exposure commuting routes for cyclists through modeling with the random forest algorithm based on low-cost sensor measurements in three Asian cities | F29: Environmental Pollution | G29: 10.1016/j.envpol.2021.118597 | H29: 2-s2.0-85120416457 | I29: include
A30: R0029 | B30: A_both | C30: v1/v2 | D30: 2024 | E30: Cross-validation strategy for performance evaluation of machine learning algorithms in underwater acoustic target recognition | F30: Ocean Engineering | G30: 10.1016/j.oceaneng.2024.117236 | H30: 2-s2.0-85186371520 | I30: exclude | J30: E4
A31: R0030 | B31: A_both | C31: v1/v2 | D31: 2023 | E31: Evaluation of linear, nonlinear and ensemble machine learning models for landslide susceptibility assessment in southwest China | F31: Geocarto International | G31: 10.1080/10106049.2022.2152493 | H31: 2-s2.0-85143635131 | I31: exclude | J31: E2
A32: R0031 | B32: A_both | C32: v1/v2 | D32: 2025 | E32: A dissimilarity-adaptive cross-validation method for evaluating geospatial machine learning predictions with clustered samples | F32: Ecological Informatics | G32: 10.1016/j.ecoinf.2025.103287 | H32: 2-s2.0-105009502618 | I32: include
A33: R0032 | B33: A_both | C33: v1/v2 | D33: 2019 | E33: Statistical stability and spatial instability in mapping forest tree species by comparing 9 years of satellite image time series | F33: Remote Sensing | G33: 10.3390/rs11212512 | H33: 2-s2.0-85074657977 | I33: include
A34: R0033 | B34: A_both | C34: v1/v2 | D34: 2021 | E34: Importance of spatial autocorrelation in machine learning modeling of polymetallic nodules, model uncertainty and transferability at local scale | F34: Minerals | G34: 10.3390/min11111172 | H34: 2-s2.0-85117621165 | I34: exclude | J34: E4
A35: R0034 | B35: A_both | C35: v1/v2 | D35: 2024 | E35: Deep learning bias correction of GEMS tropospheric NO2: A comparative validation of NO2 from GEMS and TROPOMI using Pandora observations | F35: Environment International | G35: 10.1016/j.envint.2024.108818 | H35: 2-s2.0-85196035166 | I35: exclude | J35: E2
A36: R0035 | B36: A_both | C36: v1/v2 | D36: 2025 | E36: A Comparative Assessment of Regular and Spatial Cross-Validation in Subfield Machine Learning Prediction of Maize Yield from Sentinel-2 Phenology | F36: Eng | G36: 10.3390/eng6100270 | H36: 2-s2.0-105020012052 | I36: include
A37: R0036 | B37: A_both | C37: v1/v2 | D37: 2024 | E37: Toward an Operational Monitoring of Oak Dieback With Multispectral Satellite Time Series: A Case Study in Centre-Val De Loire Region of France | F37: IEEE Journal of Selected Topics in Applied Earth Observations and Remote Sensing | G37: 10.1109/JSTARS.2023.3332420 | H37: 2-s2.0-85177071887 | I37: include
A38: R0037 | B38: A_both | C38: v1/v2 | D38: 2025 | E38: Foundation for unbiased cross-validation of spatio-temporal models for Species Distribution Modeling | F38: Ecological Informatics | G38: 10.1016/j.ecoinf.2025.103521 | H38: 2-s2.0-105022288803 | I38: include
A39: R0038 | B39: A_both | C39: v1/v2 | D39: 2024 | E39: Benchmarking data handling strategies for landslide susceptibility modelingusing random forest workflows | F39: Artificial Intelligence in Geosciences | G39: 10.1016/j.aiig.2024.100093 | H39: 2-s2.0-85206855138 | I39: include
A40: R0039 | B40: A_both | C40: v1/v2 | D40: 2024 | E40: Modelling Europe-wide fine resolution daily ambient temperature for 2003–2020 using machine learning | F40: Science of the Total Environment | G40: 10.1016/j.scitotenv.2024.172454 | H40: 2-s2.0-85190717933 | I40: include
A41: R0040 | B41: A_both | C41: v1/v2 | D41: 2025 | E41: A temporal perspective on the reliability of wildfire hazard assessment based on machine learning and remote sensing data | F41: Earth Science Informatics | G41: 10.1007/s12145-024-01501-5 | H41: 2-s2.0-85211444278 | I41: exclude | J41: E2
A42: R0041 | B42: A_both | C42: v1/v2 | D42: 2023 | E42: A Comparative Analysis of Machine Learning Techniques for National Glacier Mapping: Evaluating Performance through Spatial Cross-Validation in Perú | F42: Water (Switzerland) | G42: 10.3390/w15244214 | H42: 2-s2.0-85180434790 | I42: include
A43: R0042 | B43: A_both | C43: v1/v2 | D43: 2024 | E43: Revealing the impact of spatial bias in survey design for habitat mapping: A tale of two sampling designs | F43: Remote Sensing Applications: Society and Environment | G43: 10.1016/j.rsase.2024.101327 | H43: 2-s2.0-85201915446 | I43: exclude | J43: E2
A44: R0043 | B44: A_both | C44: v1/v2 | D44: 2025 | E44: A multiscale and seasonal model for urban surface temperature prediction based on landscape, land use and spectral indices | F44: Sustainable Cities and Society | G44: 10.1016/j.scs.2025.106783 | H44: 2-s2.0-105014626637 | I44: include
A45: R0044 | B45: A_both | C45: v1/v2 | D45: 2024 | E45: A random forests-based hedonic price model accounting for spatial autocorrelation: A random forests-based hedonic price model accounting for..: E. Tepe | F45: Journal of Geographical Systems | G45: 10.1007/s10109-024-00449-w | H45: 2-s2.0-85208226706 | I45: exclude | J45: E4
A46: R0045 | B46: A_both | C46: v1/v2 | D46: 2026 | E46: A comparative analysis of empirical, machine learning, and deep learning models for water quality retrieval in Wenzhou Bay with sparse in situ measurements | F46: Journal of Hydrology: Regional Studies | G46: 10.1016/j.ejrh.2025.103101 | H46: 2-s2.0-105034593180 | I46: include
A47: R0046 | B47: A_both | C47: v1/v2 | D47: 2024 | E47: Learning With Location-Based Fairness: A Statistically-Robust Framework and Acceleration | F47: IEEE Transactions on Knowledge and Data Engineering | G47: 10.1109/TKDE.2024.3371460 | H47: 2-s2.0-85187400850 | I47: exclude | J47: E2
A48: R0047 | B48: A_both | C48: v1/v2 | D48: 2023 | E48: Three Common Machine Learning Algorithms Neither Enhance Prediction Accuracy Nor Reduce Spatial Autocorrelation in Residuals: An Analysis of Twenty-five Socioeconomic Data Sets | F48: Geographical Analysis | G48: 10.1111/gean.12351 | H48: 2-s2.0-85139721299 | I48: exclude | J48: E4
A49: R0048 | B49: A_both | C49: v1/v2 | D49: 2026 | E49: Lightweight Hybrid Deep Learning and Fuzzy-AHP Framework for Predictive Flood Susceptibility Mapping in the Ghaghara River Basin, India: A Data-Driven Approach for Enhanced Spatiotemporal Precision and Risk Prediction | F49: Earth Systems and Environment | G49: 10.1007/s41748-025-00970-y | H49: 2-s2.0-105027379543 | I49: exclude | J49: E2
A50: R0049 | B50: A_both | C50: v1/v2 | D50: 2025 | E50: Comparative Performance of Machine Learning Models for Landslide Susceptibility Assessment: Impact of Sampling Strategies in Highway Buffer Zone | F50: Applied Sciences (Switzerland) | G50: 10.3390/app15158416 | H50: 2-s2.0-105013342147 | I50: exclude | J50: E2
A51: R0050 | B51: A_both | C51: v1/v2 | D51: 2026 | E51: Comparative Analysis of Sinkhole Susceptibility Models Using Ensemble Machine Learning and Local Interpretable Model-Agnostic Explanations (LIME) | F51: Transactions in GIS | G51: 10.1111/tgis.70210 | H51: 2-s2.0-105030266092 | I51: exclude | J51: E2
A52: R0051 | B52: A_both | C52: v1/v2 | D52: 2026 | E52: GeoHybridGNN: A Hybrid Intelligent Mapping Framework for Porphyry Copper Prospectivity Mapping Integrating Remote Sensing, Geology, and Geochemistry | F52: Remote Sensing | G52: 10.3390/rs18101638 | H52: 2-s2.0-105040235056 | I52: exclude | J52: E2
A53: R0052 | B53: A_both | C53: v1/v2 | D53: 2026 | E53: Ensemble deep learning framework for landslide susceptibility mapping and road vulnerability index development in the Chittagong Hill Tracts, Bangladesh | F53: Geomatics, Natural Hazards and Risk | G53: 10.1080/19475705.2026.2634207 | H53: 2-s2.0-105030702218 | I53: exclude | J53: E2
A54: R0053 | B54: A_both | C54: v1/v2 | D54: 2025 | E54: Mapping wildfire dynamics: GeoAI-driven comparative analysis of deep and machine learning ensembles for susceptibility prediction in California | F54: Geomatica | G54: 10.1016/j.geomat.2025.100081 | H54: 2-s2.0-105020943417 | I54: include
A55: R0054 | B55: A_both | C55: v1/v2 | D55: 2026 | E55: Enhancing machine learning-based gully erosion susceptibility modeling using a prediction-oriented spatial cross-validation framework | F55: Environmental Challenges | G55: 10.1016/j.envc.2026.101418 | H55: 2-s2.0-105029107099 | I55: include
A56: R0055 | B56: A_both | C56: v1/v2 | D56: 2025 | E56: Predicting the impact of climate change on desert locust (Schistocerca gregaria) breeding areas using an ensemble model: A case study of the Wabe Shebelle River Basin, Ethiopia | F56: Environmental Challenges | G56: 10.1016/j.envc.2025.101365 | H56: 2-s2.0-105021047762 | I56: maybe
A57: R0056 | B57: A_both | C57: v1/v2 | D57: 2025 | E57: Expanding cryospheric landform inventories – quantitative approaches for underestimated periglacial block- and talus slopes in the Dry Andes of Argentina | F57: Frontiers in Earth Science | G57: 10.3389/feart.2025.1534410 | H57: 2-s2.0-105005526088 | I57: include
A58: R0057 | B58: A_both | C58: v1/v2 | D58: 2026 | E58: Multi-Model Machine Learning Mapping of Gully Erosion Susceptibility in the Heihe Region of the Xiaoxingán Mountains, China | F58: Remote Sensing | G58: 10.3390/rs18111844 | H58: 2-s2.0-105041409504 | I58: include
A59: R0058 | B59: A_both | C59: v1/v2 | D59: 2026 | E59: Mapping soil organic carbon as soil health indicator of cocoa landscapes in middle Côte d’Ivoire | F59: International Soil and Water Conservation Research | G59: 10.1016/j.iswcr.2025.09.002 | H59: 2-s2.0-105016218623 | I59: include
A60: R0059 | B60: A_both | C60: v1/v2 | D60: 2026 | E60: Enhancing digital mapping of soil organic carbon through spatial modeling and validation | F60: Scientific Reports | G60: 10.1038/s41598-026-39496-2 | H60: 2-s2.0-105033478136 | I60: include
A61: R0060 | B61: A_both | C61: v1/v2 | D61: 2026 | E61: Improving grade estimation using machine learning: A comparative study of ordinary kriging against machine learning algorithms | F61: Journal of the Southern African Institute of Mining and Metallurgy | G61: 10.17159/2411-9717/3664/2026 | H61: 2-s2.0-105034490313 | I61: exclude | J61: E4
A62: R0061 | B62: A_both | C62: v1/v2 | D62: 2026 | E62: Enhancing Estimation of Fine Particulate Matter Chemical Composition across North America by Including Geophysical A Priori Information in Deep Learning with Uncertainty Quantification | F62: ACS ES&T Air | G62: 10.1021/acsestair.5c00251 | H62: 2-s2.0-105031165555 | I62: maybe
A63: R0062 | B63: A_both | C63: v1/v2 | D63: 2024 | E63: Spatial differences in predicted Phalaris arundinacea (reed canarygrass) occurrence in floodplain forest understories | F63: Ecosphere | G63: 10.1002/ecs2.70138 | H63: 2-s2.0-85212491824 | I63: include
A64: R0063 | B64: A_both | C64: v1/v2 | D64: 2026 | E64: Seasonal agricultural vulnerability in semi-arid Morocco: combining remote sensing and farmer knowledge to inform climate adaptation | F64: Climatic Change | G64: 10.1007/s10584-026-04160-1 | H64: 2-s2.0-105033807600 | I64: maybe
A65: R0064 | B65: A_both | C65: v1/v2 | D65: 2026 | E65: Validation design and cross-cluster transferability in machine learning–based prospectivity mapping of magmatic Ni sulphide systems | F65: Ore Geology Reviews | G65: 10.1016/j.oregeorev.2026.107313 | H65: 2-s2.0-105038252701 | I65: exclude | J65: E4
A66: R0065 | B66: A_both | C66: v1/v2 | D66: 2026 | E66: Time-Aware Machine Learning for Biomass Power Output Estimation Using SCADA Data | F66: Arabian Journal for Science and Engineering | G66: 10.1007/s13369-026-11143-y | H66: 2-s2.0-105030700174 | I66: exclude | J66: E4
A67: R0066 | B67: A_both | C67: v1/v2 | D67: 2026 | E67: Prediction of soil available nitrogen using machine learning and digital mapping techniques in Northeast India | F67: Environmental Challenges | G67: 10.1016/j.envc.2025.101375 | H67: 2-s2.0-105023904943 | I67: include
A68: R0067 | B68: A_both | C68: v1/v2 | D68: 2026 | E68: Mapping land use and land cover change as a dimension of urban morphology: a multi-scale workflow from Cairo | F68: Archnet-IJAR: International Journal of Architectural Research | G68: 10.1108/ARCH-03-2026-0213 | H68: 2-s2.0-105047971283 | I68: include
A69: R0068 | B69: A_both | C69: v1/v2 | D69: 2026 | E69: Interpretable geospatial machine learning for seasonal land surface temperature prediction using multi-source earth observation data | F69: Earth Science Informatics | G69: 10.1007/s12145-026-02215-6 | H69: 2-s2.0-105047443825 | I69: include
A70: R0069 | B70: A_both | C70: v1/v2 | D70: 2026 | E70: Analyzing meteorological effects on crop yield and yield prediction through machine learning with different data partitioning approaches: A case study from Czech Republic | F70: Journal of Agriculture and Food Research | G70: 10.1016/j.jafr.2026.102662 | H70: 2-s2.0-105041742684 | I70: include
A71: R0070 | B71: A_both | C71: v1/v2 | D71: 2026 | E71: Deciphering environmental determinants of soil metals in dust-influenced arid soils through interpretable models across data-availability scenarios | F71: Journal of Environmental Management | G71: 10.1016/j.jenvman.2026.129472 | H71: 2-s2.0-105034171722 | I71: exclude | J71: E2
A72: R0071 | B72: A_both | C72: v1/v2 | D72: 2026 | E72: Multi-Model Back Analysis for Predicting Landslide Occurrences Under Extreme Anthropogenic Regime in the Indian Himalaya | F72: International Journal of Environmental Research | G72: 10.1007/s41742-026-01112-6 | H72: 2-s2.0-105038399721 | I72: maybe
A73: R0072 | B73: A_both | C73: v1/v2 | D73: 2026 | E73: Contributions of climate and population change to global flood–landslide multi-hazard population exposure under future climate scenarios | F73: Geoscience Frontiers | G73: 10.1016/j.gsf.2026.102363 | H73: 2-s2.0-105045905233 | I73: include
A74: R0073 | B74: A_both | C74: v1/v2 | D74: 2026 | E74: Explainable machine learning for sandstone rock typing: Triple-anchor convergence with closed-form permeability laws | F74: Chemical Engineering Journal Advances | G74: 10.1016/j.ceja.2026.101323 | H74: 2-s2.0-105043588147 | I74: exclude | J74: E4
A75: R0074 | B75: A_both | C75: v1/v2 | D75: 2026 | E75: Research on spatial heterogeneity of urban flood susceptibility and model attribution in Beijing: An XGBoost-SHAP analysis based on spatial cross-validation | F75: Sustainable Cities and Society | G75: 10.1016/j.scs.2026.107914 | H75: 2-s2.0-105051089815 | I75: exclude | J75: E2
A76: R0075 | B76: A_both | C76: v1/v2 | D76: 2026 | E76: Evaluating ANN, Tabular CNN and Ensemble Random Forest for Aboveground Biomass Estimation: An Integrated Approach Utilizing SAR and Optical Remote Sensing Data | F76: Remote Sensing in Earth Systems Sciences | G76: 10.1007/s41976-026-00302-2 | H76: 2-s2.0-105049672995 | I76: include
A77: R0076 | B77: A_both | C77: v1/v2 | D77: 2026 | E77: Mukara: A deep learning alternative to the four-step travel demand model with a case study on interurban highway traffic prediction in the UK | F77: PLOS ONE | G77: 10.1371/journal.pone.0345576 | H77: 2-s2.0-105035819056 | I77: exclude | J77: E4
A78: R0077 | B78: A_both | C78: v1/v2 | D78: 2026 | E78: A Study on Multi-Tier Categorical Soil Classification Based on Decoupled Parallel Deep Learning: A Case Study in the Southern Foothills of Qilian Mountains | F78: Land | G78: 10.3390/land15091657 | H78: 2-s2.0-105051620573 | I78: include
A79: R0078 | B79: A_both | C79: v1/v2 | D79: 2026 | E79: Associational and Causal Effects of Urban Characteristics on the Block-Scale Thermal Environment in Beijing | F79: Buildings | G79: 10.3390/buildings16163296 | H79: 2-s2.0-105048240372 | I79: exclude | J79: E2
A80: R0079 | B80: A_both | C80: v1/v2 | D80: 2026 | E80: Field-scale prediction and spatial mapping of tractor tractive efficiency in tillage operations using machine learning | F80: Precision Agriculture | G80: 10.1007/s11119-026-10443-5 | H80: 2-s2.0-105051220280 | I80: maybe
A81: R0080 | B81: A_both | C81: v1/v2 | D81: 2026 | E81: Optimizing landslide susceptibility mapping using spatially cross-validated random forest: Lhasa–Dingri corridor, Tibetan Plateau | F81: Natural Hazards | G81: 10.1007/s11069-026-08374-5 | H81: 2-s2.0-105050531783 | I81: maybe
A82: R0081 | B82: A_both | C82: v1/v2 | D82: 2026 | E82: Comparing Five Machine Learning Approaches for Local-Scale Landslide Susceptibility Mapping in the Huoi Reng Watershed, Central Vietnam | F82: International Journal of Geoinformatics | G82: 10.52939/ijg.v22i8.5139 | H82: 2-s2.0-105049559889 | I82: exclude | J82: E2
A83: R0082 | B83: A_both | C83: v1/v2 | D83: 2026 | E83: Physics-aware feature engineering improves spatial transferability of satellite estuarine salinity models: a Mekong Delta evaluation | F83: Remote Sensing Applications: Society and Environment | G83: 10.1016/j.rsase.2026.102297 | H83: 2-s2.0-105051865526 | I83: include
A84: R0083 | B84: A_both | C84: v1/v2 | D84: 2026 | E84: Spatial information explained by prediction models under block cross-validation | F84: ISPRS Journal of Photogrammetry and Remote Sensing | G84: 10.1016/j.isprsjprs.2026.09.034 | H84: 2-s2.0-105052183311 | I84: exclude | J84: E2
A85: R0084 | B85: A_both | C85: v1/v2 | D85: 2026 | E85: Landslide Susceptibility Mapping in the Himalayas: An Integrated Geospatial and Machine Learning Approach-Based Study of the Chandra-Bhaga Basin, Himachal Pradesh, India | F85: Geological Journal | G85: 10.1002/gj.70358 | H85: 2-s2.0-105040357778 | I85: exclude | J85: E2
A86: R0085 | B86: A_both | C86: v1/v2 | D86: 2026 | E86: Explainable Digital Soil Organic Carbon Mapping in Himalayan Region of India’s Northeastern State Based on Gradient Boosting Regression Technique | F86: Applied Soil Ecology | G86: 10.1016/j.apsoil.2026.107358 | H86: 2-s2.0-105046547932 | I86: maybe
A87: R0086 | B87: A_both | C87: v1/v2 | D87: 2026 | E87: Impacts of Urban Grey–Green Spaces on Diurnal and Nocturnal LST in Summer: A Comparison of Two Local Spatial Identification Approaches | F87: Sustainability (Switzerland) | G87: 10.3390/su18189430 | H87: 2-s2.0-105051955924 | I87: include
A88: R0087 | B88: A_both | C88: v1/v2 | D88: 2026 | E88: Habitat suitability modeling reveals conservation gaps for endemic canga flora in Brazil's Iron Quadrangle | F88: Environmental Challenges | G88: 10.1016/j.envc.2026.101526 | H88: 2-s2.0-105040040271 | I88: include
A89: R0088 | B89: A_both | C89: v1/v2 | D89: 2026 | E89: Satellite-driven modelling of NO2 and PM2.5 across Germany (2019–2024): A multi-sensor machine-learning approach | F89: Environmental Pollution | G89: 10.1016/j.envpol.2026.127898 | H89: 2-s2.0-105033513834 | I89: include
A90: R0089 | B90: A_both | C90: v1/v2 | D90: 2026 | E90: Small-Sample Prediction and Uncertainty Assessment of Soil Organic Carbon Content in Cropland of the Liaohe Plain Based on the TabPFN Model | F90: Agronomy | G90: 10.3390/agronomy16161562 | H90: 2-s2.0-105048420593 | I90: include
A91: R0090 | B91: A_both | C91: v1/v2 | D91: 2026 | E91: Soil Carbon Modeling at Crossroads: Building Reliable Methods for Policy and Practice | F91: European Journal of Soil Science | G91: 10.1111/ejss.70295 | H91: 2-s2.0-105031124534 | I91: maybe
A92: R0091 | B92: A_both | C92: v1/v2 | D92: 2026 | E92: Enhanced hyperspectral classification for geological mapping based on spatial–spectral novel framework of vision transformers and mamba models on PRISMA data at Arabian–Nubian Shield | F92: Geoscience Letters | G92: 10.1186/s40562-026-00506-w | H92: 2-s2.0-105051898789 | I92: exclude | J92: E4
A93: R0092 | B93: A_both | C93: v1/v2 | D93: 2026 | E93: Identifying priority planning units for urban Micro-green spaces through explainable machine learning and multi-objective optimization | F93: Ecological Indicators | G93: 10.1016/j.ecolind.2026.115371 | H93: 2-s2.0-105049407600 | I93: include
A94: R0093 | B94: A_both | C94: v1/v2 | D94: 2026 | E94: Ensemble machine learning method for δ18O prediction in groundwater | F94: Scientific Reports | G94: 10.1038/s41598-026-57131-y | H94: 2-s2.0-105042362088 | I94: include
A95: R0094 | B95: A_both | C95: v1/v2 | D95: 2026 | E95: Modeling Urban Population Dynamics Using Spatial Deep Learning: A Comparative Framework for Baghdad and Basra | F95: Indonesian Journal of Geography | G95: 10.22146/ijg.120098 | H95: 2-s2.0-105051284336 | I95: exclude | J95: E4
A96: R0095 | B96: A_both | C96: v1/v2 | D96: 2026 | E96: Deep learning-based reconstruction of high-resolution satellite-derived NO2 columns over the Bohai Sea | F96: Atmospheric Environment | G96: 10.1016/j.atmosenv.2026.122243 | H96: 2-s2.0-105045282891 | I96: include
A97: R0096 | B97: A_both | C97: v1/v2 | D97: 2026 | E97: GCMCNN: a geographically conditioned multiscale convolutional neural network for downscaling land surface temperature | F97: International Journal of Geographical Information Science | G97: 10.1080/13658816.2026.2693888 | H97: 2-s2.0-105043398661 | I97: include
A98: R0097 | B98: A_both | C98: v1/v2 | D98: 2026 | E98: Residential Price Modeling Using Spatially Validated Machine Learning Methods: A Comparison Across Geographical Contexts | F98: Transportation Research Record | G98: 10.1177/03611981261457410 | H98: 2-s2.0-105043777470 | I98: exclude | J98: E4
A99: R0098 | B99: A_both | C99: v1/v2 | D99: 2026 | E99: Limits to the Spatial Transferability of Machine-Learning Models for Farm-Record-Level Maize Yield Prediction in Manabí, Ecuador | F99: Agriculture (Switzerland) | G99: 10.3390/agriculture16171932 | H99: 2-s2.0-105050272378 | I99: include
A100: R0099 | B100: A_both | C100: v1/v2 | D100: 2026 | E100: Integrating Audiovisual Data for Short-Term Particulate Matter Concentration Prediction on Urban Sidewalks | F100: Environmental Science and Technology | G100: 10.1021/acs.est.6c03195 | H100: 2-s2.0-105046474851 | I100: include
...

Sheet 2_Full_text
A1: record_id | B1: ft_decision | C1: ft_reason | D1: n_rows_extracted | E1: notes | F1: Year | G1: Title | H1: Source title | I1: DOI
A2: R0001 | B2: include | D2: 4 | E2: Random 10-fold vs spatial 44-cluster and buffered LOO; RF AGB central Africa. | F2: 2020 | G2: Spatial validation reveals poor predictive performance of large-scale ecological mapping models | H2: Nature Communications | I2: 10.1038/s41467-020-18321-y
A3: R0002 | B3: include | D3: 4 | E3: Nested random vs k-means spatial repeated 5-fold CV; 4 ML models plus GLM/GAM (not extracted). Preprint. | F3: 2019 | G3: Hyperparameter tuning and performance assessment of statistical and machine-learning algorithms using spatial data | H3: Ecological Modelling | I3: 10.1016/j.ecolmodel.2019.06.002
A4: R0005 | B4: include | D4: 4 | E4: Random vs block (LULC) and leave-cluster-out (LAI) CV; RF. Preprint. | F4: 2019 | G4: Importance of spatial predictor variable selection in machine learning applications – Moving from data reproduction to spatial prediction | H4: Ecological Modelling | I4: 10.1016/j.ecolmodel.2019.108815
A5: R0006 | B5: exclude | C5: E2 | D5: 0 | E5: Virtual-species SDMs; only random split CV vs true performance; no spatial CV. | F5: 2021 | G5: Assessing the reliability of species distribution projections in climate change research | H5: Diversity and Distributions | I5: 10.1111/ddi.13252
A6: R0009 | B6: include | D6: 3 | E6: CNN tree species; random tile split vs site-block hold-out; F1 read from Fig. 3 boxplots. | F6: 2022 | G6: Spatially autocorrelated training and validation samples inflate performance assessment of convolutional neural networks | H6: ISPRS Open Journal of Photogrammetry and Remote Sensing | I6: 10.1016/j.ophoto.2022.100018
A7: R0013 | B7: include | D7: 3 | E7: Global Ksat RF; random vs 5-degree block 5-fold CV, Table 2. | F7: 2021 | G7: Global Prediction of Soil Saturated Hydraulic Conductivity Using Random Forest in a Covariate-Based GeoTransfer Function (CoGTF) Framework | H7: Journal of Advances in Modeling Earth Systems | I7: 10.1029/2020MS002242
A8: R0036 | B8: include | D8: 2 | E8: RF oak dieback; LOO vs 10 km buffered SLOO; values read from Fig. 10. | F8: 2024 | G8: Toward an Operational Monitoring of Oak Dieback With Multispectral Satellite Time Series: A Case Study in Centre-Val De Loire Region of France | H8: IEEE Journal of Selected Topics in Applied Earth Observations and Remote Sensing | I8: 10.1109/JSTARS.2023.3332420
A9: R0037 | B9: exclude | C9: E5 | D9: 0 | E9: Fold-mean CV AUC per scheme not in main text; only CV-test MAE and test AUC. Check supplement S4/GitHub. | F9: 2025 | G9: Foundation for unbiased cross-validation of spatio-temporal models for Species Distribution Modeling | H9: Ecological Informatics | I9: 10.1016/j.ecoinf.2025.103521
A10: R0059 | B10: include | D10: 3 | E10: RF SOC; random repeated 10-fold vs spatial CV (Table 4); spatial CV poorly described. | F10: 2026 | G10: Enhancing digital mapping of soil organic carbon through spatial modeling and validation | H10: Scientific Reports | I10: 10.1038/s41598-026-39496-2
A11: R0093 | B11: include | D11: 2 | E11: RF/GBR delta18O; LOOCV vs 4 longitude blocks; R2 only; n=96. | F11: 2026 | G11: Ensemble machine learning method for δ18O prediction in groundwater | H11: Scientific Reports | I11: 10.1038/s41598-026-57131-y
A12: R0025 | B12: include | D12: 1 | E12: Random 80/20 split vs leave-one-sub-basin-out (9 sub-basins), RF metamodel of drainage fraction. | F12: 2022 | G12: Assessing spatial transferability of a random forest metamodel for predicting drainage fraction | H12: Journal of Hydrology | I12: 10.1016/j.jhydrol.2022.128177
A13: R0063 | B13: include | D13: 6 | E13: Borderline domain (farmer-perceived agricultural vulnerability). Standard vs 50 km spatial block CV, Table 1 macro-F1; accuracy and other block sizes only in supplement. | F13: 2026 | G13: Seasonal agricultural vulnerability in semi-arid Morocco: combining remote sensing and farmer knowledge to inform climate adaptation | H13: Climatic Change | I13: 10.1007/s10584-026-04160-1
A14: R0069 | B14: include | D14: 72 | E14: Random repeated 70/30 vs region-grouped CV for 4 crop yields x 3 models; with/without Year variants. | F14: 2026 | G14: Analyzing meteorological effects on crop yield and yield prediction through machine learning with different data partitioning approaches: A case study from Czech Republic | H14: Journal of Agriculture and Food Research | I14: 10.1016/j.jafr.2026.102662
A15: R0111 | B15: include | D15: 8 | E15: Borderline domain (Fasciola infection risk from drone environmental indices). Stratified 5-fold vs 3 spatial cluster folds, accuracy Table 3. | F15: 2026 | G15: Drone-based geospatial prediction modeling identifies Fasciola hepatica infection risk in the Cusco Highlands of Peru | H15: Infectious Diseases of Poverty | I15: 10.1186/s40249-026-01420-1
A16: R0113 | B16: include | D16: 2 | E16: Random 5-fold vs leave-one-district-out, GB only (Table 4). Article in press; internal inconsistencies noted. | F16: 2026 | G16: Explainable machine learning for climate change attribution and hotspot identification: spatial cross-validation analysis in South Asian Region | H16: Scientific Reports | I16: 10.1038/s41598-026-57382-9
A17: R0122 | B17: exclude | C17: E2 | D17: 0 | E17: Only spatial (block GroupKFold and block-based 70/30 test); no random CV. | F17: 2026 | G17: Predicting surface urban heat island intensity and its drivers using machine learning and spatial XAI for achieving SDG-11 | H17: Computational Urban Science | I17: 10.1007/s43762-026-00291-4
A18: R0136 | B18: include | D18: 1 | E18: Preprint (arXiv) of Meyer & Pebesma 2021 MEE; simulated response; random 10-fold vs leave-cluster-out RMSE from text. Check published version. | F18: 2021 | G18: Predicting into unknown space? Estimating the area of applicability of spatial prediction models | H18: Methods in Ecology and Evolution | I18: 10.1111/2041-210X.13650
A19: R0158 | B19: include | D19: 24 | E19: LOO (h=0, digitised from Fig. 3) vs h-block CV at variogram range (Table 3); pollen-climate calibration, NA and Europe. | F19: 2019 | G19: Machine-learning based reconstructions of primary and secondary climate variables from North American and European fossil pollen data | H19: Scientific Reports | I19: 10.1038/s41598-019-52293-4
A20: R0174 | B20: exclude | C20: E3 | D20: 0 | E20: No ML model and no CV comparison (temporal adjustment of short-term air pollution observations). | F20: 2020 | G20: Spatial modelling of particulate matter air pollution sensor measurements collected by community scientists while cycling, land use regression with spatial cross-validation, and applications of machine learning for data correction | H20: Atmospheric Environment | I20: 10.1016/j.atmosenv.2020.117479
A21: R0200 | B21: include | D21: 8 | E21: 5-fold vs spatial block CV MAE of best algorithm per pigment (Table 4); best-model identity under 5-fold in Suppl. S4. | F21: 2020 | G21: Accuracy of Empirical Satellite Algorithms for Mapping Phytoplankton Diagnostic Pigments in the Open Ocean: A Supervised Learning Perspective | H21: Frontiers in Marine Science | I21: 10.3389/fmars.2020.00599
A22: R0201 | B22: include | D22: 30 | E22: Random 10-fold vs station-grouped 10-fold CV, PCNN-DNN, Table 1 per year (RMSE, MAE; R in notes). | F22: 2023 | G22: A Coupled Deep Learning Model for Estimating Surface NO2 Levels From Remote Sensing Data: 15-Year Study Over the Contiguous United States | H22: Journal of Geophysical Research: Atmospheres | I22: 10.1029/2022JD037010
A23: R0208 | B23: include | D23: 3 | E23: arXiv preprint of IJGIS 2023 paper; RF values digitised from Figs 2 and 4 (Meuse RMSE; Maipo accuracy = 1-error rate). Geostatistical/linear models not extracted. | F23: 2023 | G23: Spatial machine-learning model diagnostics: a model-agnostic distance-based approach | H23: International Journal of Geographical Information Science | I23: 10.1080/13658816.2022.2131789
A24: R0218 | B24: exclude | C24: E2 | D24: 0 | E24: Only spatial block CV (blockCV, 100 km, 13 folds) reported; AUC comparisons are across thinning datasets, not random vs spatial CV. Supplement (Fig. S4) not checked. | F24: 2022 | G24: Large-scale forecasting of Heracleum sosnowskyi habitat suitability under the climate change on publicly available data | H24: Scientific Reports | I24: 10.1038/s41598-022-09953-9
A25: R0232 | B25: include | D25: 16 | E25: Spatial k-means CV vs non-spatial CV, RF land cover (Table 2) and foliar cover (Table 5). | F25: 2022 | G25: Contributions to Satellite-Based Land Cover Classification, Vegetation Quantification and Grassland Monitoring in Central Asian Highlands Using Sentinel-2 and MODIS Data | H25: Frontiers in Environmental Science | I25: 10.3389/fenvs.2022.684589
A26: R0245 | B26: include | D26: 6 | E26: Sea-ice DeepLabV3: benchmark held-out test (random-like, not stated random) vs 2-region spatial CV (Fig. 13 digitised). Borderline random comparator; flagged. | F26: 2025 | G26: Enhancing and Interpreting Deep Learning for Sea Ice Charting using the AutoICE Benchmark | H26: Remote Sensing Applications: Society and Environment | I26: 10.1016/j.rsase.2025.101538
A27: R0270 | B27: include | D27: 6 | E27: RF pasture biomass: 75/25 random split vs leave-location-out; values printed in Fig. 9. | F27: 2020 | G27: Retrieval of hyperspectral information from multispectral data for perennial ryegrass biomass estimation | H27: Sensors (Switzerland) | I27: 10.3390/s20247192
A28: R0408 | B28: include | D28: 6 | E28: Country-level FAOSTAT panel, RF/XGB 10-fold vs 10-block spatial CV (Table 2). Scope borderline; flagged for second reviewer. | F28: 2025 | G28: A machine learning approach to identifying climate change drivers in Africa’s bioenergy sector | H28: Discover Sustainability | I28: 10.1007/s43621-025-01475-4
A29: R0453 | B29: exclude | C29: E2 | D29: 0 | E29: Barn-filter RF evaluated only with spatial block CV (buffers 500-5000 m); farm-type and population RFs only random split. No same model with both. Also borderline E4 (livestock infrastructure). | F29: 2026 | G29: Predicting the spatial distribution and demographics of commercial swine farms in the United States | H29: Preventive Veterinary Medicine | I29: 10.1016/j.prevetmed.2026.106963
A30: R0473 | B30: include | D30: 12 | E30: 4 tree models: random 105/46 test split vs 4-block spatial CV (Table 3, Fig. 3). | F30: 2026 | G30: Interpretable machine learning reveals spatial drivers and regional gradients of soil organic matter across Anhui Province, China | H30: Environmental Earth Sciences | I30: 10.1007/s12665-026-13102-0
A31: R0603 | B31: include | D31: 12 | E31: 4 boosting/RF models, random 80/20 vs 5-fold spatial block CV (Table 3); LR not extracted. | F31: 2026 | G31: Spatially validated assessment of seismic hazard-prone environments in Myanmar using multi-source data and interpretable machine learning | H31: Scientific reports | I31: 10.1038/s41598-026-45557-3
A32: R0672 | B32: exclude | C32: E2 | D32: 0 | E32: Only spatial CV (k-means 5-block GroupKFold) on the training set; the 70/30 hold-out of positive sites is not described as random and is evaluated with the final model, so no matched random CV. RF spatial-CV AUC 0.883 vs hold-out AUC 0.883. Also borderline domain (urban illegal dumping, PU learning). | F32: 2026 | G32: A GeoAI framework for detecting risk zones from illegal dumping sites in Khulna, Bangladesh | H32: PLOS ONE | I32: 10.1371/journal.pone.0345178
A33: R0676 | B33: exclude | C33: E2 | D33: 0 | E33: QC reconciliation 2026-10-12: first decision kept. Global AUC is resubstitution, not random CV: the public notebook (github.com/RelativelyBurberry/wildfire-wuipi) fits on the balanced sample and scores predict_proba on all pixels. Spatial = west/east half hold-out. RF global AUC 0.948 vs spatial AUC 0.547 (Tables 6, 9); not usable as random-vs-spatial comparison. | F33: 2026 | G33: Spatial bias in wildfire ignition models using a wildland urban Interface Pressure Index in the Tamil Nadu and Karnataka Belt | H33: Frontiers in Forests and Global Change | I33: 10.3389/ffgc.2026.1857505
A34: R0715 | B34: exclude | C34: E2 | D34: 0 | E34: In-domain evaluation trains and tests on the same pixels (no random CV); only 4-fold spatial quadrant block holdout. Train vs test-block R2 in Table 4. EarthArXiv preprint of RSE paper (10.1016/j.rse.2026.115610). | F34: 2026 | G34: Calibrated spatial uncertainty for Earth observation foundation models via Matérn-motivated latent stochastic regularization | H34: Remote Sensing of Environment | I34: 10.1016/j.rse.2026.115610
A35: R0722 | B35: exclude | C35: E2 | D35: 0 | E35: Only random 70:30 and 80:20 splits; spatial validation on other rice plots mentioned but not quantified. | F35: 2025 | G35: Spatial Analysis of Ensemble Learning Models for Agricultural Drought Early Warning | H35: Journal of Applied Data Sciences | I35: 10.47738/jads.v7i1.1108
A36: R0757 | B36: include | D36: 16 | E36: RF (+CV predictors, full season): random 70/30 test (dashed lines Fig. 7) vs leave-one-field-out (10 fields); 8 fibre traits x R2/RMSE. LOFO means partly from text, rest digitised from Fig. 7. | F36: 2026 | G36: Geospatializing cotton fiber quality: a step towards on-farm traceability and predictability | H36: Precision Agriculture | I36: 10.1007/s11119-026-10332-x
A37: R0976 | B37: include | D37: 9 | E37: Three GFMs (Prithvi 2.0, Clay, DOFA) x 3 sensors; random 75/10/15 split (Table III) vs leave-one-region-out over 5 regions (Table IV). F1 extracted (mIoU in notes); PlanetScope primary. | F37: 2026 | G37: Assessing Geo-Foundational Models for Flood Inundation Mapping: Benchmarking Models for Sentinel-1, Sentinel-2, and Planetscope | H37: IEEE Journal of Selected Topics in Applied Earth Observations and Remote Sensing | I37: 10.1109/JSTARS.2026.3656855
A38: R0980 | B38: include | D38: 6 | E38: RF digital soil mapping; leave-one-country-out reconstructed from four 3-country donor models (Table 6) vs their 10-fold random CV (Table 4); clay, OC, pH x RMSE/MEC. | F38: 2024 | G38: Evaluating the extrapolation potential of random forest digital soil mapping | H38: Geoderma | I38: 10.1016/j.geoderma.2023.116740
A39: R0986 | B39: include | D39: 8 | E39: Multitask LSTM soil moisture; random 5-fold over sites vs 7-region leave-one-region-out (Table 1b/c). RMSE global (primary) + 7 regional subsets (primary=no); Pearson R in notes. | F39: 2023 | G39: Evaluating a global soil moisture dataset from a multitask model (GSM3 v1.0) with potential applications for crop threats | H39: Geoscientific Model Development | I39: 10.5194/gmd-16-1553-2023
A40: R1001 | B40: exclude | C40: E5 | D40: 0 | E40: GBM (xgboost) with random 5-fold CV vs data-driven spatiotemporal CV (Table 1), but the only metric is the EVA 2021 challenge score (weighted squared exceedance-probability errors), not in the codebook metric list. E.g. dGPD 2896 (random) vs 3215 (spatial) vs 3068 true test score. Usable only if metric list is expanded. | F40: 2023 | G40: Gradient boosting with extreme-value theory for wildfire prediction | H40: Extremes | I40: 10.1007/s10687-022-00454-6
A41: R1016 | B41: include | D41: 10 | E41: RF and LightGBM, 5 feature sets; random 5-fold (Fig. 3A) vs leave-one-site-out over 10 sites (Fig. 5A); R2 digitised (LGBM F4 random exact 0.844). F4 primary. LOSO RMSE only in supplement. | F41: 2026 | G41: Deployment-oriented evaluation of stage-specific information for rice yield prediction across years, sites and site-year environments in southern China | H41: Frontiers in Plant Science | I41: 10.3389/fpls.2026.1915306
A42: R1047 | B42: include | D42: 18 | E42: XGB/DT/RF; random 5-fold vs 1-deg spatial block 5-fold; 2 soil depths (S1047a/b). | F42: 2026 | G42: Spatial assessment of forest soil carbon and climate-related value inside and outside protected areas in China | H42: Environmental Monitoring and Assessment | I42: 10.1007/s10661-026-15630-5
A43: R1170 | B43: include | D43: 12 | E43: RF/HGBR/SVR; random 10-fold vs pasture-block and ecosite LOGO; values digitised from Fig. 4. Linear models not extracted. | F43: 2026 | G43: Bringing cross-validation into the real world to evaluate transferability of satellite-based vegetation models | H43: Scientific Reports | I43: 10.1038/s41598-026-39866-w
A44: R1206 | B44: include | D44: 1 | E44: RF only; random 70/30 split vs station-grouped CV; only R2 available for both. | F44: 2026 | G44: Monitoring network design limits detection of sediment-mediated contaminant mobilisation in the River Mersey estuary (UK) | H44: Marine Pollution Bulletin | I44: 10.1016/j.marpolbul.2026.120004
A45: R1265 | B45: exclude | C45: E1 | D45: 0 | E45: Methodological overview + simulations (arXiv preprint of Stat Sci 2026 paper); simulations explicitly not done for spatial data; no empirical random vs spatial CV comparison. | F45: 2026 | G45: Evaluating Machine Learning Models in Nonstandard Settings: An Overview and New Findings | H45: Statistical Science | I45: 10.1214/25-STS984
A46: R1378 | B46: include | D46: 5 | E46: LightGBM per species; tree-grouped random 5-fold vs plot-grouped 5-fold; journal pre-proof PDF. | F46: 2026 | G46: Drivers of tree growth across Europe: An explainable AI analysis of tree- and site-level influences | H46: Ecological Informatics | I46: 10.1016/j.ecoinf.2026.103932
A47: R1440 | B47: include | D47: 6 | E47: XGBoost; random hold-out vs leave-one-dataset-out (and spatiotemporal variant, primary=no). | F47: 2026 | G47: Machine learning predictions for microbial eukaryotic plankton: implications from unevenly structured data | H47: Frontiers in Marine Science | I47: 10.3389/fmars.2026.1875929
A48: R1489 | B48: exclude | C48: E2 | D48: 0 | E48: Forest fire classification (Algerian/Canadian/Portugal datasets) with random 80/20 split and 5-fold tuning only; no spatial CV. arXiv preprint version read. | F48: 2026 | G48: Advancing Forest Fires Classification Using Neurochaos Learning | H48: IEEE Access | I48: 10.1109/ACCESS.2026.3734132
A49: R1592 | B49: include | D49: 6 | E49: RF/SVM; stratified random 50:50 split vs train-one-site/test-other-site; WCM not extracted. | F49: 2026 | G49: Comparison of soil moisture mapping techniques: Evaluating dataset variability and spatial transferability across regions | H49: Environmental Earth Sciences | I49: 10.1007/s12665-026-12963-9
A50: R1609 | B50: include | D50: 2 | E50: RF only; random 10-fold x100 (buffer non-landslides) vs k-means spatial CV (10 clusters); other ML only random. | F50: 2026 | G50: Validation and prediction challenges in data-driven landslide susceptibility mapping: insights from random sampling of training and test data in machine learning models | H50: Bulletin of Engineering Geology and the Environment | I50: 10.1007/s10064-026-04911-5
A51: R1892 | B51: exclude | C51: E2 | D51: 0 | E51: Crop phenology LightGBM; nested random 10-fold CV only, spatial CV explicitly not used. | F51: 2025 | G51: A novel fusion of Sentinel-1 and Sentinel-2 with climate data for crop phenology estimation using Machine Learning | H51: Science of Remote Sensing | I51: 10.1016/j.srs.2025.100227
A52: R1895 | B52: include | D52: 1 | E52: Borderline: random 10-fold CV (internal testing) vs hold-out of 30% of tree-ring sites, TS model only; R2 definitions differ. Author manuscript (ORCA) of J Ecol 2025. | F52: 2025 | G52: Integrating spatiotemporal variation of climate improves predictability of tree growth | H52: Journal of Ecology | I52: 10.1111/1365-2745.70073
A53: R2055 | B53: exclude | C53: E2 | D53: 0 | E53: Landform classification Poland (RF/XGBoost/LightGBM/U-Net): only random 30% holdout and random 5-fold CV per sheet; spatial validation only discussed, country-wide extrapolation reported qualitatively. | F53: 2024 | G53: Explanation of the influence of geomorphometric variables on the landform classification based on selected areas in Poland | H53: Scientific Reports | I53: 10.1038/s41598-024-56066-6
A54: R2080 | B54: include | D54: 4 | E54: 10-fold random CV vs leave-block-out and leave-site-out (Table 3); leave-year-out not extracted. | F54: 2024 | G54: Combining production ecology principles with random forest to model potato yield in China | H54: Field Crops Research | I54: 10.1016/j.fcr.2024.109619
A55: R2118 | B55: exclude | C55: E2 | D55: 0 | E55: Only leave-one-experiment-out CV (21 N strip trials, Australia) with data thinning; no random CV comparator. | F55: 2025 | G55: What makes on-farm experimental data suitable for data-driven decision-making? implications of trial design and spatial distribution of field data for machine learning models | H55: Precision Agriculture | I55: 10.1007/s11119-025-10280-y
A56: R2127 | B56: exclude | C56: E2 | D56: 0 | E56: Tree species classification (arXiv 2408.08887): only plot-level stratified 10-fold CV; no random vs spatial comparison. | F56: 2025 | G56: Tree Species Classification at the Pixel Level Using Deep Learning and Multispectral Time Series in an Imbalanced Context | H56: Remote Sensing | I56: 10.3390/rs17071190
A57: R2130 | B57: include | D57: 64 | E57: LOOCV vs leave-site-out and leave-zone-out, 4 ML models x 4 targets (Table 2). | F57: 2025 | G57: Modeling maize yield and agronomic efficiency using machine learning models: A comparative analysis | H57: Agronomy Journal | I57: 10.1002/agj2.70206
A58: R2211 | B58: exclude | C58: E2 | D58: 0 | E58: Black-grass density: within-field 5-fold CV of single-field RF vs leave-one-field-out of weighted ensemble (different models); metric GMS per class only in Fig. 3 (~0.7 vs ~0.1). Data/code Dryad. | F58: 2024 | G58: Black-Grass Monitoring Using Hyperspectral Image Data Is Limited by Between-Site Variability | H58: Remote Sensing | I58: 10.3390/rs16244749
A59: R2289 | B59: include | D59: 6 | E59: Random vs k-means spatial 4-fold CV, 3 datasets (Table 2); independent other-region test for LSF-21 model (Table 3). | F59: 2023 | G59: Detecting abandoned citrus crops using Sentinel-2 time series. A case study in the Comunitat Valenciana region (Spain) | H59: ISPRS Journal of Photogrammetry and Remote Sensing | I59: 10.1016/j.isprsjprs.2023.05.003
A60: R2433 | B60: include | D60: 4 | E60: 50-fold random vs 50-fold spatial k-means CV for RRF, 2 eel species (Tables 1-2); VAST/GRaF not ML. Accepted manuscript version. | F60: 2023 | G60: Comparing the performance of three common species distribution modelling frameworks for freshwater environments through application to eel species in New Zealand | H60: Canadian Journal of Fisheries and Aquatic Sciences | I60: 10.1139/cjfas-2022-0212
A61: R2484 | B61: exclude | C61: E2 | D61: 0 | E61: PhD thesis (Guelph): ML gully susceptibility with random 70/30 local validation vs transfer of single-watershed models to other watersheds (external other-region test, not spatial CV). Chapter published as Mohebzadeh et al. 2024 Natural Hazards; transfer matrices (Tables 2.5-2.9) could serve a sensitivity analysis. | F61: 2024 | G61: Transferability of predictive models to map susceptibility of ephemeral gullies at large scale | H61: Natural Hazards | I61: 10.1007/s11069-023-06377-0
A62: R2506 | B62: include | D62: 22 | E62: Software paper (stressor R package) with original agricultural applications. Corn yield: random 10-fold vs k-means lat/lon SCV (primary) and feature-space SCV. Crop suitability: only feature-space SCV, extracted as primary=no. | F62: 2024 | G62: Producing Fast and Convenient Machine Learning Benchmarks in R with the stressor Package | H62: Journal of Data Science | I62: 10.6339/24-JDS1123
A63: R2541 | B63: include | D63: 7 | E63: Random 80/10/10 split within north vs transfer to south region (single regional hold-out). Macro-F1 computed from per-class F1 tables A1-A7 and Table 7. Borderline: spatial design is one region transfer. | F63: 2024 | G63: Transferability of Machine Learning Models for Crop Classification in Remote Sensing Imagery Using a New Test Methodology: A Study on Phenological, Temporal, and Spatial Influences | H63: Remote Sensing | I63: 10.3390/rs16091493
A64: R2596 | B64: exclude | C64: E5 | D64: 0 | E64: Lynx habitat (Maxent, RF, GAMM). Internal CV = held-out individuals within sites (not random observation CV); external = leave-one-site-out (14 folds). Main text only reports a combined normalized AUC/CBI score (Fig. 3); absolute AUC per level in Appendix S7 (supplement not available). Also questionable as random comparator (E2). | F64: 2023 | G64: Integrating animal tracking datasets at a continental scale for mapping Eurasian lynx habitat | H64: Diversity and Distributions | I64: 10.1111/ddi.13784
A65: R2613 | B65: exclude | C65: E5 | D65: 0 | E65: Global wood density (RF, XGB, LightGBM, etc.). Random 5-fold R2 0.50-0.56 in text; spatial block 10-fold (5 deg) and other cluster CVs only in Supplementary Fig. S2b. Check supplement / Zenodo 10.5281/zenodo.10692059. | F65: 2024 | G65: Global patterns of tree wood density | H65: Global Change Biology | I65: 10.1111/gcb.17224
A66: R2615 | B66: include | D66: 6 | E66: Soil moisture from geophysics: 1000 random 60/40 splits vs two spatial half-transect hold-outs (Table 2). R2 only. | F66: 2023 | G66: Field evaluation of semi-automated moisture estimation from geophysics using machine learning | H66: Vadose Zone Journal | I66: 10.1002/vzj2.20246
A67: R2906 | B67: not_retrieved | D67: 0 | E67: PDF is only the supplementary figures (S1-S18 residual maps) of Stock et al. fisheries bycatch SDM paper, not the article. | F67: 2020 | G67: Comparing predictions of fisheries bycatch using multiple spatiotemporal species distribution model frameworks | H67: Canadian Journal of Fisheries and Aquatic Sciences | I67: 10.1139/cjfas-2018-0281
A68: R2907 | B68: exclude | C68: E2 | D68: 0 | E68: Soil pH NL (QRF): OOB vs location-grouped 10-fold CV (grouping depth observations of the same profile, authors call it random k-fold grouped by location; not spatial CV) plus independent probability sample. Numbers: RMSE OOB 0.47, grouped CV 0.71, LSK 0.79; MEC 0.88/0.72/0.68. Could be reconsidered as leave_location_out if team accepts point-location grouping. | F68: 2022 | G68: Tier 4 maps of soil pH at 25 m resolution for the Netherlands | H68: Geoderma | I68: 10.1016/j.geoderma.2021.115659
A69: R2934 | B69: include | D69: 10 | E69: GEDI canopy height CNN ensemble: random 10-fold vs leave-one-continental-region-out (Table 1). Spatial RMSE lower than random. arXiv v2 used; published RSE 2022. | F69: 2022 | G69: Global canopy height regression and uncertainty estimation from GEDI LIDAR waveforms with deep ensembles | H69: Remote Sensing of Environment | I69: 10.1016/j.rse.2021.112760
A70: R3051 | B70: include | D70: 8 | E70: Mushroom productivity: k-fold vs spatial 10-fold vs environmental CV, MSE in Table 2, converted to RMSE. | F70: 2021 | G70: Performance of statistical and machine learning-based methods for predicting biogeographical patterns of fungal productivity in forest ecosystems | H70: Forest Ecosystems | I70: 10.1186/s40663-021-00297-w
A71: R3094 | B71: exclude | C71: E2 | D71: 0 | E71: Simulation study of sampling designs (random/systematic/clustered) with hyperspectral simulated data; no comparison of random vs spatial CV of same model (10-fold CV only for tuning; validation on other realizations). | F71: 2021 | G71: Role of Sampling Design When Predicting Spatially Dependent Ecological Data with Remote Sensing | H71: IEEE Transactions on Geoscience and Remote Sensing | I71: 10.1109/TGRS.2020.2989216
A72: R3124 | B72: exclude | C72: E2 | D72: 0 | E72: Gregr 2021 PLOS ONE marine substrate RF: random 67/33 split and OOB vs independent datasets (dive, ROV, camera); no spatial CV. | F72: 2021 | G72: Comprehensive marine substrate classification applied to Canada’s Pacific shelf | H72: PLoS ONE | I72: 10.1371/journal.pone.0259156
A73: R3145 | B73: exclude | C73: E5 | D73: 0 | E73: Lyons 2018 RSE: random vs block hold-out (survey blocks) resampling, but main figures only for maximum likelihood (discriminant analysis); RF results only in Supplementary Figs S3-S4 (not in PDF), shown as violins. Code/data on GitHub/Zenodo (doi 10.5281/zenodo.1146099) could allow recomputation. | F73: 2018 | G73: A comparison of resampling methods for remote sensing classification and accuracy assessment | H73: Remote Sensing of Environment | I73: 10.1016/j.rse.2018.02.026
A74: R3149 | B74: exclude | C74: E2 | D74: 0 | E74: Rocha 2018 Remote Sensing: simulated landscapes (PROSAIL); random 10-fold CV vs test/independent sets; no spatial CV. | F74: 2018 | G74: Machine learning using hyperspectral data inaccurately predicts plant traits under spatial dependency | H74: Remote Sensing | I74: 10.3390/rs10081263
A75: R3167 | B75: include | D75: 1 | E75: Gavish 2018 MEE (accepted ms): RF per-site land-cover models; within-site kappa 0.780 vs transferred to other sites 0.360. Within-site validation method only in Appendix S1 - verify (possible OOB/resubstitution). Borderline: site-transfer rather than pooled spatial CV. | F75: 2018 | G75: Quantifying and modelling decay in forecast proficiency indicates the limits of transferability in land-cover classification | H75: Methods in Ecology and Evolution | I75: 10.1111/2041-210X.12870
A76: R3209 | B76: include | D76: 1 | E76: Karasiak 2022 Machine Learning: RF forest type; object LOO 90.76% vs SLOO (19.74 km buffer) 82.08% OA; 2-fold k-fold as alt; independent other-region tests. | F76: 2022 | G76: Spatial dependence between training and test sets: another pitfall of classification accuracy assessment in remote sensing | H76: MACHINE LEARNING | I76: 10.1007/s10994-021-05972-1
A77: R3219 | B77: include | D77: 9 | E77: Chen 2021 ESSD: RF daily air temperature China; random 1/5 test split vs leave-location-out (7 station clusters); 3 weather-condition models x R2/MAE/RMSE. | F77: 2021 | G77: An all-sky 1 km daily land surface air temperature product over mainland China for 2003-2019 from MODIS and ancillary data | H77: EARTH SYSTEM SCIENCE DATA | I77: 10.5194/essd-13-4241-2021
A78: R3221 | B78: exclude | C78: E5 | D78: 0 | E78: Merckx thesis chapter (published as Merckx et al. 2011 Ecol Model 222:588-597): Maxent for 223 nematode species, random 5-fold vs 5/10 km separated 5-fold CV. Only per-species AUC scatter plots and mean AUC decrease (0.046 at 5 km, 0.110 at 10 km) reported; no paired mean AUC values. Check published version. | F78: 2011 | G78: Null models reveal preferential sampling, spatial autocorrelation and overfitting in habitat suitability modelling | H78: ECOLOGICAL MODELLING | I78: 10.1016/j.ecolmodel.2010.11.016
A79: R3226 | B79: include | D79: 6 | E79: Shah 2026 Folia Oecologica: GEDI + FIA tree diversity; random 5-fold vs leave-one-latitude-band-out; RF and GBM x 3 diversity metrics (R2). Shannon/Simpson spatial from Fig. 5 labels; exact in Suppl. Table S5. | F79: 2026 | G79: Predicting forest biodiversity from spaceborne GEDI LiDAR and machine learning: structural drivers and regional transferability across Pacific Northwest forests | H79: FOLIA OECOLOGICA | I79: 10.2478/foecol-2026-0018
A80: R3229 | B80: include | D80: 24 | E80: Ruther 2026 EGUsphere preprint: landslide release, GBM and GPBoost; random vs k-means cluster, large and small block CV; nested (test AUC) and simple CV; full and forest-only data. Primary = full/nested/small block. Check for peer-reviewed version (published_doi). | F80: 2026 | G80: Spatial machine learning modelling reveals that soil indicators and tree type best explain shallow landslide release | H80: NATURAL HAZARDS AND EARTH SYSTEM SCIENCES | I80: 10.5194/nhess-26-4675-2026
A81: R3232 | B81: exclude | C81: E2 | D81: 0 | E81: Zhang 2026 Sci Data: CNN-Transformer Greenland SMB; spatial (station) 5-fold CV vs training fit (Best model) only; random 80/20 tuning split metrics not reported. | F81: 2026 | G81: A machine-learning-based reconstruction of surface mass balance over the Greenland Ice Sheet from 1950 to 2020 | H81: SCIENTIFIC DATA | I81: 10.1038/s41597-026-07615-3
A82: R0014 | B82: include | D82: 4 | E82: Killeen 2024 Remote Sens: UAV corn yield; RF random 10-fold vs k-means spatial 10-fold (field-level, same data). Only Pearson CC reported (metric outside v2 list, kept native as Pearson_r); 1 value pair from abstract, 3 digitised from Fig. 4. LOFO not same data. | F82: 2024 | G82: Corn Grain Yield Prediction Using UAV-Based High Spatiotemporal Resolution Imagery, Machine Learning, and Spatial Cross-Validation | H82: Remote Sensing | I82: 10.3390/rs16040683
A83: R0015 | B83: include | D83: 48 | E83: Mushagalusa 2024 ESR: simulation study, RF species abundance; random 5-fold vs spatial block (random/systematic/checkerboard) and buffered LOO. MEC (=R2) medians digitised from Fig. 7 boxplots (12 scenarios). Other metrics (RMSE, bias, Spearman r2) only in boxplots/supplement. | F83: 2024 | G83: Random forest and spatial cross-validation performance in predicting species abundance distributions | H83: Environmental Systems Research | I83: 10.1186/s40068-024-00352-9
A84: R0016 | B84: include | D84: 10 | E84: Kumar 2025 Remote Sens: landslide susceptibility Arequipa; R-CV vs k-means S-CV 10-fold x5; Table 4 AUC and OA for kNN, SVM, ANN, RF, C5.0. Fold/variable/training-size series in Supplementary S1-S3. | F84: 2025 | G84: Random Cross-Validation Produces Biased Assessment of Machine Learning Performance in Regional Landslide Susceptibility Prediction | H84: Remote Sensing | I84: 10.3390/rs17020213
A85: R0017 | B85: include | D85: 20 | E85: Misiuk 2019 Geosciences: seabed sediment RF; LOO vs spatial buffered LOO (1500 m grain size, 200 m coarse). Tables 4, 5, A15. Domain marine habitat (not geology/mining). | F85: 2019 | G85: A spatially explicit comparison of quantitative and categorical modelling approaches for mapping seabed sediments using random forest | H85: Geosciences (Switzerland) | I85: 10.3390/geosciences9060254
A86: R0018 | B86: include | D86: 10 | E86: Stock 2025 Front Remote Sens: synthetic Chl a, Baltic; RF and RFXY; 10-fold vs subbasin/latitudinal/blockCV blocks; "true" error on probability sample of pixels (Table 1). blockCV size series in Fig. 5 not extracted. | F86: 2025 | G86: Choosing blocks for spatial cross-validation: lessons from a marine remote sensing case study | H86: Frontiers in Remote Sensing | I86: 10.3389/frsen.2025.1531097
A87: R0019 | B87: include | D87: 6 | E87: Dai 2023 Remote Sens: landslide susceptibility Liangshan; RF and GRF; random 10-fold vs k-means spatial 10-fold (Table 5). | F87: 2023 | G87: Examining the Spatially Varying Relationships between Landslide Susceptibility and Conditioning Factors Using a Geographical Random Forest Approach: A Case Study in Liangshan, China | H87: Remote Sensing | I87: 10.3390/rs15061513
A88: R0032 | B88: include | D88: 10 | E88: Karasiak 2019 Remote Sens: tree species SVM, Formosat-2; LOO vs spatial LOO (340 m); OA per year (Table 2). Primary year arbitrary (2013). | F88: 2019 | G88: Statistical stability and spatial instability in mapping forest tree species by comparing 9 years of satellite image time series | H88: Remote Sensing | I88: 10.3390/rs11212512
A89: R0035 | B89: include | D89: 54 | E89: Radocaj 2025 Eng: maize yield 3 parcels; RF regular vs k-means spatial 10-fold x5 (Table 3). BGLM not extracted. | F89: 2025 | G89: A Comparative Assessment of Regular and Spatial Cross-Validation in Subfield Machine Learning Prediction of Maize Yield from Sentinel-2 Phenology | H89: Eng | I89: 10.3390/eng6100270
A90: R0041 | B90: include | D90: 27 | E90: Bueno 2023 Water: glacier mapping 9 Peruvian Cordilleras; GBM, kNN, RF (LR excluded); non-spatial vs k-means spatial 5-fold x50; independent SRS test. Only MCC reported (outside v2 metric list, kept native); per-model medians digitised from Fig. 4. | F90: 2023 | G90: A Comparative Analysis of Machine Learning Techniques for National Glacier Mapping: Evaluating Performance through Spatial Cross-Validation in Perú | H90: Water (Switzerland) | I90: 10.3390/w15244214
A91: R0056 | B91: include | D91: 24 | E91: Koehler 2025 Front Earth Sci: periglacial block/talus slopes (cryosphere; borderline geomorphology, not mining/geology); RF random 10-fold vs leave-one-key-site-out; AUC/accuracy from Fig. 6 and text. | F91: 2025 | G91: Expanding cryospheric landform inventories – quantitative approaches for underestimated periglacial block- and talus slopes in the Dry Andes of Argentina | H91: Frontiers in Earth Science | I91: 10.3389/feart.2025.1534410
A92: R0057 | B92: include | D92: 12 | E92: Random 70/30 stratified test vs leave-one-district-out (6) for RF/XGB/GBM gully susceptibility; Tables 8-9. | F92: 2026 | G92: Multi-Model Machine Learning Mapping of Gully Erosion Susceptibility in the Heihe Region of the Xiaoxingán Mountains, China | H92: Remote Sensing | I92: 10.3390/rs18111844
A93: R0077 | B93: include | D93: 10 | E93: CNN-Transformer soil class: random 7:3 split vs 5-fold 10 km spatial-block CV (OA only, Discussion); plus buffer-filtered and distance-band test subsets (primary=no). | F93: 2026 | G93: A Study on Multi-Tier Categorical Soil Classification Based on Decoupled Parallel Deep Learning: A Case Study in the Southern Foothills of Qilian Mountains | H93: Land | I93: 10.3390/land15091657
... A105: R0166 | B105: include | D105: 6 | E105: Crop type RF, 7 German sites; within-site parcel-disjoint random holdout (reference system) vs leave-site-out (target system); medians digitised from Fig. 6. | F105: 2022 | G105: Spatial Transferability of Random Forest Models for Crop Type Classification Using Sentinel-1 and Sentinel-2 | H105: Remote Sensing | I105: 10.3390/rs14061493
A106: R0249 | B106: exclude | C106: E5 | D106: 0 | E106: Block-CV vs random 70/30 hold-out RF LULC (eThekwini, Nelson Mandela Bay); main text gives only deltas (OA delta EM S1 -3.22, S2 -1.31; NMBM S1 -2.43, S2 -0.08; NMBM macro-F1 -5.60/-3.30). Absolute values in Supplementary Tables C5/C6 (not in PDF) - retrieve supplement to include. | F106: 2026 | G106: Enhancing land cover classification in the heterogeneous landscape by integrating auxiliary data with Sentinel-2 imagery using the random forest algorithm | H106: Frontiers in Remote Sensing | I106: 10.3389/frsen.2025.1697897
A107: R0310 | B107: include | D107: 3 | E107: Mass movement susceptibility China; TBMM (GPBoost) only ML model; 3 datasets (debris flow, rockfall, landslide) S0310a-c; median AUROC 10x10-fold CV vs SCV (Table 4). GLMM/GAMM not extracted. | F107: 2022 | G107: Comparison of Three Mixed-Effects Models for Mass Movement Susceptibility Mapping Based on Incomplete Inventory in China | H107: Remote Sensing | I107: 10.3390/rs14236068
A108: R0317 | B108: exclude | C108: E2 | D108: 0 | E108: Oilseed flax county yield CNN-Informer; chronological split and county-based spatial 5-fold CV (combined with temporal holdout); no random CV. | F108: 2026 | G108: Oilseed Flax Yield Prediction in Arid Gansu, China Using a CNN–Informer Model and Multi-Source Spatio-Temporal Data | H108: Remote Sensing | I108: 10.3390/rs18010181
A109: R0353 | B109: include | D109: 2 | E109: Wheat yield Kazakhstan district-year; XGBoost random 5-fold vs district leave-group-out (Fig. 6). Other models spatial CV only. | F109: 2026 | G109: Beyond Vegetation Indices: Winter Solar Radiation and Soil Properties Drive Wheat Yield Prediction in the Arid Steppes of Kazakhstan Using Gradient Boosting | H109: Agriculture (Switzerland) | I109: 10.3390/agriculture16070782
A110: R0382 | B110: include | D110: 6 | E110: Crop classification Donggang; prior-guided CNN, XGBoost, unguided CNN; random 7:3 vs 0.02 deg block 5-fold (Table 6). | F110: 2026 | G110: Knowledge-Guided Multi-Source Time-Series Approach for Spatially Robust Crop Type Classification | H110: Applied Sciences (Switzerland) | I110: 10.3390/app16094194
A111: R0396 | B111: include | D111: 1 | E111: Impervious surface RF on AlphaEarth embeddings; random 70/30 vs leave-one-city-out F1 (Tables 3, 9). Repeated random vs 0.05 deg block holdouts only as IoU (in notes). | F111: 2026 | G111: Impact of Impervious Surface Expansion on Urban Thermal Environment Across Tropical Southeast Asian Megacities: Reliable Assessment Through Foundation Model Embeddings | H111: Earth (Switzerland) | I111: 10.3390/earth7030076
...

Sheet 3_Extraction_raw
A1: record_id | B1: study_id | C1: first_author | D1: year | E1: doi | F1: journal | G1: country | H1: domain | I1: target_variable | J1: task | K1: sampling_design | L1: n_samples | M1: study_area_km2 | N1: model | O1: spatial_cv_type | P1: random_cv_type | Q1: block_or_buffer_size_m | R1: autocorrelation_range_m | S1: n_folds | T1: metric | U1: value_random | V1: value_spatial | W1: sd_random | X1: sd_spatial | Y1: independent_validation | Z1: value_independent | AA1: source_location | AB1: digitised | AC1: open_data | AD1: open_code | AE1: notes | AF1: primary | AG1: variant | AH1: random_cv_alt | AI1: metric_aggregation | AJ1: n_folds_random | AK1: n_folds_spatial | AL1: n_repeats | AM1: block_size_unit | AN1: independent_type | AO1: published_doi
A2: R0001 | B2: S0001 | C2: Ploton | D2: 2020 | E2: 10.1038/s41467-020-18321-y | F2: Nature Communications | G2: Central Africa (Gabon, Cameroon, Congo, CAR, DRC) | H2: vegetation | I2: aboveground forest biomass (1-km pixels) | J2: regression | K2: clustered | L2: 28225 | N2: RF | O2: cluster | P2: random_kfold | Q2: 150000 | R2: 120000 | S2: 10 random / 44 spatial | T2: R2 | U2: 0.53 | V2: 0.14 | Y2: no | AA2: p.4-5 text; Fig. 4 | AB2: no | AC2: yes | AD2: yes | AE2: Hierarchical clustering of coordinates, cluster height 150 km. R2 = squared Pearson r. Inventory plots in logging concessions. RF on coordinates only (RFXY) not extracted. | AF2: yes | AJ2: 10 random / 44 spatial
A3: R0001 | B3: S0001 | C3: Ploton | D3: 2020 | E3: 10.1038/s41467-020-18321-y | F3: Nature Communications | G3: Central Africa (Gabon, Cameroon, Congo, CAR, DRC) | H3: vegetation | I3: aboveground forest biomass (1-km pixels) | J3: regression | K3: clustered | L3: 28225 | N3: RF | O3: cluster | P3: random_kfold | Q3: 150000 | R3: 120000 | S3: 10 random / 44 spatial | T3: RMSE | U3: 56.5 | V3: 77.5 | Y3: no | AA3: p.4-5 text | AB3: no | AC3: yes | AD3: yes | AE3: RMSPE in Mg/ha. Null (intercept-only) model RMSPE = 82 Mg/ha. | AF3: yes | AJ3: 10 random / 44 spatial
A4: R0001 | B4: S0001 | C4: Ploton | D4: 2020 | E4: 10.1038/s41467-020-18321-y | F4: Nature Communications | G4: Central Africa (Gabon, Cameroon, Congo, CAR, DRC) | H4: vegetation | I4: aboveground forest biomass (1-km pixels) | J4: regression | K4: clustered | L4: 28225 | N4: RF | O4: buffer_LOO | P4: LOO | Q4: 150000 | R4: 120000 | S4: LOO (100 test obs x 10 reps) | T4: R2 | U4: 0.50 | V4: 0.03 | Y4: no | AA4: p.5 text; Fig. 5a | AB4: yes | AC4: yes | AD4: yes | AE4: Random = B-LOO with 0 km buffer (text). Spatial = 150 km buffer read from Fig. 5a (approx.). R2 ~0.15 at 50 km. | AF4: yes | AJ4: LOO (100 test obs x 10 reps)
A5: R0001 | B5: S0001 | C5: Ploton | D5: 2020 | E5: 10.1038/s41467-020-18321-y | F5: Nature Communications | G5: Central Africa (Gabon, Cameroon, Congo, CAR, DRC) | H5: vegetation | I5: aboveground forest biomass (1-km pixels) | J5: regression | K5: clustered | L5: 28225 | N5: RF | O5: buffer_LOO | P5: LOO | Q5: 150000 | R5: 120000 | S5: LOO (100 test obs x 10 reps) | T5: RMSE | U5: 58 | V5: 83 | Y5: no | AA5: Fig. 5b | AB5: yes | AC5: yes | AD5: yes | AE5: RMSPE in Mg/ha, both read from Fig. 5b (approx.): 0 km vs 150 km buffer. | AF5: yes | AJ5: LOO (100 test obs x 10 reps)
A6: R0002 | B6: S0002 | C6: Schratz | D6: 2018 | E6: arXiv:1803.11266 | F6: arXiv preprint (later Ecological Modelling 2019) | G6: Spain (Basque Country) | H6: species_distribution | I6: Diplodia sapinea infection of Pinus radiata trees (presence/absence) | J6: classification | K6: unknown | L6: 926 | M6: 7355 | N6: RF | O6: cluster | P6: repeated_kfold | S6: 5 (x100 repetitions) | T6: AUC | U6: 0.912 | V6: 0.699 | Y6: no | AA6: Table 2 | AB6: no | AC6: no | AD6: yes | AE6: k-means coordinate clustering. Matched setups: non-spatial/non-spatial vs spatial/spatial tuning. no tuning: 0.913 vs 0.704. GLM/GAM not extracted. | AF6: yes | AJ6: 5 (x100 repetitions)
A7: R0002 | B7: S0002 | C7: Schratz | D7: 2018 | E7: arXiv:1803.11266 | F7: arXiv preprint (later Ecological Modelling 2019) | G7: Spain (Basque Country) | H7: species_distribution | I7: Diplodia sapinea infection of Pinus radiata trees (presence/absence) | J7: classification | K7: unknown | L7: 926 | M7: 7355 | N7: GBM | O7: cluster | P7: repeated_kfold | S7: 5 (x100 repetitions) | T7: AUC | U7: 0.908 | V7: 0.671 | Y7: no | AA7: Table 2 | AB7: no | AC7: no | AD7: yes | AE7: k-means coordinate clustering. Matched setups: non-spatial/non-spatial vs spatial/spatial tuning. BRT (gbm); no tuning: 0.792 vs 0.583. GLM/GAM not extracted. | AF7: yes | AJ7: 5 (x100 repetitions)
A8: R0002 | B8: S0002 | C8: Schratz | D8: 2018 | E8: arXiv:1803.11266 | F8: arXiv preprint (later Ecological Modelling 2019) | G8: Spain (Basque Country) | H8: species_distribution | I8: Diplodia sapinea infection of Pinus radiata trees (presence/absence) | J8: classification | K8: unknown | L8: 926 | M8: 7355 | N8: SVM | O8: cluster | P8: repeated_kfold | S8: 5 (x100 repetitions) | T8: AUC | U8: 0.878 | V8: 0.650 | Y8: no | AA8: Table 2 | AB8: no | AC8: no | AD8: yes | AE8: k-means coordinate clustering. Matched setups: non-spatial/non-spatial vs spatial/spatial tuning. no tuning: 0.881 vs 0.573. GLM/GAM not extracted. | AF8: yes | AJ8: 5 (x100 repetitions)
A9: R0002 | B9: S0002 | C9: Schratz | D9: 2018 | E9: arXiv:1803.11266 | F9: arXiv preprint (later Ecological Modelling 2019) | G9: Spain (Basque Country) | H9: species_distribution | I9: Diplodia sapinea infection of Pinus radiata trees (presence/absence) | J9: classification | K9: unknown | L9: 926 | M9: 7355 | N9: other | O9: cluster | P9: repeated_kfold | S9: 5 (x100 repetitions) | T9: AUC | U9: 0.872 | V9: 0.624 | Y9: no | AA9: Table 2 | AB9: no | AC9: no | AD9: yes | AE9: k-means coordinate clustering. Matched setups: non-spatial/non-spatial vs spatial/spatial tuning. WKNN (kknn); no tuning: 0.870 vs 0.635. GLM/GAM not extracted. | AF9: yes | AJ9: 5 (x100 repetitions)
A10: R0005 | B10: S0005a | C10: Meyer | D10: 2019 | E10: arXiv:1908.07805 | F10: arXiv preprint (later Ecological Modelling 2019) | G10: Germany (Marburg Open Forest) | H10: land_cover | I10: land use/land cover (10 classes) | J10: classification | K10: clustered | L10: 185000 | M10: 7.5 | N10: RF | O10: block | P10: random_kfold | S10: 20 | T10: accuracy | U10: 0.99 | V10: 0.71 | Y10: no | AA10: Table 2 | AB10: no | AC10: no | AD10: yes | AE10: Model 1 (all 16 predictors incl. lat/lon), by-fold mean. Random reported as >0.99 (lower bound). Global: >0.99 vs 0.68. Spatial FFS model: 0.89 vs 0.71. | AF10: yes | AJ10: 20
A11: R0005 | B11: S0005a | C11: Meyer | D11: 2019 | E11: arXiv:1908.07805 | F11: arXiv preprint (later Ecological Modelling 2019) | G11: Germany (Marburg Open Forest) | H11: land_cover | I11: land use/land cover (10 classes) | J11: classification | K11: clustered | L11: 185000 | M11: 7.5 | N11: RF | O11: block | P11: random_kfold | S11: 20 | T11: kappa | U11: 0.99 | V11: 0.55 | Y11: no | AA11: Table 2 | AB11: no | AC11: no | AD11: yes | AE11: Model 1, by-fold mean. Random reported as >0.99. 20 equal blocks, size not stated (~600 m). Global: >0.99 vs 0.61. Spatial FFS: 0.87 vs 0.56. | AF11: yes | AJ11: 20
A12: R0005 | B12: S0005b | C12: Meyer | D12: 2019 | E12: arXiv:1908.07805 | F12: arXiv preprint (later Ecological Modelling 2019) | G12: Germany (Marburg Open Forest) | H12: vegetation | I12: leaf area index (lidar-derived) | J12: regression | K12: clustered | L12: 824 | M12: 7.5 | N12: RF | O12: leave_location_out | P12: random_kfold | S12: 11 | T12: RMSE | U12: 0.96 | V12: 1.25 | Y12: no | AA12: Table 3 | AB12: no | AC12: no | AD12: yes | AE12: Model 1 (all 15 predictors), by-fold mean; LAI units (m2/m2). Leave-one-cluster-out, 11 clusters of 60 m radius. Global: 0.97 vs 1.75. Spatial FFS: 1.12 vs 1.20. | AF12: yes | AJ12: 11
A13: R0005 | B13: S0005b | C13: Meyer | D13: 2019 | E13: arXiv:1908.07805 | F13: arXiv preprint (later Ecological Modelling 2019) | G13: Germany (Marburg Open Forest) | H13: vegetation | I13: leaf area index (lidar-derived) | J13: regression | K13: clustered | L13: 824 | M13: 7.5 | N13: RF | O13: leave_location_out | P13: random_kfold | S13: 11 | T13: R2 | U13: 0.86 | V13: 0.58 | Y13: no | AA13: Table 3 | AB13: no | AC13: no | AD13: yes | AE13: Model 1, GLOBAL R2 (authors say by-fold R2 unreliable: 0.87 vs 0.07). Spatial FFS global: 0.81 vs 0.63. | AF13: yes | AJ13: 11
A14: R0009 | B14: S0009 | C14: Kattenborn | D14: 2022 | E14: 10.1016/j.ophoto.2022.100018 | F14: ISPRS Open Journal of Photogrammetry and Remote Sensing | G14: Germany (Black Forest) | H14: vegetation | I14: tree species (semantic segmentation of UAV RGB tiles) | J14: classification | K14: clustered | L14: 10 training sites (~1500 tiles each); 7 test sites | M14: 3600 | N14: CNN | O14: leave_location_out | P14: random_split | Q14: 100 | S14: 5 repetitions | T14: F1 | U14: 0.71 | V14: 0.47 | Y14: no | AA14: Fig. 3; p.4 text | AB14: yes | AC14: yes | AD14: yes | AE14: U-net, no augmentation; boxplot medians read from Fig. 3. Random = 80/20 tiles within training sites; spatial = 7 unseen 100x100 m sites. Text optimism 27.9%. SAC flattens ~20 m. | AF14: yes | AJ14: 5 repetitions
A15: R0009 | B15: S0009 | C15: Kattenborn | D15: 2022 | E15: 10.1016/j.ophoto.2022.100018 | F15: ISPRS Open Journal of Photogrammetry and Remote Sensing | G15: Germany (Black Forest) | H15: vegetation | I15: tree species (semantic segmentation of UAV RGB tiles) | J15: classification | K15: clustered | L15: 25 training sites (~1500 tiles each); 7 test sites | M15: 3600 | N15: CNN | O15: leave_location_out | P15: random_split | Q15: 100 | S15: 5 repetitions | T15: F1 | U15: 0.74 | V15: 0.59 | Y15: no | AA15: Fig. 3; p.4 text | AB15: yes | AC15: yes | AD15: yes | AE15: U-net, no augmentation; boxplot medians read from Fig. 3. Random = 80/20 tiles within training sites; spatial = 7 unseen 100x100 m sites. Text optimism 17.7%. SAC flattens ~20 m. | AF15: yes | AJ15: 5 repetitions
A16: R0009 | B16: S0009 | C16: Kattenborn | D16: 2022 | E16: 10.1016/j.ophoto.2022.100018 | F16: ISPRS Open Journal of Photogrammetry and Remote Sensing | G16: Germany (Black Forest) | H16: vegetation | I16: tree species (semantic segmentation of UAV RGB tiles) | J16: classification | K16: clustered | L16: 40 training sites (~1500 tiles each); 7 test sites | M16: 3600 | N16: CNN | O16: leave_location_out | P16: random_split | Q16: 100 | S16: 5 repetitions | T16: F1 | U16: 0.76 | V16: 0.65 | Y16: no | AA16: Fig. 3; p.4 text | AB16: yes | AC16: yes | AD16: yes | AE16: U-net, no augmentation; boxplot medians read from Fig. 3. Random = 80/20 tiles within training sites; spatial = 7 unseen 100x100 m sites. Text optimism 14.6%. SAC flattens ~20 m. | AF16: yes | AJ16: 5 repetitions
A17: R0013 | B17: S0013 | C17: Gupta | D17: 2021 | E17: 10.1029/2020MS002242 | F17: Journal of Advances in Modeling Earth Systems | G17: Global | H17: soil | I17: log10 saturated hydraulic conductivity (Ksat) | J17: regression | K17: clustered | L17: 6814 | N17: RF | O17: block | P17: repeated_kfold | Q17: 555000 | S17: 5 (x3 repetitions) | T17: RMSE | U17: 0.72 | V17: 1.18 | Y17: no | AA17: Table 2 | AB17: no | AC17: yes | AD17: yes | AE17: Full CoGTF model (28 covariates, mtry 6). 5x5 degree blocks (~555 km at equator). RMSE in log10(cm/day). Soil-only and environment-only subsets also in Table 2. | AF17: yes | AJ17: 5 (x3 repetitions)
A18: R0013 | B18: S0013 | C18: Gupta | D18: 2021 | E18: 10.1029/2020MS002242 | F18: Journal of Advances in Modeling Earth Systems | G18: Global | H18: soil | I18: log10 saturated hydraulic conductivity (Ksat) | J18: regression | K18: clustered | L18: 6814 | N18: RF | O18: block | P18: repeated_kfold | Q18: 555000 | S18: 5 (x3 repetitions) | T18: R2 | U18: 0.66 | V18: 0.10 | Y18: no | AA18: Table 2 | AB18: no | AC18: yes | AD18: yes | AE18: Full CoGTF model (28 covariates, mtry 6). 5x5 degree blocks (~555 km at equator). RMSE in log10(cm/day). Soil-only and environment-only subsets also in Table 2. | AF18: yes | AJ18: 5 (x3 repetitions)
A19: R0013 | B19: S0013 | C19: Gupta | D19: 2021 | E19: 10.1029/2020MS002242 | F19: Journal of Advances in Modeling Earth Systems | G19: Global | H19: soil | I19: log10 saturated hydraulic conductivity (Ksat) | J19: regression | K19: clustered | L19: 6814 | N19: RF | O19: block | P19: repeated_kfold | Q19: 555000 | S19: 5 (x3 repetitions) | T19: CCC | U19: 0.79 | V19: 0.16 | Y19: no | AA19: Table 2 | AB19: no | AC19: yes | AD19: yes | AE19: Full CoGTF model (28 covariates, mtry 6). 5x5 degree blocks (~555 km at equator). RMSE in log10(cm/day). Soil-only and environment-only subsets also in Table 2. | AF19: yes | AJ19: 5 (x3 repetitions)
A20: R0036 | B20: S0036 | C20: Mouret | D20: 2023 | E20: 10.1109/JSTARS.2023.3332420 | F20: IEEE Journal of Selected Topics in Applied Earth Observations and Remote Sensing | G20: France (Centre-Val de Loire) | H20: vegetation | I20: oak dieback status (healthy vs declining plots) | J20: classification | K20: clustered | L20: 2700 | M20: 110000 | N20: RF | O20: buffer_LOO | P20: LOO | Q20: 10000 | S20: LOO (300 reps per year) | T20: balanced_accuracy | U20: 0.745 | V20: 0.68 | Y20: no | AA20: Fig. 10 | AB20: yes | AC20: no | AD20: no | AE20: Raw references, 2 classes, mean all years, both read from Fig. 10. Plot-level LOO, 10 km buffer (20 km similar). Text: BA and OA drop ~5%. | AF20: yes | AJ20: LOO (300 reps per year)
A21: R0036 | B21: S0036 | C21: Mouret | D21: 2023 | E21: 10.1109/JSTARS.2023.3332420 | F21: IEEE Journal of Selected Topics in Applied Earth Observations and Remote Sensing | G21: France (Centre-Val de Loire) | H21: vegetation | I21: oak dieback status (healthy vs declining plots) | J21: classification | K21: clustered | L21: 2700 | M21: 110000 | N21: RF | O21: buffer_LOO | P21: repeated_kfold | Q21: 10000 | S21: 5 (x10 repetitions) | T21: balanced_accuracy | U21: 0.78 | V21: 0.73 | Y21: no | AA21: Table IV; Fig. 10 | AB21: yes | AC21: no | AD21: no | AE21: Expanded references + SMOTE. Random = stratified plot-grouped 5-fold x10 (Table IV, not digitised). Spatial = SLOOCV read from Fig. 10. Different random scheme. | AF21: yes | AJ21: 5 (x10 repetitions)
A22: R0059 | B22: S0059 | C22: Jafari | D22: 2026 | E22: 10.1038/s41598-026-39496-2 | F22: Scientific Reports | G22: Iran (Qazvin plain, Abyek) | H22: soil | I22: soil organic carbon 0-30 cm (%) | J22: regression | K22: probability_random | L22: 281 | M22: 580 | N22: RF | O22: other | P22: repeated_kfold | S22: 10 (x10 repetitions) random; spatial NA | T22: RMSE | U22: 0.17 | V22: 0.16 | Y22: no | AA22: Table 4 | AB22: no | AC22: no | AD22: no | AE22: Scenario 1 vs 3 (classic RF, non-spatial covariates). Spatial CV vaguely described (spatial stratification, spdep/caret). Units SOC %. Stratified random sampling. | AF22: yes | AJ22: 10 (x10 repetitions) random; spatial NA
A23: R0059 | B23: S0059 | C23: Jafari | D23: 2026 | E23: 10.1038/s41598-026-39496-2 | F23: Scientific Reports | G23: Iran (Qazvin plain, Abyek) | H23: soil | I23: soil organic carbon 0-30 cm (%) | J23: regression | K23: probability_random | L23: 281 | M23: 580 | N23: RF | O23: other | P23: repeated_kfold | S23: 10 (x10 repetitions) random; spatial NA | T23: MAE | U23: 0.15 | V23: 0.14 | Y23: no | AA23: Table 4 | AB23: no | AC23: no | AD23: no | AE23: Scenario 1 vs 3 (classic RF, non-spatial covariates). Spatial CV vaguely described (spatial stratification, spdep/caret). Units SOC %. Stratified random sampling. | AF23: yes | AJ23: 10 (x10 repetitions) random; spatial NA
A24: R0059 | B24: S0059 | C24: Jafari | D24: 2026 | E24: 10.1038/s41598-026-39496-2 | F24: Scientific Reports | G24: Iran (Qazvin plain, Abyek) | H24: soil | I24: soil organic carbon 0-30 cm (%) | J24: regression | K24: probability_random | L24: 281 | M24: 580 | N24: RF | O24: other | P24: repeated_kfold | S24: 10 (x10 repetitions) random; spatial NA | T24: R2 | U24: 0.69 | V24: 0.68 | Y24: no | AA24: Table 4 | AB24: no | AC24: no | AD24: no | AE24: Scenario 1 vs 3 (classic RF, non-spatial covariates). Spatial CV vaguely described (spatial stratification, spdep/caret). Units SOC %. Stratified random sampling. | AF24: yes | AJ24: 10 (x10 repetitions) random; spatial NA
A25: R0093 | B25: S0093 | C25: Mohamed | D25: 2026 | E25: 10.1038/s41598-026-57131-y | F25: Scientific Reports | G25: Egypt (western mid-Nile Valley) | H25: hydrology | I25: groundwater delta18O (permil) | J25: regression | K25: unknown | L25: 96 | N25: RF | O25: block | P25: LOO | S25: LOO random / 4 spatial | T25: R2 | U25: 0.82 | V25: 0.50 | Y25: no | AA25: p.10 text; Table 4; Fig. 8 | AB25: no | AC25: no | AD25: no | AE25: 4 longitude-bin blocks. Random 70/30 test R2 0.83. Predictors include longitude; without it spatial R2 0.405. With outliers, spatial R2 0.32. | AF25: yes | AJ25: LOO random / 4 spatial
A26: R0093 | B26: S0093 | C26: Mohamed | D26: 2026 | E26: 10.1038/s41598-026-57131-y | F26: Scientific Reports | G26: Egypt (western mid-Nile Valley) | H26: hydrology | I26: groundwater delta18O (permil) | J26: regression | K26: unknown | L26: 96 | N26: GBM | O26: block | P26: LOO | S26: LOO random / 4 spatial | T26: R2 | U26: 0.70 | V26: 0.41 | Y26: no | AA26: p.10 text; Table 4; Fig. 8 | AB26: no | AC26: no | AD26: no | AE26: GBR. LOOCV 0.70 (text). Random 70/30 test R2 0.82 in Table 4, but text says 0.80. Lasso (0.76 vs 0.45) not extracted. | AF26: yes | AJ26: LOO random / 4 spatial
A27: R0025 | B27: S0025 | C27: Bjerre | D27: 2022 | E27: 10.1016/j.jhydrol.2022.128177 | F27: Journal of Hydrology | G27: Denmark (Storaa catchment) | H27: hydrology | I27: drainage fraction (RF metamodel emulating Mike-SHE groundwater model output) | J27: regression | K27: regular_grid | L27: 77333 | M27: 1000 | N27: RF | O27: leave_location_out | P27: random_split | T27: R2 | U27: 0.79 | V27: 0.421 | X27: 0.155 | Y27: no | AA27: Fig. 5; Fig. 6 (printed R2 per sub-basin); p.6 text | AB27: no | AC27: yes | AD27: yes | AE27: Mappable covariates only (same in both). Random = single 80/20 split holdout (R2 0.79). Spatial = 9 sub-basin holdouts (leave-one-sub-basin-out), R2 printed in Fig. 6 panels: 0.60,0.44,0.59,0.52,0.30,0.43,0.15,0.26,0.50; mean and SD computed by extractor (not reported by authors). Text range 0.15-0.60. Sub-basins ~110 km2 on average. Response is simulated output of process model on all grid cells (sampling = full grid). All-covariate model (R2 0.85 random) not evaluated with spatial CV. | AF27: yes | AG27: mappable covariates | AH27: OOB (R2 0.79-0.82 across the 10 metamodels) | AI27: mean_of_folds | AJ27: 1 (80/20 split) | AK27: 9 | AN27: none
A28: R0063 | B28: S0063 | C28: Alvarez | D28: 2026 | E28: 10.1007/s10584-026-04160-1 | F28: Climatic Change | G28: Morocco | H28: other | I28: perceived agricultural climate vulnerability (overall), 4 classes | J28: classification | K28: unknown | L28: 3591 | N28: RF | O28: block | P28: random_kfold | Q28: 50000 | T28: F1 | U28: 0.60 | V28: 0.53 | Y28: no | AA28: Table 1 | AB28: no | AC28: on_request | AD28: no | AE28: Borderline domain: farmer-perceived climate vulnerability class (low/medium/high/not aware) from survey, predictors = survey + EO (NDVI, ERA5 CV). Macro-F1. Standard CV scheme not fully described (assumed random k-fold). Spatial = 50 km grid blocks, GroupKFold k=5, OOF predictions. Sampling: "random sampling facilitated by local farmer collaborators" (unclear). Block sizes 25/100 km and accuracy only in Suppl. Tables S2-S3 (not available). SMOTE/ROS within training folds. Logit and majority-class baselines not extracted. | AF28: yes | AG28: combined survey + EO predictors | AI28: pooled | AK28: 5 | AM28: km | AN28: none
A29: R0063 | B29: S0063 | C29: Alvarez | D29: 2026 | E29: 10.1007/s10584-026-04160-1 | F29: Climatic Change | G29: Morocco | H29: other | I29: perceived agricultural climate vulnerability (overall), 4 classes | J29: classification | K29: unknown | L29: 3591 | N29: XGB | O29: block | P29: random_kfold | Q29: 50000 | T29: F1 | U29: 0.60 | V29: 0.53 | Y29: no | AA29: Table 1 | AB29: no | AC29: on_request | AD29: no | AE29: Borderline domain: farmer-perceived climate vulnerability class (low/medium/high/not aware) from survey, predictors = survey + EO (NDVI, ERA5 CV). Macro-F1. Standard CV scheme not fully described (assumed random k-fold). Spatial = 50 km grid blocks, GroupKFold k=5, OOF predictions. Sampling: "random sampling facilitated by local farmer collaborators" (unclear). Block sizes 25/100 km and accuracy only in Suppl. Tables S2-S3 (not available). SMOTE/ROS within training folds. Logit and majority-class baselines not extracted. | AF29: yes | AG29: combined survey + EO predictors | AI29: pooled | AK29: 5 | AM29: km | AN29: none
A30: R0063 | B30: S0063 | C30: Alvarez | D30: 2026 | E30: 10.1007/s10584-026-04160-1 | F30: Climatic Change | G30: Morocco | H30: other | I30: perceived agricultural climate vulnerability (winter), 4 classes | J30: classification | K30: unknown | L30: 3591 | N30: RF | O30: block | P30: random_kfold | Q30: 50000 | T30: F1 | U30: 0.64 | V30: 0.69 | Y30: no | AA30: Table 1 | AB30: no | AC30: on_request | AD30: no | AE30: Borderline domain: farmer-perceived climate vulnerability class (low/medium/high/not aware) from survey, predictors = survey + EO (NDVI, ERA5 CV). Macro-F1. Standard CV scheme not fully described (assumed random k-fold). Spatial = 50 km grid blocks, GroupKFold k=5, OOF predictions. Sampling: "random sampling facilitated by local farmer collaborators" (unclear). Block sizes 25/100 km and accuracy only in Suppl. Tables S2-S3 (not available). SMOTE/ROS within training folds. Logit and majority-class baselines not extracted. | AF30: yes | AG30: combined survey + EO predictors | AI30: pooled | AK30: 5 | AM30: km | AN30: none
A31: R0063 | B31: S0063 | C31: Alvarez | D31: 2026 | E31: 10.1007/s10584-026-04160-1 | F31: Climatic Change | G31: Morocco | H31: other | I31: perceived agricultural climate vulnerability (winter), 4 classes | J31: classification | K31: unknown | L31: 3591 | N31: XGB | O31: block | P31: random_kfold | Q31: 50000 | T31: F1 | U31: 0.63 | V31: 0.68 | Y31: no | AA31: Table 1 | AB31: no | AC31: on_request | AD31: no | AE31: Borderline domain: farmer-perceived climate vulnerability class (low/medium/high/not aware) from survey, predictors = survey + EO (NDVI, ERA5 CV). Macro-F1. Standard CV scheme not fully described (assumed random k-fold). Spatial = 50 km grid blocks, GroupKFold k=5, OOF predictions. Sampling: "random sampling facilitated by local farmer collaborators" (unclear). Block sizes 25/100 km and accuracy only in Suppl. Tables S2-S3 (not available). SMOTE/ROS within training folds. Logit and majority-class baselines not extracted. | AF31: yes | AG31: combined survey + EO predictors | AI31: pooled | AK31: 5 | AM31: km | AN31: none
A32: R0063 | B32: S0063 | C32: Alvarez | D32: 2026 | E32: 10.1007/s10584-026-04160-1 | F32: Climatic Change | G32: Morocco | H32: other | I32: perceived agricultural climate vulnerability (summer), 4 classes | J32: classification | K32: unknown | L32: 3591 | N32: RF | O32: block | P32: random_kfold | Q32: 50000 | T32: F1 | U32: 0.76 | V32: 0.72 | Y32: no | AA32: Table 1 | AB32: no | AC32: on_request | AD32: no | AE32: Borderline domain: farmer-perceived climate vulnerability class (low/medium/high/not aware) from survey, predictors = survey + EO (NDVI, ERA5 CV). Macro-F1. Standard CV scheme not fully described (assumed random k-fold). Spatial = 50 km grid blocks, GroupKFold k=5, OOF predictions. Sampling: "random sampling facilitated by local farmer collaborators" (unclear). Block sizes 25/100 km and accuracy only in Suppl. Tables S2-S3 (not available). SMOTE/ROS within training folds. Logit and majority-class baselines not extracted. | AF32: yes | AG32: combined survey + EO predictors | AI32: pooled | AK32: 5 | AM32: km | AN32: none
A33: R0063 | B33: S0063 | C33: Alvarez | D33: 2026 | E33: 10.1007/s10584-026-04160-1 | F33: Climatic Change | G33: Morocco | H33: other | I33: perceived agricultural climate vulnerability (summer), 4 classes | J33: classification | K33: unknown | L33: 3591 | N33: XGB | O33: block | P33: random_kfold | Q33: 50000 | T33: F1 | U33: 0.71 | V33: 0.71 | Y33: no | AA33: Table 1 | AB33: no | AC33: on_request | AD33: no | AE33: Borderline domain: farmer-perceived climate vulnerability class (low/medium/high/not aware) from survey, predictors = survey + EO (NDVI, ERA5 CV). Macro-F1. Standard CV scheme not fully described (assumed random k-fold). Spatial = 50 km grid blocks, GroupKFold k=5, OOF predictions. Sampling: "random sampling facilitated by local farmer collaborators" (unclear). Block sizes 25/100 km and accuracy only in Suppl. Tables S2-S3 (not available). SMOTE/ROS within training folds. Logit and majority-class baselines not extracted. | AF33: yes | AG33: combined survey + EO predictors | AI33: pooled | AK33: 5 | AM33: km | AN33: none
A34: R0069 | B34: S0069a | C34: Petrovic | D34: 2026 | E34: 10.1016/j.jafr.2026.102662 | F34: Journal of Agriculture and Food Research | G34: Czech Republic | H34: crop_yield | I34: barley yield (NUTS-3 region x year) | J34: regression | K34: unknown | L34: 126 | M34: 78866 | N34: GBM | O34: leave_location_out | P34: random_split | T34: R2 | U34: 0.4456 | V34: 0.3193 | W34: 0.3340 | X34: 0.2288 | Y34: no | Z34: 0.2866 | AA34: Table 2 | AB34: no | AC34: on_request | AD34: no | AE34: Regional yields of all 14 NUTS-3 regions 2016-2024 (census, not a sample; sampling_design unknown). Predictors: ERA5-Land/SMAP meteorology by phenological period + Year + one-hot Region. Default hyperparameters. Random = 10 repeated random 70/30 splits; spatial = 10 grouped folds with 4 regions held out. SD across folds. Temporal holdout (2022-2024) also in table (value_independent). GB = sklearn GradientBoostingRegressor. R2 reported in % in paper; converted to proportion. value_independent = temporal holdout (train 2016-2021, test 2022-2024); minus signs for SVR rapeseed/rye in Table 2 garbled in PDF text (read as negative where layout shows sign glyph). | AF34: yes | AG34: with Year feature (main) | AI34: mean_of_folds | AJ34: 10 (repeated 70/30 splits) | AK34: 10 (4 of 14 regions held out per fold) | AM34: site | AN34: temporal
A35: R0069 | B35: S0069a | C35: Petrovic | D35: 2026 | E35: 10.1016/j.jafr.2026.102662 | F35: Journal of Agriculture and Food Research | G35: Czech Republic | H35: crop_yield | I35: barley yield (NUTS-3 region x year) | J35: regression | K35: unknown | L35: 126 | M35: 78866 | N35: GBM | O35: leave_location_out | P35: random_split | T35: RMSE | U35: 3.80 | V35: 4.42 | W35: 0.98 | X35: 0.65 | Y35: no | Z35: 4.57 | AA35: Table 2 | AB35: no | AC35: on_request | AD35: no | AE35: Regional yields of all 14 NUTS-3 regions 2016-2024 (census, not a sample; sampling_design unknown). Predictors: ERA5-Land/SMAP meteorology by phenological period + Year + one-hot Region. Default hyperparameters. Random = 10 repeated random 70/30 splits; spatial = 10 grouped folds with 4 regions held out. SD across folds. Temporal holdout (2022-2024) also in table (value_independent). GB = sklearn GradientBoostingRegressor. Normalised RMSE (nRMSE, % of mean observed yield in test set), not absolute RMSE. value_independent = temporal holdout (train 2016-2021, test 2022-2024); minus signs for SVR rapeseed/rye in Table 2 garbled in PDF text (read as negative where layout shows sign glyph). | AF35: yes | AG35: with Year feature (main) | AI35: mean_of_folds | AJ35: 10 (repeated 70/30 splits) | AK35: 10 (4 of 14 regions held out per fold) | AM35: site | AN35: temporal
A36: R0069 | B36: S0069a | C36: Petrovic | D36: 2026 | E36: 10.1016/j.jafr.2026.102662 | F36: Journal of Agriculture and Food Research | G36: Czech Republic | H36: crop_yield | I36: barley yield (NUTS-3 region x year) | J36: regression | K36: unknown | L36: 126 | M36: 78866 | N36: GBM | O36: leave_location_out | P36: random_split | T36: MAE | U36: 3.13 | V36: 3.60 | W36: 0.88 | X36: 0.53 | Y36: no | Z36: 4.06 | AA36: Table 2 | AB36: no | AC36: on_request | AD36: no | AE36: Regional yields of all 14 NUTS-3 regions 2016-2024 (census, not a sample; sampling_design unknown). Predictors: ERA5-Land/SMAP meteorology by phenological period + Year + one-hot Region. Default hyperparameters. Random = 10 repeated random 70/30 splits; spatial = 10 grouped folds with 4 regions held out. SD across folds. Temporal holdout (2022-2024) also in table (value_independent). GB = sklearn GradientBoostingRegressor. Normalised MAE (nMAE, % of mean observed yield in test set), not absolute MAE. value_independent = temporal holdout (train 2016-2021, test 2022-2024); minus signs for SVR rapeseed/rye in Table 2 garbled in PDF text (read as negative where layout shows sign glyph). | AF36: yes | AG36: with Year feature (main) | AI36: mean_of_folds | AJ36: 10 (repeated 70/30 splits) | AK36: 10 (4 of 14 regions held out per fold) | AM36: site | AN36: temporal
A37: R0069 | B37: S0069a | C37: Petrovic | D37: 2026 | E37: 10.1016/j.jafr.2026.102662 | F37: Journal of Agriculture and Food Research | G37: Czech Republic | H37: crop_yield | I37: barley yield (NUTS-3 region x year) | J37: regression | K37: unknown | L37: 126 | M37: 78866 | N37: RF | O37: leave_location_out | P37: random_split | T37: R2 | U37: 0.4321 | V37: 0.2980 | W37: 0.2431 | X37: 0.3237 | Y37: no | Z37: 0.1435 | AA37: Table 2 | AB37: no | AC37: on_request | AD37: no | AE37: Regional yields of all 14 NUTS-3 regions 2016-2024 (census, not a sample; sampling_design unknown). Predictors: ERA5-Land/SMAP meteorology by phenological period + Year + one-hot Region. Default hyperparameters. Random = 10 repeated random 70/30 splits; spatial = 10 grouped folds with 4 regions held out. SD across folds. Temporal holdout (2022-2024) also in table (value_independent). R2 reported in % in paper; converted to proportion. value_independent = temporal holdout (train 2016-2021, test 2022-2024); minus signs for SVR rapeseed/rye in Table 2 garbled in PDF text (read as negative where layout shows sign glyph). | AF37: yes | AG37: with Year feature (main) | AI37: mean_of_folds | AJ37: 10 (repeated 70/30 splits) | AK37: 10 (4 of 14 regions held out per fold) | AM37: site | AN37: temporal
A38: R0069 | B38: S0069a | C38: Petrovic | D38: 2026 | E38: 10.1016/j.jafr.2026.102662 | F38: Journal of Agriculture and Food Research | G38: Czech Republic | H38: crop_yield | I38: barley yield (NUTS-3 region x year) | J38: regression | K38: unknown | L38: 126 | M38: 78866 | N38: RF | O38: leave_location_out | P38: random_split | T38: RMSE | U38: 3.95 | V38: 4.45 | W38: 0.83 | X38: 0.86 | Y38: no | Z38: 5.00 | AA38: Table 2 | AB38: no | AC38: on_request | AD38: no | AE38: Regional yields of all 14 NUTS-3 regions 2016-2024 (census, not a sample; sampling_design unknown). Predictors: ERA5-Land/SMAP meteorology by phenological period + Year + one-hot Region. Default hyperparameters. Random = 10 repeated random 70/30 splits; spatial = 10 grouped folds with 4 regions held out. SD across folds. Temporal holdout (2022-2024) also in table (value_independent). Normalised RMSE (nRMSE, % of mean observed yield in test set), not absolute RMSE. value_independent = temporal holdout (train 2016-2021, test 2022-2024); minus signs for SVR rapeseed/rye in Table 2 garbled in PDF text (read as negative where layout shows sign glyph). | AF38: yes | AG38: with Year feature (main) | AI38: mean_of_folds | AJ38: 10 (repeated 70/30 splits) | AK38: 10 (4 of 14 regions held out per fold) | AM38: site | AN38: temporal
A39: R0069 | B39: S0069a | C39: Petrovic | D39: 2026 | E39: 10.1016/j.jafr.2026.102662 | F39: Journal of Agriculture and Food Research | G39: Czech Republic | H39: crop_yield | I39: barley yield (NUTS-3 region x year) | J39: regression | K39: unknown | L39: 126 | M39: 78866 | N39: RF | O39: leave_location_out | P39: random_split | T39: MAE | U39: 3.28 | V39: 3.63 | W39: 0.72 | X39: 0.69 | Y39: no | Z39: 4.44 | AA39: Table 2 | AB39: no | AC39: on_request | AD39: no | AE39: Regional yields of all 14 NUTS-3 regions 2016-2024 (census, not a sample; sampling_design unknown). Predictors: ERA5-Land/SMAP meteorology by phenological period + Year + one-hot Region. Default hyperparameters. Random = 10 repeated random 70/30 splits; spatial = 10 grouped folds with 4 regions held out. SD across folds. Temporal holdout (2022-2024) also in table (value_independent). Normalised MAE (nMAE, % of mean observed yield in test set), not absolute MAE. value_independent = temporal holdout (train 2016-2021, test 2022-2024); minus signs for SVR rapeseed/rye in Table 2 garbled in PDF text (read as negative where layout shows sign glyph). | AF39: yes | AG39: with Year feature (main) | AI39: mean_of_folds | AJ39: 10 (repeated 70/30 splits) | AK39: 10 (4 of 14 regions held out per fold) | AM39: site | AN39: temporal
A40: R0069 | B40: S0069a | C40: Petrovic | D40: 2026 | E40: 10.1016/j.jafr.2026.102662 | F40: Journal of Agriculture and Food Research | G40: Czech Republic | H40: crop_yield | I40: barley yield (NUTS-3 region x year) | J40: regression | K40: unknown | L40: 126 | M40: 78866 | N40: SVM | O40: leave_location_out | P40: random_split | T40: R2 | U40: -0.1387 | V40: -0.1700 | W40: 0.2007 | X40: 0.3190 | Y40: no | Z40: -0.0754 | AA40: Table 2 | AB40: no | AC40: on_request | AD40: no | AE40: Regional yields of all 14 NUTS-3 regions 2016-2024 (census, not a sample; sampling_design unknown). Predictors: ERA5-Land/SMAP meteorology by phenological period + Year + one-hot Region. Default hyperparameters. Random = 10 repeated random 70/30 splits; spatial = 10 grouped folds with 4 regions held out. SD across folds. Temporal holdout (2022-2024) also in table (value_independent). SVR (default RBF) negative R2 in all schemes. R2 reported in % in paper; converted to proportion. value_independent = temporal holdout (train 2016-2021, test 2022-2024); minus signs for SVR rapeseed/rye in Table 2 garbled in PDF text (read as negative where layout shows sign glyph). | AF40: yes | AG40: with Year feature (main) | AI40: mean_of_folds | AJ40: 10 (repeated 70/30 splits) | AK40: 10 (4 of 14 regions held out per fold) | AM40: site | AN40: temporal
A41: R0069 | B41: S0069a | C41: Petrovic | D41: 2026 | E41: 10.1016/j.jafr.2026.102662 | F41: Journal of Agriculture and Food Research | G41: Czech Republic | H41: crop_yield | I41: barley yield (NUTS-3 region x year) | J41: regression | K41: unknown | L41: 126 | M41: 78866 | N41: SVM | O41: leave_location_out | P41: random_split | T41: RMSE | U41: 5.76 | V41: 5.84 | W41: 0.87 | X41: 0.67 | Y41: no | Z41: 5.61 | AA41: Table 2 | AB41: no | AC41: on_request | AD41: no | AE41: Regional yields of all 14 NUTS-3 regions 2016-2024 (census, not a sample; sampling_design unknown). Predictors: ERA5-Land/SMAP meteorology by phenological period + Year + one-hot Region. Default hyperparameters. Random = 10 repeated random 70/30 splits; spatial = 10 grouped folds with 4 regions held out. SD across folds. Temporal holdout (2022-2024) also in table (value_independent). SVR (default RBF) negative R2 in all schemes. Normalised RMSE (nRMSE, % of mean observed yield in test set), not absolute RMSE. value_independent = temporal holdout (train 2016-2021, test 2022-2024); minus signs for SVR rapeseed/rye in Table 2 garbled in PDF text (read as negative where layout shows sign glyph). | AF41: yes | AG41: with Year feature (main) | AI41: mean_of_folds | AJ41: 10 (repeated 70/30 splits) | AK41: 10 (4 of 14 regions held out per fold) | AM41: site | AN41: temporal
A42: R0069 | B42: S0069a | C42: Petrovic | D42: 2026 | E42: 10.1016/j.jafr.2026.102662 | F42: Journal of Agriculture and Food Research | G42: Czech Republic | H42: crop_yield | I42: barley yield (NUTS-3 region x year) | J42: regression | K42: unknown | L42: 126 | M42: 78866 | N42: SVM | O42: leave_location_out | P42: random_split | T42: MAE | U42: 4.80 | V42: 4.90 | W42: 0.77 | X42: 0.57 | Y42: no | Z42: 4.91 | AA42: Table 2 | AB42: no | AC42: on_request | AD42: no | AE42: Regional yields of all 14 NUTS-3 regions 2016-2024 (census, not a sample; sampling_design unknown). Predictors: ERA5-Land/SMAP meteorology by phenological period + Year + one-hot Region. Default hyperparameters. Random = 10 repeated random 70/30 splits; spatial = 10 grouped folds with 4 regions held out. SD across folds. Temporal holdout (2022-2024) also in table (value_independent). SVR (default RBF) negative R2 in all schemes. Normalised MAE (nMAE, % of mean observed yield in test set), not absolute MAE. value_independent = temporal holdout (train 2016-2021, test 2022-2024); minus signs for SVR rapeseed/rye in Table 2 garbled in PDF text (read as negative where layout shows sign glyph). | AF42: yes | AG42: with Year feature (main) | AI42: mean_of_folds | AJ42: 10 (repeated 70/30 splits) | AK42: 10 (4 of 14 regions held out per fold) | AM42: site | AN42: temporal
A43: R0069 | B43: S0069b | C43: Petrovic | D43: 2026 | E43: 10.1016/j.jafr.2026.102662 | F43: Journal of Agriculture and Food Research | G43: Czech Republic | H43: crop_yield | I43: rapeseed yield (NUTS-3 region x year) | J43: regression | K43: unknown | L43: 126 | M43: 78866 | N43: GBM | O43: leave_location_out | P43: random_split | T43: R2 | U43: 0.0895 | V43: -0.4466 | W43: 1.1582 | X43: 1.5100 | Y43: no | Z43: -0.1402 | AA43: Table 2 | AB43: no | AC43: on_request | AD43: no | AE43: Regional yields of all 14 NUTS-3 regions 2016-2024 (census, not a sample; sampling_design unknown). Predictors: ERA5-Land/SMAP meteorology by phenological period + Year + one-hot Region. Default hyperparameters. Random = 10 repeated random 70/30 splits; spatial = 10 grouped folds with 4 regions held out. SD across folds. Temporal holdout (2022-2024) also in table (value_independent). GB = sklearn GradientBoostingRegressor. R2 reported in % in paper; converted to proportion. value_independent = temporal holdout (train 2016-2021, test 2022-2024); minus signs for SVR rapeseed/rye in Table 2 garbled in PDF text (read as negative where layout shows sign glyph). | AF43: yes | AG43: with Year feature (main) | AI43: mean_of_folds | AJ43: 10 (repeated 70/30 splits) | AK43: 10 (4 of 14 regions held out per fold) | AM43: site | AN43: temporal
A44: R0069 | B44: S0069b | C44: Petrovic | D44: 2026 | E44: 10.1016/j.jafr.2026.102662 | F44: Journal of Agriculture and Food Research | G44: Czech Republic | H44: crop_yield | I44: rapeseed yield (NUTS-3 region x year) | J44: regression | K44: unknown | L44: 126 | M44: 78866 | N44: GBM | O44: leave_location_out | P44: random_split | T44: RMSE | U44: 8.11 | V44: 11.51 | W44: 7.04 | X44: 5.15 | Y44: no | Z44: 11.55 | AA44: Table 2 | AB44: no | AC44: on_request | AD44: no | AE44: Regional yields of all 14 NUTS-3 regions 2016-2024 (census, not a sample; sampling_design unknown). Predictors: ERA5-Land/SMAP meteorology by phenological period + Year + one-hot Region. Default hyperparameters. Random = 10 repeated random 70/30 splits; spatial = 10 grouped folds with 4 regions held out. SD across folds. Temporal holdout (2022-2024) also in table (value_independent). GB = sklearn GradientBoostingRegressor. Normalised RMSE (nRMSE, % of mean observed yield in test set), not absolute RMSE. value_independent = temporal holdout (train 2016-2021, test 2022-2024); minus signs for SVR rapeseed/rye in Table 2 garbled in PDF text (read as negative where layout shows sign glyph). | AF44: yes | AG44: with Year feature (main) | AI44: mean_of_folds | AJ44: 10 (repeated 70/30 splits) | AK44: 10 (4 of 14 regions held out per fold) | AM44: site | AN44: temporal
A45: R0069 | B45: S0069b | C45: Petrovic | D45: 2026 | E45: 10.1016/j.jafr.2026.102662 | F45: Journal of Agriculture and Food Research | G45: Czech Republic | H45: crop_yield | I45: rapeseed yield (NUTS-3 region x year) | J45: regression | K45: unknown | L45: 126 | M45: 78866 | N45: GBM | O45: leave_location_out | P45: random_split | T45: MAE | U45: 4.62 | V45: 5.83 | W45: 2.62 | X45: 3.11 | Y45: no | Z45: 10.05 | AA45: Table 2 | AB45: no | AC45: on_request | AD45: no | AE45: Regional yields of all 14 NUTS-3 regions 2016-2024 (census, not a sample; sampling_design unknown). Predictors: ERA5-Land/SMAP meteorology by phenological period + Year + one-hot Region. Default hyperparameters. Random = 10 repeated random 70/30 splits; spatial = 10 grouped folds with 4 regions held out. SD across folds. Temporal holdout (2022-2024) also in table (value_independent). GB = sklearn GradientBoostingRegressor. Normalised MAE (nMAE, % of mean observed yield in test set), not absolute MAE. value_independent = temporal holdout (train 2016-2021, test 2022-2024); minus signs for SVR rapeseed/rye in Table 2 garbled in PDF text (read as negative where layout shows sign glyph). | AF45: yes | AG45: with Year feature (main) | AI45: mean_of_folds | AJ45: 10 (repeated 70/30 splits) | AK45: 10 (4 of 14 regions held out per fold) | AM45: site | AN45: temporal
... A105: R0069 | B105: S0069d | C105: Petrovic | D105: 2026 | E105: 10.1016/j.jafr.2026.102662 | F105: Journal of Agriculture and Food Research | G105: Czech Republic | H105: crop_yield | I105: wheat yield (NUTS-3 region x year) | J105: regression | K105: unknown | L105: 126 | M105: 78866 | N105: SVM | O105: leave_location_out | P105: random_split | T105: MAE | U105: 5.17 | V105: 5.29 | W105: 1.05 | X105: 0.67 | Y105: no | Z105: 3.93 | AA105: Table 3 | AB105: no | AC105: on_request | AD105: no | AE105: Regional yields of all 14 NUTS-3 regions 2016-2024 (census, not a sample; sampling_design unknown). Predictors: ERA5-Land/SMAP meteorology by phenological period + Year + one-hot Region. Default hyperparameters. Random = 10 repeated random 70/30 splits; spatial = 10 grouped folds with 4 regions held out. SD across folds. Temporal holdout (2022-2024) also in table (value_independent). SVR (default RBF) negative R2 in all schemes. Normalised MAE (nMAE, % of mean observed yield in test set), not absolute MAE. value_independent = temporal holdout (train 2016-2021, test 2022-2024); minus signs for SVR rapeseed/rye in Table 2 garbled in PDF text (read as negative where layout shows sign glyph). | AF105: no | AG105: without Year feature | AI105: mean_of_folds | AJ105: 10 (repeated 70/30 splits) | AK105: 10 (4 of 14 regions held out per fold) | AM105: site | AN105: temporal
A106: R0111 | B106: S0111a | C106: Fernandez-Camacho | D106: 2026 | E106: 10.1186/s40249-026-01420-1 | F106: Infectious Diseases of Poverty | G106: Peru (Huayllapata, Cusco) | H106: other | I106: Fasciola hepatica infection presence in households (human) per 50 m hexagon | J106: classification | K106: unknown | L106: 432 | M106: 1 | N106: RF | O106: spatial_kfold_cluster | P106: random_kfold | T106: accuracy | U106: 0.89 | V106: 0.73 | Y106: no | AA106: Table 3 | AB106: no | AC106: yes | AD106: yes | AE106: Borderline domain (environmentally driven parasite infection risk; drone-derived predictors). Hexagon cells (n=419 neg/13 pos, Table 1); all households visited in one community. Random = stratified 5-fold; spatial = neighbouring hexagons grouped into 3 spatial folds (each with >=1 positive); Optuna tuning nested in each scheme. Sensitivity/specificity random 99/88, spatial 99/72 (%). Strong class imbalance: accuracy dominated by negatives. LR and MLP evaluated only with standard CV (not extracted). Data/code: GitHub (stated "will be available"). | AF106: yes | AG106: Literature-based variable selection | AJ106: 5 | AK106: 3 | AM106: n_clusters | AN106: none
A107: R0111 | B107: S0111a | C107: Fernandez-Camacho | D107: 2026 | E107: 10.1186/s40249-026-01420-1 | F107: Infectious Diseases of Poverty | G107: Peru (Huayllapata, Cusco) | H107: other | I107: Fasciola hepatica infection presence in households (human) per 50 m hexagon | J107: classification | K107: unknown | L107: 432 | M107: 1 | N107: XGB | O107: spatial_kfold_cluster | P107: random_kfold | T107: accuracy | U107: 0.87 | V107: 0.69 | Y107: no | AA107: Table 3 | AB107: no | AC107: yes | AD107: yes | AE107: Borderline domain (environmentally driven parasite infection risk; drone-derived predictors). Hexagon cells (n=419 neg/13 pos, Table 1); all households visited in one community. Random = stratified 5-fold; spatial = neighbouring hexagons grouped into 3 spatial folds (each with >=1 positive); Optuna tuning nested in each scheme. Sensitivity/specificity random 54/88, spatial 99/68 (%). Strong class imbalance: accuracy dominated by negatives. LR and MLP evaluated only with standard CV (not extracted). Data/code: GitHub (stated "will be available"). | AF107: yes | AG107: Literature-based variable selection | AJ107: 5 | AK107: 3 | AM107: n_clusters | AN107: none
A108: R0111 | B108: S0111a | C108: Fernandez-Camacho | D108: 2026 | E108: 10.1186/s40249-026-01420-1 | F108: Infectious Diseases of Poverty | G108: Peru (Huayllapata, Cusco) | H108: other | I108: Fasciola hepatica infection presence in households (human) per 50 m hexagon | J108: classification | K108: unknown | L108: 432 | M108: 1 | N108: RF | O108: spatial_kfold_cluster | P108: random_kfold | T108: accuracy | U108: 0.84 | V108: 0.64 | Y108: no | AA108: Table 3 | AB108: no | AC108: yes | AD108: yes | AE108: Borderline domain (environmentally driven parasite infection risk; drone-derived predictors). Hexagon cells (n=419 neg/13 pos, Table 1); all households visited in one community. Random = stratified 5-fold; spatial = neighbouring hexagons grouped into 3 spatial folds (each with >=1 positive); Optuna tuning nested in each scheme. Sensitivity/specificity random 60/85, spatial 60/65 (%). Strong class imbalance: accuracy dominated by negatives. LR and MLP evaluated only with standard CV (not extracted). Data/code: GitHub (stated "will be available"). | AF108: no | AG108: PCA-based variable selection | AJ108: 5 | AK108: 3 | AM108: n_clusters | AN108: none
A109: R0111 | B109: S0111a | C109: Fernandez-Camacho | D109: 2026 | E109: 10.1186/s40249-026-01420-1 | F109: Infectious Diseases of Poverty | G109: Peru (Huayllapata, Cusco) | H109: other | I109: Fasciola hepatica infection presence in households (human) per 50 m hexagon | J109: classification | K109: unknown | L109: 432 | M109: 1 | N109: XGB | O109: spatial_kfold_cluster | P109: random_kfold | T109: accuracy | U109: 0.85 | V109: 0.70 | Y109: no | AA109: Table 3 | AB109: no | AC109: yes | AD109: yes | AE109: Borderline domain (environmentally driven parasite infection risk; drone-derived predictors). Hexagon cells (n=419 neg/13 pos, Table 1); all households visited in one community. Random = stratified 5-fold; spatial = neighbouring hexagons grouped into 3 spatial folds (each with >=1 positive); Optuna tuning nested in each scheme. Sensitivity/specificity random 75/85, spatial 80/71 (%). Strong class imbalance: accuracy dominated by negatives. LR and MLP evaluated only with standard CV (not extracted). Data/code: GitHub (stated "will be available"). | AF109: no | AG109: PCA-based variable selection | AJ109: 5 | AK109: 3 | AM109: n_clusters | AN109: none
A110: R0111 | B110: S0111b | C110: Fernandez-Camacho | D110: 2026 | E110: 10.1186/s40249-026-01420-1 | F110: Infectious Diseases of Poverty | G110: Peru (Huayllapata, Cusco) | H110: other | I110: Fasciola hepatica infection presence in household sheep per 50 m hexagon | J110: classification | K110: unknown | L110: 422 | M110: 1 | N110: RF | O110: spatial_kfold_cluster | P110: random_kfold | T110: accuracy | U110: 0.88 | V110: 0.62 | Y110: no | AA110: Table 3 | AB110: no | AC110: yes | AD110: yes | AE110: Borderline domain (environmentally driven parasite infection risk; drone-derived predictors). Hexagon cells (n=394 neg/28 pos, Table 1); all households visited in one community. Random = stratified 5-fold; spatial = neighbouring hexagons grouped into 3 spatial folds (each with >=1 positive); Optuna tuning nested in each scheme. Sensitivity/specificity random 61/89, spatial 98/61 (%). Strong class imbalance: accuracy dominated by negatives. LR and MLP evaluated only with standard CV (not extracted). Data/code: GitHub (stated "will be available"). | AF110: yes | AG110: Literature-based variable selection | AJ110: 5 | AK110: 3 | AM110: n_clusters | AN110: none
A111: R0111 | B111: S0111b | C111: Fernandez-Camacho | D111: 2026 | E111: 10.1186/s40249-026-01420-1 | F111: Infectious Diseases of Poverty | G111: Peru (Huayllapata, Cusco) | H111: other | I111: Fasciola hepatica infection presence in household sheep per 50 m hexagon | J111: classification | K111: unknown | L111: 422 | M111: 1 | N111: XGB | O111: spatial_kfold_cluster | P111: random_kfold | T111: accuracy | U111: 0.93 | V111: 0.79 | Y111: no | AA111: Table 3 | AB111: no | AC111: yes | AD111: yes | AE111: Borderline domain (environmentally driven parasite infection risk; drone-derived predictors). Hexagon cells (n=394 neg/28 pos, Table 1); all households visited in one community. Random = stratified 5-fold; spatial = neighbouring hexagons grouped into 3 spatial folds (each with >=1 positive); Optuna tuning nested in each scheme. Sensitivity/specificity random 65/93, spatial 99/77 (%). Strong class imbalance: accuracy dominated by negatives. LR and MLP evaluated only with standard CV (not extracted). Data/code: GitHub (stated "will be available"). | AF111: yes | AG111: Literature-based variable selection | AJ111: 5 | AK111: 3 | AM111: n_clusters | AN111: none
A112: R0111 | B112: S0111b | C112: Fernandez-Camacho | D112: 2026 | E112: 10.1186/s40249-026-01420-1 | F112: Infectious Diseases of Poverty | G112: Peru (Huayllapata, Cusco) | H112: other | I112: Fasciola hepatica infection presence in household sheep per 50 m hexagon | J112: classification | K112: unknown | L112: 422 | M112: 1 | N112: RF | O112: spatial_kfold_cluster | P112: random_kfold | T112: accuracy | U112: 0.85 | V112: 0.76 | Y112: no | AA112: Table 3 | AB112: no | AC112: yes | AD112: yes | AE112: Borderline domain (environmentally driven parasite infection risk; drone-derived predictors). Hexagon cells (n=394 neg/28 pos, Table 1); all households visited in one community. Random = stratified 5-fold; spatial = neighbouring hexagons grouped into 3 spatial folds (each with >=1 positive); Optuna tuning nested in each scheme. Sensitivity/specificity random 75/86, spatial 98/75 (%). Strong class imbalance: accuracy dominated by negatives. LR and MLP evaluated only with standard CV (not extracted). Data/code: GitHub (stated "will be available"). | AF112: no | AG112: PCA-based variable selection | AJ112: 5 | AK112: 3 | AM112: n_clusters | AN112: none
A113: R0111 | B113: S0111b | C113: Fernandez-Camacho | D113: 2026 | E113: 10.1186/s40249-026-01420-1 | F113: Infectious Diseases of Poverty | G113: Peru (Huayllapata, Cusco) | H113: other | I113: Fasciola hepatica infection presence in household sheep per 50 m hexagon | J113: classification | K113: unknown | L113: 422 | M113: 1 | N113: XGB | O113: spatial_kfold_cluster | P113: random_kfold | T113: accuracy | U113: 0.85 | V113: 0.78 | Y113: no | AA113: Table 3 | AB113: no | AC113: yes | AD113: yes | AE113: Borderline domain (environmentally driven parasite infection risk; drone-derived predictors). Hexagon cells (n=394 neg/28 pos, Table 1); all households visited in one community. Random = stratified 5-fold; spatial = neighbouring hexagons grouped into 3 spatial folds (each with >=1 positive); Optuna tuning nested in each scheme. Sensitivity/specificity random 68/86, spatial 95/77 (%). Strong class imbalance: accuracy dominated by negatives. LR and MLP evaluated only with standard CV (not extracted). Data/code: GitHub (stated "will be available"). | AF113: no | AG113: PCA-based variable selection | AJ113: 5 | AK113: 3 | AM113: n_clusters | AN113: none
A114: R0113 | B114: S0113 | C114: Chand | D114: 2026 | E114: 10.1038/s41598-026-57382-9 | F114: Scientific Reports | G114: Pakistan (Sindh) | H114: climate | I114: annual temperature anomaly per district (deg C) | J114: regression | K114: unknown | L114: 968 | N114: GBM | O114: leave_location_out | P114: random_kfold | T114: R2 | U114: 0.917 | V114: 0.911 | W114: 0.009 | X114: 0.118 | Y114: no | Z114: 0.445 | AA114: Table 4 | AB114: no | AC114: yes | AD114: no | AE114: Article in Press (unedited). 22 districts x 44 years (1981-2024). Same GB hyperparameters in both CVs. Leave-one-district-out. Inconsistencies: Table 3/abstract LODO R2 0.914 +/- 0.098, text says random 5-fold R2 ~0.93; Table 4 values used. Temporal blocked (train <=2015) R2 0.445, RMSE 0.479 -> value_independent. Predictors include temporal trend/CO2 variables. Other 7 models only on temporal test set (not extracted). Data from public sources (NASA POWER, EDGAR). | AF114: yes | AG114: Set A baseline (33 features, no temperature-derived predictors) | AI114: mean_of_folds | AJ114: 5 | AK114: 22 | AM114: site | AN114: temporal
A115: R0113 | B115: S0113 | C115: Chand | D115: 2026 | E115: 10.1038/s41598-026-57382-9 | F115: Scientific Reports | G115: Pakistan (Sindh) | H115: climate | I115: annual temperature anomaly per district (deg C) | J115: regression | K115: unknown | L115: 968 | N115: GBM | O115: leave_location_out | P115: random_kfold | T115: RMSE | U115: 0.139 | V115: 0.124 | Y115: no | Z115: 0.479 | AA115: Table 4 | AB115: no | AC115: yes | AD115: no | AE115: Article in Press (unedited). 22 districts x 44 years (1981-2024). Same GB hyperparameters in both CVs. Leave-one-district-out. Inconsistencies: Table 3/abstract LODO R2 0.914 +/- 0.098, text says random 5-fold R2 ~0.93; Table 4 values used. Temporal blocked (train <=2015) R2 0.445, RMSE 0.479 -> value_independent. Predictors include temporal trend/CO2 variables. Other 7 models only on temporal test set (not extracted). Data from public sources (NASA POWER, EDGAR). RMSE in deg C; spatial RMSE lower than random as reported. | AF115: yes | AG115: Set A baseline (33 features, no temperature-derived predictors) | AI115: mean_of_folds | AJ115: 5 | AK115: 22 | AM115: site | AN115: temporal
A116: R0136 | B116: S0136 | C116: Meyer | D116: 2020 | E116: arXiv:2005.07939 | F116: arXiv preprint (later Methods in Ecology and Evolution 2021) | G116: Europe (simulated) | H116: other | I116: simulated virtual-species-like continuous response (0-1) from WorldClim bioclim predictors | J116: regression | K116: clustered | L116: 500 | N116: RF | O116: leave_location_out | P116: random_kfold | T116: RMSE | U116: 0.021 | V116: 0.039 | Y116: no | AA116: p.7 text (case study) | AB116: no | AC116: yes | AD116: yes | AE116: Simulated response (single case-study simulation) - consider sensitivity analysis excluding simulated data. Clustered design: 10 points around each of 50 random locations; leave-cluster-out (50 clusters). True prediction RMSE within AOA: 0.043 (spatial-CV AOA) and 0.024 (random-CV AOA); no RMSE for whole area given for clustered design. Random design (50 points) had random CV only (R2 0.95, RMSE 0.08). Preprint: check published version (Meyer & Pebesma 2021, MEE, doi 10.1111/2041-210X.13650) for identical numbers (rule 11). | AF116: yes | AG116: clustered sampling design | AJ116: 10 | AK116: 50 | AM116: n_clusters | AN116: none | AO116: 10.1111/2041-210X.13650
A117: R0158 | B117: S0158a | C117: Salonen | D117: 2019 | E117: 10.1038/s41598-019-52293-4 | F117: Scientific Reports | G117: North America | H117: climate | I117: modern July mean temperature (deg C) at pollen sites (pollen-climate calibration) | J117: regression | K117: clustered | L117: 2254 | N117: other | O117: buffer_LOO | P117: LOO | Q117: 600000 | R117: 600000 | T117: RMSE | U117: 1.23 | V117: 1.73 | Y117: no | AA117: Fig. 3 (h=0, LOO); Table 3 (h-block) | AB117: yes | AC117: yes | AD117: yes | AE117: ETREES = extremely randomised trees. Predictors = pollen taxa percentages. RMSEP. Random = LOO (h=0) read from Fig. 3 by pixel-colour sampling (visual/pixel digitising); RF/BRT/ETREES lines share colour and overlap at h=0; common value assigned, precision ~+/-0.05 deg C. Spatial = h-block CV with h = variogram range of WA residuals (~600 km, orange bar in Fig. 3, value read from figure), exact value from Table 3. h series 0-1500 km by 100 km only in figure (not extracted). WA/WA-PLS not extracted (non-ML). Compilation database sites (clustered). | AF117: yes | AI117: pooled | AJ117: LOO | AK117: LOO (h-block) | AM117: km | AN117: none
A118: R0158 | B118: S0158a | C118: Salonen | D118: 2019 | E118: 10.1038/s41598-019-52293-4 | F118: Scientific Reports | G118: North America | H118: climate | I118: modern July mean temperature (deg C) at pollen sites (pollen-climate calibration) | J118: regression | K118: clustered | L118: 2254 | N118: GBM | O118: buffer_LOO | P118: LOO | Q118: 600000 | R118: 600000 | T118: RMSE | U118: 1.23 | V118: 1.75 | Y118: no | AA118: Fig. 3 (h=0, LOO); Table 3 (h-block) | AB118: yes | AC118: yes | AD118: yes | AE118: BRT. Predictors = pollen taxa percentages. RMSEP. Random = LOO (h=0) read from Fig. 3 by pixel-colour sampling (visual/pixel digitising); RF/BRT/ETREES lines share colour and overlap at h=0; common value assigned, precision ~+/-0.05 deg C. Spatial = h-block CV with h = variogram range of WA residuals (~600 km, orange bar in Fig. 3, value read from figure), exact value from Table 3. h series 0-1500 km by 100 km only in figure (not extracted). WA/WA-PLS not extracted (non-ML). Compilation database sites (clustered). | AF118: yes | AI118: pooled | AJ118: LOO | AK118: LOO (h-block) | AM118: km | AN118: none
A119: R0158 | B119: S0158a | C119: Salonen | D119: 2019 | E119: 10.1038/s41598-019-52293-4 | F119: Scientific Reports | G119: North America | H119: climate | I119: modern July mean temperature (deg C) at pollen sites (pollen-climate calibration) | J119: regression | K119: clustered | L119: 2254 | N119: RF | O119: buffer_LOO | P119: LOO | Q119: 600000 | R119: 600000 | T119: RMSE | U119: 1.23 | V119: 1.84 | Y119: no | AA119: Fig. 3 (h=0, LOO); Table 3 (h-block) | AB119: yes | AC119: yes | AD119: yes | AE119: RF. Predictors = pollen taxa percentages. RMSEP. Random = LOO (h=0) read from Fig. 3 by pixel-colour sampling (visual/pixel digitising); RF/BRT/ETREES lines share colour and overlap at h=0; common value assigned, precision ~+/-0.05 deg C. Spatial = h-block CV with h = variogram range of WA residuals (~600 km, orange bar in Fig. 3, value read from figure), exact value from Table 3. h series 0-1500 km by 100 km only in figure (not extracted). WA/WA-PLS not extracted (non-ML). Compilation database sites (clustered). | AF119: yes | AI119: pooled | AJ119: LOO | AK119: LOO (h-block) | AM119: km | AN119: none
A120: R0158 | B120: S0158a | C120: Salonen | D120: 2019 | E120: 10.1038/s41598-019-52293-4 | F120: Scientific Reports | G120: North America | H120: climate | I120: modern July mean temperature (deg C) at pollen sites (pollen-climate calibration) | J120: regression | K120: clustered | L120: 2254 | N120: kNN | O120: buffer_LOO | P120: LOO | Q120: 600000 | R120: 600000 | T120: RMSE | U120: 1.22 | V120: 1.89 | Y120: no | AA120: Fig. 3 (h=0, LOO); Table 3 (h-block) | AB120: yes | AC120: yes | AD120: yes | AE120: MAT = modern analogue technique (k-nearest-analogue). Predictors = pollen taxa percentages. RMSEP. Random = LOO (h=0) read from Fig. 3 by pixel-colour sampling (visual/pixel digitising); Precision ~+/-0.05 deg C. Spatial = h-block CV with h = variogram range of WA residuals (~600 km, orange bar in Fig. 3, value read from figure), exact value from Table 3. h series 0-1500 km by 100 km only in figure (not extracted). WA/WA-PLS not extracted (non-ML). Compilation database sites (clustered). | AF120: yes | AI120: pooled | AJ120: LOO | AK120: LOO (h-block) | AM120: km | AN120: none
A121: R0158 | B121: S0158a | C121: Salonen | D121: 2019 | E121: 10.1038/s41598-019-52293-4 | F121: Scientific Reports | G121: North America | H121: climate | I121: modern July mean temperature (deg C) at pollen sites (pollen-climate calibration) | J121: regression | K121: clustered | L121: 2254 | N121: ANN | O121: buffer_LOO | P121: LOO | Q121: 600000 | R121: 600000 | T121: RMSE | U121: 1.84 | V121: 2.29 | Y121: no | AA121: Fig. 3 (h=0, LOO); Table 3 (h-block) | AB121: yes | AC121: yes | AD121: yes | AE121: NNET = neural network. Predictors = pollen taxa percentages. RMSEP. Random = LOO (h=0) read from Fig. 3 by pixel-colour sampling (visual/pixel digitising); Precision ~+/-0.05 deg C. Spatial = h-block CV with h = variogram range of WA residuals (~600 km, orange bar in Fig. 3, value read from figure), exact value from Table 3. h series 0-1500 km by 100 km only in figure (not extracted). WA/WA-PLS not extracted (non-ML). Compilation database sites (clustered). | AF121: yes | AI121: pooled | AJ121: LOO | AK121: LOO (h-block) | AM121: km | AN121: none
A122: R0158 | B122: S0158a | C122: Salonen | D122: 2019 | E122: 10.1038/s41598-019-52293-4 | F122: Scientific Reports | G122: North America | H122: climate | I122: modern July mean temperature (deg C) at pollen sites (pollen-climate calibration) | J122: regression | K122: clustered | L122: 2254 | N122: ANN | O122: buffer_LOO | P122: LOO | Q122: 600000 | R122: 600000 | T122: RMSE | U122: 1.93 | V122: 2.37 | Y122: no | AA122: Fig. 3 (h=0, LOO); Table 3 (h-block) | AB122: yes | AC122: yes | AD122: yes | AE122: ELM = extreme learning machine. Predictors = pollen taxa percentages. RMSEP. Random = LOO (h=0) read from Fig. 3 by pixel-colour sampling (visual/pixel digitising); Precision ~+/-0.05 deg C. Spatial = h-block CV with h = variogram range of WA residuals (~600 km, orange bar in Fig. 3, value read from figure), exact value from Table 3. h series 0-1500 km by 100 km only in figure (not extracted). WA/WA-PLS not extracted (non-ML). Compilation database sites (clustered). | AF122: yes | AI122: pooled | AJ122: LOO | AK122: LOO (h-block) | AM122: km | AN122: none
A123: R0158 | B123: S0158a | C123: Salonen | D123: 2019 | E123: 10.1038/s41598-019-52293-4 | F123: Scientific Reports | G123: North America | H123: climate | I123: modern annual water balance (mm) at pollen sites (pollen-climate calibration) | J123: regression | K123: clustered | L123: 2254 | N123: GBM | O123: buffer_LOO | P123: LOO | Q123: 400000 | R123: 400000 | T123: RMSE | U123: 104 | V123: 161.55 | Y123: no | AA123: Fig. 3 (h=0, LOO); Table 3 (h-block) | AB123: yes | AC123: yes | AD123: yes | AE123: BRT. Predictors = pollen taxa percentages. RMSEP. Random = LOO (h=0) read from Fig. 3 by pixel-colour sampling (visual/pixel digitising); RF/BRT/ETREES lines share colour and overlap at h=0; common value assigned, precision ~+/-5 mm. Spatial = h-block CV with h = variogram range of WA residuals (~400 km, orange bar in Fig. 3, value read from figure), exact value from Table 3. h series 0-1500 km by 100 km only in figure (not extracted). WA/WA-PLS not extracted (non-ML). Compilation database sites (clustered). | AF123: yes | AI123: pooled | AJ123: LOO | AK123: LOO (h-block) | AM123: km | AN123: none
A124: R0158 | B124: S0158a | C124: Salonen | D124: 2019 | E124: 10.1038/s41598-019-52293-4 | F124: Scientific Reports | G124: North America | H124: climate | I124: modern annual water balance (mm) at pollen sites (pollen-climate calibration) | J124: regression | K124: clustered | L124: 2254 | N124: RF | O124: buffer_LOO | P124: LOO | Q124: 400000 | R124: 400000 | T124: RMSE | U124: 104 | V124: 161.92 | Y124: no | AA124: Fig. 3 (h=0, LOO); Table 3 (h-block) | AB124: yes | AC124: yes | AD124: yes | AE124: RF. Predictors = pollen taxa percentages. RMSEP. Random = LOO (h=0) read from Fig. 3 by pixel-colour sampling (visual/pixel digitising); RF/BRT/ETREES lines share colour and overlap at h=0; common value assigned, precision ~+/-5 mm. Spatial = h-block CV with h = variogram range of WA residuals (~400 km, orange bar in Fig. 3, value read from figure), exact value from Table 3. h series 0-1500 km by 100 km only in figure (not extracted). WA/WA-PLS not extracted (non-ML). Compilation database sites (clustered). | AF124: yes | AI124: pooled | AJ124: LOO | AK124: LOO (h-block) | AM124: km | AN124: none
A125: R0158 | B125: S0158a | C125: Salonen | D125: 2019 | E125: 10.1038/s41598-019-52293-4 | F125: Scientific Reports | G125: North America | H125: climate | I125: modern annual water balance (mm) at pollen sites (pollen-climate calibration) | J125: regression | K125: clustered | L125: 2254 | N125: other | O125: buffer_LOO | P125: LOO | Q125: 400000 | R125: 400000 | T125: RMSE | U125: 104 | V125: 162.14 | Y125: no | AA125: Fig. 3 (h=0, LOO); Table 3 (h-block) | AB125: yes | AC125: yes | AD125: yes | AE125: ETREES = extremely randomised trees. Predictors = pollen taxa percentages. RMSEP. Random = LOO (h=0) read from Fig. 3 by pixel-colour sampling (visual/pixel digitising); RF/BRT/ETREES lines share colour and overlap at h=0; common value assigned, precision ~+/-5 mm. Spatial = h-block CV with h = variogram range of WA residuals (~400 km, orange bar in Fig. 3, value read from figure), exact value from Table 3. h series 0-1500 km by 100 km only in figure (not extracted). WA/WA-PLS not extracted (non-ML). Compilation database sites (clustered). | AF125: yes | AI125: pooled | AJ125: LOO | AK125: LOO (h-block) | AM125: km | AN125: none
A126: R0158 | B126: S0158a | C126: Salonen | D126: 2019 | E126: 10.1038/s41598-019-52293-4 | F126: Scientific Reports | G126: North America | H126: climate | I126: modern annual water balance (mm) at pollen sites (pollen-climate calibration) | J126: regression | K126: clustered | L126: 2254 | N126: kNN | O126: buffer_LOO | P126: LOO | Q126: 400000 | R126: 400000 | T126: RMSE | U126: 109 | V126: 190.71 | Y126: no | AA126: Fig. 3 (h=0, LOO); Table 3 (h-block) | AB126: yes | AC126: yes | AD126: yes | AE126: MAT = modern analogue technique (k-nearest-analogue). Predictors = pollen taxa percentages. RMSEP. Random = LOO (h=0) read from Fig. 3 by pixel-colour sampling (visual/pixel digitising); Precision ~+/-5 mm. Spatial = h-block CV with h = variogram range of WA residuals (~400 km, orange bar in Fig. 3, value read from figure), exact value from Table 3. h series 0-1500 km by 100 km only in figure (not extracted). WA/WA-PLS not extracted (non-ML). Compilation database sites (clustered). | AF126: yes | AI126: pooled | AJ126: LOO | AK126: LOO (h-block) | AM126: km | AN126: none
A127: R0158 | B127: S0158a | C127: Salonen | D127: 2019 | E127: 10.1038/s41598-019-52293-4 | F127: Scientific Reports | G127: North America | H127: climate | I127: modern annual water balance (mm) at pollen sites (pollen-climate calibration) | J127: regression | K127: clustered | L127: 2254 | N127: ANN | O127: buffer_LOO | P127: LOO | Q127: 400000 | R127: 400000 | T127: RMSE | U127: 150 | V127: 194.05 | Y127: no | AA127: Fig. 3 (h=0, LOO); Table 3 (h-block) | AB127: yes | AC127: yes | AD127: yes | AE127: ELM = extreme learning machine. Predictors = pollen taxa percentages. RMSEP. Random = LOO (h=0) read from Fig. 3 by pixel-colour sampling (visual/pixel digitising); Precision ~+/-5 mm. Spatial = h-block CV with h = variogram range of WA residuals (~400 km, orange bar in Fig. 3, value read from figure), exact value from Table 3. h series 0-1500 km by 100 km only in figure (not extracted). WA/WA-PLS not extracted (non-ML). Compilation database sites (clustered). | AF127: yes | AI127: pooled | AJ127: LOO | AK127: LOO (h-block) | AM127: km | AN127: none
A128: R0158 | B128: S0158a | C128: Salonen | D128: 2019 | E128: 10.1038/s41598-019-52293-4 | F128: Scientific Reports | G128: North America | H128: climate | I128: modern annual water balance (mm) at pollen sites (pollen-climate calibration) | J128: regression | K128: clustered | L128: 2254 | N128: ANN | O128: buffer_LOO | P128: LOO | Q128: 400000 | R128: 400000 | T128: RMSE | U128: 195 | V128: 231.63 | Y128: no | AA128: Fig. 3 (h=0, LOO); Table 3 (h-block) | AB128: yes | AC128: yes | AD128: yes | AE128: NNET = neural network. Predictors = pollen taxa percentages. RMSEP. Random = LOO (h=0) read from Fig. 3 by pixel-colour sampling (visual/pixel digitising); Precision ~+/-5 mm. Spatial = h-block CV with h = variogram range of WA residuals (~400 km, orange bar in Fig. 3, value read from figure), exact value from Table 3. h series 0-1500 km by 100 km only in figure (not extracted). WA/WA-PLS not extracted (non-ML). Compilation database sites (clustered). | AF128: yes | AI128: pooled | AJ128: LOO | AK128: LOO (h-block) | AM128: km | AN128: none
... A140: R0158 | B140: S0158b | C140: Salonen | D140: 2019 | E140: 10.1038/s41598-019-52293-4 | F140: Scientific Reports | G140: Europe | H140: climate | I140: modern January mean temperature (deg C) at pollen sites (pollen-climate calibration) | J140: regression | K140: clustered | L140: 807 | N140: ANN | O140: buffer_LOO | P140: LOO | Q140: 300000 | R140: 300000 | T140: RMSE | U140: 2.76 | V140: 4.03 | Y140: no | AA140: Fig. 3 (h=0, LOO); Table 3 (h-block) | AB140: yes | AC140: yes | AD140: yes | AE140: NNET = neural network. Predictors = pollen taxa percentages. RMSEP. Random = LOO (h=0) read from Fig. 3 by pixel-colour sampling (visual/pixel digitising); Precision ~+/-0.05 deg C. Spatial = h-block CV with h = variogram range of WA residuals (~300 km, orange bar in Fig. 3, value read from figure), exact value from Table 3. h series 0-1500 km by 100 km only in figure (not extracted). WA/WA-PLS not extracted (non-ML). Compilation database sites (clustered). | AF140: yes | AI140: pooled | AJ140: LOO | AK140: LOO (h-block) | AM140: km | AN140: none
A141: R0200 | B141: S0200 | C141: Stock | D141: 2020 | E141: 10.3389/fmars.2020.00599 | F141: Frontiers in Marine Science | G141: Global open ocean | H141: other | I141: relative concentration of 19'-butanoyloxyfucoxanthin (proportion of total diagnostic pigments) | J141: regression | K141: clustered | L141: 446 | N141: RF | O141: block | P141: random_kfold | T141: MAE | U141: 0.031 | V141: 0.038 | Y141: no | AA141: Table 4; Table 2 | AB141: no | AC141: on_request | AD141: yes | AE141: Ocean phytoplankton pigment (domain other). "Best algorithm" MAE under each CV (Table 4); model/variant here = best under spatial block CV (Ecological (RF), Table 2) - best model under 5-fold CV is in Suppl. Table S4 and may differ (verify). MAE as % of null model: 5-fold 68.2, spatial 83.8. Nested (double) CV in both schemes with declustering weights. Manually defined large ocean blocks (8-94 obs each; number of blocks not stated in text). In situ HPLC data clustered along cruise tracks. Splines/polynomials (abundance-based) not extracted. | AF141: yes | AG141: Ecological (RF) | AJ141: 5 | AN141: none
A142: R0200 | B142: S0200 | C142: Stock | D142: 2020 | E142: 10.3389/fmars.2020.00599 | F142: Frontiers in Marine Science | G142: Global open ocean | H142: other | I142: relative concentration of 19'-hexanoyloxyfucoxanthin (proportion of total diagnostic pigments) | J142: regression | K142: clustered | L142: 446 | N142: GBM | O142: block | P142: random_kfold | T142: MAE | U142: 0.070 | V142: 0.092 | Y142: no | AA142: Table 4; Table 2 | AB142: no | AC142: on_request | AD142: yes | AE142: Ocean phytoplankton pigment (domain other). "Best algorithm" MAE under each CV (Table 4); model/variant here = best under spatial block CV (Ecological (BRT), Table 2) - best model under 5-fold CV is in Suppl. Table S4 and may differ (verify). MAE as % of null model: 5-fold 67.7, spatial 87.5. Nested (double) CV in both schemes with declustering weights. Manually defined large ocean blocks (8-94 obs each; number of blocks not stated in text). In situ HPLC data clustered along cruise tracks. Splines/polynomials (abundance-based) not extracted. | AF142: yes | AG142: Ecological (BRT) | AJ142: 5 | AN142: none
A143: R0200 | B143: S0200 | C143: Stock | D143: 2020 | E143: 10.3389/fmars.2020.00599 | F143: Frontiers in Marine Science | G143: Global open ocean | H143: other | I143: relative concentration of alloxanthin (proportion of total diagnostic pigments) | J143: regression | K143: clustered | L143: 446 | N143: GBM | O143: block | P143: random_kfold | T143: MAE | U143: 0.019 | V143: 0.020 | Y143: no | AA143: Table 4; Table 2 | AB143: no | AC143: on_request | AD143: yes | AE143: Ocean phytoplankton pigment (domain other). "Best algorithm" MAE under each CV (Table 4); model/variant here = best under spatial block CV (Spectral (BRT), Table 2) - best model under 5-fold CV is in Suppl. Table S4 and may differ (verify). MAE as % of null model: 5-fold 75.9, spatial 99.7. Nested (double) CV in both schemes with declustering weights. Manually defined large ocean blocks (8-94 obs each; number of blocks not stated in text). In situ HPLC data clustered along cruise tracks. Splines/polynomials (abundance-based) not extracted. | AF143: yes | AG143: Spectral (BRT) | AJ143: 5 | AN143: none
A144: R0200 | B144: S0200 | C144: Stock | D144: 2020 | E144: 10.3389/fmars.2020.00599 | F144: Frontiers in Marine Science | G144: Global open ocean | H144: other | I144: relative concentration of fucoxanthin (proportion of total diagnostic pigments) | J144: regression | K144: clustered | L144: 446 | N144: GBM | O144: block | P144: random_kfold | T144: MAE | U144: 0.063 | V144: 0.060 | Y144: no | AA144: Table 4; Table 2 | AB144: no | AC144: on_request | AD144: yes | AE144: Ocean phytoplankton pigment (domain other). "Best algorithm" MAE under each CV (Table 4); model/variant here = best under spatial block CV (Ecological (BRT), Table 2) - best model under 5-fold CV is in Suppl. Table S4 and may differ (verify). MAE as % of null model: 5-fold 41.7, spatial 45.5. Nested (double) CV in both schemes with declustering weights. Manually defined large ocean blocks (8-94 obs each; number of blocks not stated in text). In situ HPLC data clustered along cruise tracks. Splines/polynomials (abundance-based) not extracted. | AF144: yes | AG144: Ecological (BRT) | AJ144: 5 | AN144: none
A145: R0200 | B145: S0200 | C145: Stock | D145: 2020 | E145: 10.3389/fmars.2020.00599 | F145: Frontiers in Marine Science | G145: Global open ocean | H145: other | I145: relative concentration of peridinin (proportion of total diagnostic pigments) | J145: regression | K145: clustered | L145: 446 | N145: RF | O145: block | P145: random_kfold | T145: MAE | U145: 0.017 | V145: 0.019 | Y145: no | AA145: Table 4; Table 2 | AB145: no | AC145: on_request | AD145: yes | AE145: Ocean phytoplankton pigment (domain other). "Best algorithm" MAE under each CV (Table 4); model/variant here = best under spatial block CV (Spectral (RF), Table 2) - best model under 5-fold CV is in Suppl. Table S4 and may differ (verify). MAE as % of null model: 5-fold 79.0, spatial 93.6. Nested (double) CV in both schemes with declustering weights. Manually defined large ocean blocks (8-94 obs each; number of blocks not stated in text). In situ HPLC data clustered along cruise tracks. Splines/polynomials (abundance-based) not extracted. | AF145: yes | AG145: Spectral (RF) | AJ145: 5 | AN145: none
A146: R0200 | B146: S0200 | C146: Stock | D146: 2020 | E146: 10.3389/fmars.2020.00599 | F146: Frontiers in Marine Science | G146: Global open ocean | H146: other | I146: relative concentration of zeaxanthin (proportion of total diagnostic pigments) | J146: regression | K146: clustered | L146: 446 | N146: GBM | O146: block | P146: random_kfold | T146: MAE | U146: 0.083 | V146: 0.130 | Y146: no | AA146: Table 4; Table 2 | AB146: no | AC146: on_request | AD146: yes | AE146: Ocean phytoplankton pigment (domain other). "Best algorithm" MAE under each CV (Table 4); model/variant here = best under spatial block CV (Ecological (BRT), Table 2) - best model under 5-fold CV is in Suppl. Table S4 and may differ (verify). MAE as % of null model: 5-fold 37.2, spatial 57.8. Nested (double) CV in both schemes with declustering weights. Manually defined large ocean blocks (8-94 obs each; number of blocks not stated in text). In situ HPLC data clustered along cruise tracks. Splines/polynomials (abundance-based) not extracted. | AF146: yes | AG146: Ecological (BRT) | AJ146: 5 | AN146: none
A147: R0200 | B147: S0200 | C147: Stock | D147: 2020 | E147: 10.3389/fmars.2020.00599 | F147: Frontiers in Marine Science | G147: Global open ocean | H147: other | I147: relative concentration of divinyl chlorophyll b (proportion of total diagnostic pigments) | J147: regression | K147: clustered | L147: 446 | N147: RF | O147: block | P147: random_kfold | T147: MAE | U147: 0.012 | V147: 0.016 | Y147: no | AA147: Table 4; Table 2 | AB147: no | AC147: on_request | AD147: yes | AE147: Ocean phytoplankton pigment (domain other). "Best algorithm" MAE under each CV (Table 4); model/variant here = best under spatial block CV (Ecological (RF), Table 2) - best model under 5-fold CV is in Suppl. Table S4 and may differ (verify). MAE as % of null model: 5-fold 59.6, spatial 80.7. Nested (double) CV in both schemes with declustering weights. Manually defined large ocean blocks (8-94 obs each; number of blocks not stated in text). In situ HPLC data clustered along cruise tracks. Splines/polynomials (abundance-based) not extracted. | AF147: yes | AG147: Ecological (RF) | AJ147: 5 | AN147: none
A148: R0200 | B148: S0200 | C148: Stock | D148: 2020 | E148: 10.3389/fmars.2020.00599 | F148: Frontiers in Marine Science | G148: Global open ocean | H148: other | I148: relative concentration of total chlorophyll b (proportion of total diagnostic pigments) | J148: regression | K148: clustered | L148: 446 | N148: GBM | O148: block | P148: random_kfold | T148: MAE | U148: 0.052 | V148: 0.057 | Y148: no | AA148: Table 4; Table 2 | AB148: no | AC148: on_request | AD148: yes | AE148: Ocean phytoplankton pigment (domain other). "Best algorithm" MAE under each CV (Table 4); model/variant here = best under spatial block CV (Ecological (BRT), Table 2) - best model under 5-fold CV is in Suppl. Table S4 and may differ (verify). MAE as % of null model: 5-fold 77.9, spatial 92.3. Nested (double) CV in both schemes with declustering weights. Manually defined large ocean blocks (8-94 obs each; number of blocks not stated in text). In situ HPLC data clustered along cruise tracks. Splines/polynomials (abundance-based) not extracted. | AF148: yes | AG148: Ecological (BRT) | AJ148: 5 | AN148: none
A149: R0201 | B149: S0201 | C149: Ghahremanloo | D149: 2023 | E149: 10.1029/2022JD037010 | F149: Journal of Geophysical Research: Atmospheres | G149: USA (contiguous US) | H149: climate | I149: daily surface NO2 concentration (ppb) at EPA stations | J149: regression | K149: clustered | N149: CNN | O149: leave_location_out | P149: random_kfold | S149: 10 random / 10 spatial (station-grouped) | T149: RMSE | U149: 1.97 | V149: 3.93 | Y149: no | AA149: Table 1 | AB149: no | AC149: yes | AD149: no | AE149: RMSE in ppb. PCNN-DNN (DepthWise partial-conv CNN imputation + DNN), annual model 2005; one row per year (within-study replicates, aggregate in analysis). 10-CV splits station-days randomly; spatial-CV splits by ground station (10-fold). Correlation R (not extracted as allowed metric): random 0.975 vs spatial 0.91. Station count not reported. Urban-train/rural-test experiment in Table S4 (supplement) not extracted. | AF149: yes | AG149: year 2005 | AI149: mean_of_folds | AJ149: 10 | AK149: 10 | AM149: site
A150: R0201 | B150: S0201 | C150: Ghahremanloo | D150: 2023 | E150: 10.1029/2022JD037010 | F150: Journal of Geophysical Research: Atmospheres | G150: USA (contiguous US) | H150: climate | I150: daily surface NO2 concentration (ppb) at EPA stations | J150: regression | K150: clustered | N150: CNN | O150: leave_location_out | P150: random_kfold | S150: 10 random / 10 spatial (station-grouped) | T150: MAE | U150: 1.38 | V150: 2.7 | Y150: no | AA150: Table 1 | AB150: no | AC150: yes | AD150: no | AE150: MAB (mean absolute bias = MAE) in ppb. PCNN-DNN (DepthWise partial-conv CNN imputation + DNN), annual model 2005; one row per year (within-study replicates, aggregate in analysis). 10-CV splits station-days randomly; spatial-CV splits by ground station (10-fold). Correlation R (not extracted as allowed metric): random 0.975 vs spatial 0.91. Station count not reported. Urban-train/rural-test experiment in Table S4 (supplement) not extracted. | AF150: yes | AG150: year 2005 | AI150: mean_of_folds | AJ150: 10 | AK150: 10 | AM150: site
A151: R0201 | B151: S0201 | C151: Ghahremanloo | D151: 2023 | E151: 10.1029/2022JD037010 | F151: Journal of Geophysical Research: Atmospheres | G151: USA (contiguous US) | H151: climate | I151: daily surface NO2 concentration (ppb) at EPA stations | J151: regression | K151: clustered | N151: CNN | O151: leave_location_out | P151: random_kfold | S151: 10 random / 10 spatial (station-grouped) | T151: RMSE | U151: 1.87 | V151: 3.46 | Y151: no | AA151: Table 1 | AB151: no | AC151: yes | AD151: no | AE151: RMSE in ppb. PCNN-DNN (DepthWise partial-conv CNN imputation + DNN), annual model 2006; one row per year (within-study replicates, aggregate in analysis). 10-CV splits station-days randomly; spatial-CV splits by ground station (10-fold). Correlation R (not extracted as allowed metric): random 0.976 vs spatial 0.93. Station count not reported. Urban-train/rural-test experiment in Table S4 (supplement) not extracted. | AF151: yes | AG151: year 2006 | AI151: mean_of_folds | AJ151: 10 | AK151: 10 | AM151: site
A152: R0201 | B152: S0201 | C152: Ghahremanloo | D152: 2023 | E152: 10.1029/2022JD037010 | F152: Journal of Geophysical Research: Atmospheres | G152: USA (contiguous US) | H152: climate | I152: daily surface NO2 concentration (ppb) at EPA stations | J152: regression | K152: clustered | N152: CNN | O152: leave_location_out | P152: random_kfold | S152: 10 random / 10 spatial (station-grouped) | T152: MAE | U152: 1.28 | V152: 2.42 | Y152: no | AA152: Table 1 | AB152: no | AC152: yes | AD152: no | AE152: MAB (mean absolute bias = MAE) in ppb. PCNN-DNN (DepthWise partial-conv CNN imputation + DNN), annual model 2006; one row per year (within-study replicates, aggregate in analysis). 10-CV splits station-days randomly; spatial-CV splits by ground station (10-fold). Correlation R (not extracted as allowed metric): random 0.976 vs spatial 0.93. Station count not reported. Urban-train/rural-test experiment in Table S4 (supplement) not extracted. | AF152: yes | AG152: year 2006 | AI152: mean_of_folds | AJ152: 10 | AK152: 10 | AM152: site
A153: R0201 | B153: S0201 | C153: Ghahremanloo | D153: 2023 | E153: 10.1029/2022JD037010 | F153: Journal of Geophysical Research: Atmospheres | G153: USA (contiguous US) | H153: climate | I153: daily surface NO2 concentration (ppb) at EPA stations | J153: regression | K153: clustered | N153: CNN | O153: leave_location_out | P153: random_kfold | S153: 10 random / 10 spatial (station-grouped) | T153: RMSE | U153: 1.78 | V153: 3.43 | Y153: no | AA153: Table 1 | AB153: no | AC153: yes | AD153: no | AE153: RMSE in ppb. PCNN-DNN (DepthWise partial-conv CNN imputation + DNN), annual model 2007; one row per year (within-study replicates, aggregate in analysis). 10-CV splits station-days randomly; spatial-CV splits by ground station (10-fold). Correlation R (not extracted as allowed metric): random 0.978 vs spatial 0.93. Station count not reported. Urban-train/rural-test experiment in Table S4 (supplement) not extracted. | AF153: yes | AG153: year 2007 | AI153: mean_of_folds | AJ153: 10 | AK153: 10 | AM153: site
A154: R0201 | B154: S0201 | C154: Ghahremanloo | D154: 2023 | E154: 10.1029/2022JD037010 | F154: Journal of Geophysical Research: Atmospheres | G154: USA (contiguous US) | H154: climate | I154: daily surface NO2 concentration (ppb) at EPA stations | J154: regression | K154: clustered | N154: CNN | O154: leave_location_out | P154: random_kfold | S154: 10 random / 10 spatial (station-grouped) | T154: MAE | U154: 1.22 | V154: 2.34 | Y154: no | AA154: Table 1 | AB154: no | AC154: yes | AD154: no | AE154: MAB (mean absolute bias = MAE) in ppb. PCNN-DNN (DepthWise partial-conv CNN imputation + DNN), annual model 2007; one row per year (within-study replicates, aggregate in analysis). 10-CV splits station-days randomly; spatial-CV splits by ground station (10-fold). Correlation R (not extracted as allowed metric): random 0.978 vs spatial 0.93. Station count not reported. Urban-train/rural-test experiment in Table S4 (supplement) not extracted. | AF154: yes | AG154: year 2007 | AI154: mean_of_folds | AJ154: 10 | AK154: 10 | AM154: site
A155: R0201 | B155: S0201 | C155: Ghahremanloo | D155: 2023 | E155: 10.1029/2022JD037010 | F155: Journal of Geophysical Research: Atmospheres | G155: USA (contiguous US) | H155: climate | I155: daily surface NO2 concentration (ppb) at EPA stations | J155: regression | K155: clustered | N155: CNN | O155: leave_location_out | P155: random_kfold | S155: 10 random / 10 spatial (station-grouped) | T155: RMSE | U155: 1.79 | V155: 3.61 | Y155: no | AA155: Table 1 | AB155: no | AC155: yes | AD155: no | AE155: RMSE in ppb. PCNN-DNN (DepthWise partial-conv CNN imputation + DNN), annual model 2008; one row per year (within-study replicates, aggregate in analysis). 10-CV splits station-days randomly; spatial-CV splits by ground station (10-fold). Correlation R (not extracted as allowed metric): random 0.978 vs spatial 0.92. Station count not reported. Urban-train/rural-test experiment in Table S4 (supplement) not extracted. | AF155: yes | AG155: year 2008 | AI155: mean_of_folds | AJ155: 10 | AK155: 10 | AM155: site
A156: R0201 | B156: S0201 | C156: Ghahremanloo | D156: 2023 | E156: 10.1029/2022JD037010 | F156: Journal of Geophysical Research: Atmospheres | G156: USA (contiguous US) | H156: climate | I156: daily surface NO2 concentration (ppb) at EPA stations | J156: regression | K156: clustered | N156: CNN | O156: leave_location_out | P156: random_kfold | S156: 10 random / 10 spatial (station-grouped) | T156: MAE | U156: 1.22 | V156: 2.35 | Y156: no | AA156: Table 1 | AB156: no | AC156: yes | AD156: no | AE156: MAB (mean absolute bias = MAE) in ppb. PCNN-DNN (DepthWise partial-conv CNN imputation + DNN), annual model 2008; one row per year (within-study replicates, aggregate in analysis). 10-CV splits station-days randomly; spatial-CV splits by ground station (10-fold). Correlation R (not extracted as allowed metric): random 0.978 vs spatial 0.92. Station count not reported. Urban-train/rural-test experiment in Table S4 (supplement) not extracted. | AF156: yes | AG156: year 2008 | AI156: mean_of_folds | AJ156: 10 | AK156: 10 | AM156: site
A157: R0201 | B157: S0201 | C157: Ghahremanloo | D157: 2023 | E157: 10.1029/2022JD037010 | F157: Journal of Geophysical Research: Atmospheres | G157: USA (contiguous US) | H157: climate | I157: daily surface NO2 concentration (ppb) at EPA stations | J157: regression | K157: clustered | N157: CNN | O157: leave_location_out | P157: random_kfold | S157: 10 random / 10 spatial (station-grouped) | T157: RMSE | U157: 1.73 | V157: 3.45 | Y157: no | AA157: Table 1 | AB157: no | AC157: yes | AD157: no | AE157: RMSE in ppb. PCNN-DNN (DepthWise partial-conv CNN imputation + DNN), annual model 2009; one row per year (within-study replicates, aggregate in analysis). 10-CV splits station-days randomly; spatial-CV splits by ground station (10-fold). Correlation R (not extracted as allowed metric): random 0.977 vs spatial 0.91. Station count not reported. Urban-train/rural-test experiment in Table S4 (supplement) not extracted. | AF157: yes | AG157: year 2009 | AI157: mean_of_folds | AJ157: 10 | AK157: 10 | AM157: site
A158: R0201 | B158: S0201 | C158: Ghahremanloo | D158: 2023 | E158: 10.1029/2022JD037010 | F158: Journal of Geophysical Research: Atmospheres | G158: USA (contiguous US) | H158: climate | I158: daily surface NO2 concentration (ppb) at EPA stations | J158: regression | K158: clustered | N158: CNN | O158: leave_location_out | P158: random_kfold | S158: 10 random / 10 spatial (station-grouped) | T158: MAE | U158: 1.16 | V158: 2.27 | Y158: no | AA158: Table 1 | AB158: no | AC158: yes | AD158: no | AE158: MAB (mean absolute bias = MAE) in ppb. PCNN-DNN (DepthWise partial-conv CNN imputation + DNN), annual model 2009; one row per year (within-study replicates, aggregate in analysis). 10-CV splits station-days randomly; spatial-CV splits by ground station (10-fold). Correlation R (not extracted as allowed metric): random 0.977 vs spatial 0.91. Station count not reported. Urban-train/rural-test experiment in Table S4 (supplement) not extracted. | AF158: yes | AG158: year 2009 | AI158: mean_of_folds | AJ158: 10 | AK158: 10 | AM158: site
A159: R0201 | B159: S0201 | C159: Ghahremanloo | D159: 2023 | E159: 10.1029/2022JD037010 | F159: Journal of Geophysical Research: Atmospheres | G159: USA (contiguous US) | H159: climate | I159: daily surface NO2 concentration (ppb) at EPA stations | J159: regression | K159: clustered | N159: CNN | O159: leave_location_out | P159: random_kfold | S159: 10 random / 10 spatial (station-grouped) | T159: RMSE | U159: 1.6 | V159: 2.98 | Y159: no | AA159: Table 1 | AB159: no | AC159: yes | AD159: no | AE159: RMSE in ppb. PCNN-DNN (DepthWise partial-conv CNN imputation + DNN), annual model 2010; one row per year (within-study replicates, aggregate in analysis). 10-CV splits station-days randomly; spatial-CV splits by ground station (10-fold). Correlation R (not extracted as allowed metric): random 0.978 vs spatial 0.93. Station count not reported. Urban-train/rural-test experiment in Table S4 (supplement) not extracted. | AF159: yes | AG159: year 2010 | AI159: mean_of_folds | AJ159: 10 | AK159: 10 | AM159: site
A160: R0201 | B160: S0201 | C160: Ghahremanloo | D160: 2023 | E160: 10.1029/2022JD037010 | F160: Journal of Geophysical Research: Atmospheres | G160: USA (contiguous US) | H160: climate | I160: daily surface NO2 concentration (ppb) at EPA stations | J160: regression | K160: clustered | N160: CNN | O160: leave_location_out | P160: random_kfold | S160: 10 random / 10 spatial (station-grouped) | T160: MAE | U160: 1.08 | V160: 2.05 | Y160: no | AA160: Table 1 | AB160: no | AC160: yes | AD160: no | AE160: MAB (mean absolute bias = MAE) in ppb. PCNN-DNN (DepthWise partial-conv CNN imputation + DNN), annual model 2010; one row per year (within-study replicates, aggregate in analysis). 10-CV splits station-days randomly; spatial-CV splits by ground station (10-fold). Correlation R (not extracted as allowed metric): random 0.978 vs spatial 0.93. Station count not reported. Urban-train/rural-test experiment in Table S4 (supplement) not extracted. | AF160: yes | AG160: year 2010 | AI160: mean_of_folds | AJ160: 10 | AK160: 10 | AM160: site
... A178: R0201 | B178: S0201 | C178: Ghahremanloo | D178: 2023 | E178: 10.1029/2022JD037010 | F178: Journal of Geophysical Research: Atmospheres | G178: USA (contiguous US) | H178: climate | I178: daily surface NO2 concentration (ppb) at EPA stations | J178: regression | K178: clustered | N178: CNN | O178: leave_location_out | P178: random_kfold | S178: 10 random / 10 spatial (station-grouped) | T178: MAE | U178: 0.99 | V178: 2.01 | Y178: no | AA178: Table 1 | AB178: no | AC178: yes | AD178: no | AE178: MAB (mean absolute bias = MAE) in ppb. PCNN-DNN (DepthWise partial-conv CNN imputation + DNN), annual model 2019; one row per year (within-study replicates, aggregate in analysis). 10-CV splits station-days randomly; spatial-CV splits by ground station (10-fold). Correlation R (not extracted as allowed metric): random 0.975 vs spatial 0.91. Station count not reported. Urban-train/rural-test experiment in Table S4 (supplement) not extracted. | AF178: yes | AG178: year 2019 | AI178: mean_of_folds | AJ178: 10 | AK178: 10 | AM178: site
A179: R0208 | B179: S0208a | C179: Brenning | D179: 2021 | E179: arXiv:2111.08478 | F179: arXiv preprint (later International Journal of Geographical Information Science 2023) | G179: Netherlands (Meuse floodplain) | H179: soil | I179: log topsoil zinc concentration (log-ppm) | J179: regression | K179: unknown | L179: 155 | M179: 4 | N179: RF | O179: spatial_kfold_cluster | P179: repeated_kfold | R179: 897 | S179: 10 (x50 repetitions) | T179: RMSE | U179: 0.14 | V179: 0.167 | Y179: no | AA179: Fig. 2 (right panel) | AB179: yes | AC179: yes | AD179: yes | AE179: Both values digitised visually from Fig. 2 point estimates (zoomed render, precision ~+/-0.003). Spatial = k-means (10 clusters) coordinate partitioning; mean prediction distance 298 m spatial vs 116 m random. LOO-CV RMSE ~0.136 (random_cv_alt). Predictors elev, sqrt(dist), x, y. Sampling nearly random/uniform (author description) but design not stated. OK/KED/MLR/GWR/NN and OK-RF hybrid not extracted. Values from arXiv preprint; check published IJGIS version. | AF179: yes | AH179: LOO | AJ179: 10 | AK179: 10 | AL179: 50 | AM179: n_clusters | AO179: 10.1080/13658816.2022.2131789
A180: R0208 | B180: S0208b | C180: Brenning | D180: 2021 | E180: arXiv:2111.08478 | F180: arXiv preprint (later International Journal of Geographical Information Science 2023) | G180: Chile (Maipo, central Chile) | H180: land_cover | I180: fruit-tree crop type (4 classes) from Landsat time series | J180: classification | K180: unknown | L180: 100 fields per repetition (sampled from 400 fields / 7713 grid cells) | N180: RF | O180: leave_location_out | P180: repeated_kfold | S180: 10 random / field-level | T180: accuracy | U180: 0.997 | V180: 0.83 | Y180: no | AA180: Fig. 4 | AB180: yes | AD180: yes | AE180: Accuracy = 1 - error rate digitised visually from Fig. 4 (RF triangles; precision ~+/-0.005): random CV error ~0.003, field-level CV ~0.170. LOO and random CV visually indistinguishable. Field-level CV mean prediction distance 871 m (closest to application 831 m; authors favour it) -> primary. LDA and NN-LDA not extracted. 100 fields (25 per crop) resampled repeatedly, results averaged. Preprint values. | AF180: yes | AG180: field-level spatial CV | AH180: LOO | AJ180: 10 | AM180: site | AO180: 10.1080/13658816.2022.2131789
A181: R0208 | B181: S0208b | C181: Brenning | D181: 2021 | E181: arXiv:2111.08478 | F181: arXiv preprint (later International Journal of Geographical Information Science 2023) | G181: Chile (Maipo, central Chile) | H181: land_cover | I181: fruit-tree crop type (4 classes) from Landsat time series | J181: classification | K181: unknown | L181: 100 fields per repetition (sampled from 400 fields / 7713 grid cells) | N181: RF | O181: spatial_kfold_cluster | P181: repeated_kfold | S181: 10 random / 10 k-means spatial | T181: accuracy | U181: 0.997 | V181: 0.801 | Y181: no | AA181: Fig. 4 | AB181: yes | AD181: yes | AE181: Accuracy = 1 - error rate digitised visually from Fig. 4: random ~0.003 error vs k-means spatial CV ~0.199 error. Mean prediction distance 6664 m. Repetition count assumed as in Meuse case (not explicit for Maipo). Preprint values. | AF181: no | AG181: k-means spatial CV (10 clusters) | AH181: LOO | AJ181: 10 | AK181: 10 | AM181: n_clusters | AO181: 10.1080/13658816.2022.2131789
A182: R0232 | B182: S0232a | C182: Zandler | D182: 2022 | E182: 10.3389/fenvs.2022.684589 | F182: Frontiers in Environmental Science | G182: Afghanistan (Wakhan, Pamir) | H182: land_cover | I182: land cover / vegetation communities (9 classes), Sentinel-2 | J182: classification | K182: unknown | L182: 423 | N182: RF | O182: spatial_kfold_cluster | P182: repeated_kfold | S182: 10 (x100 repetitions) | T182: accuracy | U182: 0.91 | V182: 0.81 | Y182: no | AA182: Table 2 | AB182: no | AC182: on_request | AD182: no | AE182: Overall accuracy. Model 2016 incl. snow (NDSI) predictors; "no SCV" row assumed to be the same full model under non-spatial CV (not stated explicitly). Spatial = sperrorest k-means 10-fold x100; non-spatial presumably same repetitions. "no NDSI" variant has no non-spatial counterpart (not extracted). Field plots: preferential stand selection + probability transects + digitised water/snow plots (mixed design). | AF182: yes | AG182: year 2016 | AJ182: 10 | AK182: 10 | AL182: 100 | AM182: n_clusters
